Workbook

Sheet 01 README
A1: BUILDING RATE ANALYSIS MASTER DATABASE – FINAL (Pakistan, city-selectable)
A2: Doc: RA_Master_Pakistan_FINAL_Rev07_2026-09-27
A4: Purpose | B4: Transparent, formula-driven rate library for BOQ, tender checking, VO pricing and cost planning. Every rate is built A-material + wastage + labour + plant + transport → direct cost → OH → profit → optional tax.
A5: Scope – this issue | B5: FINAL MERGED Rev06 (rates filled from GRN register, Punjab MRS 2026, dashboard research): every trade + depth variants + 11-city selector + 16 RFQ sheet (fill quotes once, whole library updates). Rev03 added Phases 4–9: prelims, earthwork, doors, windows, joinery, façade, external works, plumbing, fire fighting, electrical, ELV, life safety, HVAC, lifts, misc. Vendor/system items carry full component structure with red inputs for quotes. Phase 3 (Rev02) added: porcelain/ceramic floor & wall tiling, marble flooring, gypsum ceilings (full component build-up), emulsion & weather-shield paint systems. Phase 2 (Rev01) added: formwork (slab, beam, column, wall), block masonry 8"/6"/4", brick 4.5", screeds 1.5"/2"/3", waterproofing (torch-on membrane, cementitious, DPC). Phase 1: 15 lab mix-design concretes transcribed from the user's 8 lab sheets (1000–6000 PSI), 3 nominal concretes, rebar, 9" brick masonry, 2 plaster items. Trade list (12) carries the full coding for all trades; items are queued, not invented.
A6: Rate basis | B6: City selector in 10 ASSUMPTIONS (default Lahore). Lahore: Sep-2026 market indications from dated web sources (09). Conflicting sources shown as Low/High in 05; working value flagged yellow.
A7: Units | B7: cft, Sft, kg, Nos, bag, litre, day, PKR. Lab batch weights converted via Batch_cft = 35.315.
A8: Colour key | B8: Blue = input · Green = formula · Yellow = assumption / dated market indication · Red = NO dated source – blank until filled · Grey = totals.
A9: How to update | B9: 1) Enter new rates in 05/06/07 col 'Base Rate' with date & source ID. 2) Change globals in 10. 3) Check 14 QC = OK. Never type into green cells.
A10: Reprice a mix | B10: Change 'Priced as' material code or batch kg in 15; analysis in 04 follows automatically.
A11: Add an item | B11: Copy an analysis block in 04, change code/resources, add a row in 03 pointing to the new block's summary cells.
A12: Critical inputs still blank | B12: Admixture, water, binding wire, Zinda Pir sand, nails, release oil, membrane, primer, bitumen, LPG, cementitious slurry, all plant/prop hire; timber rate OLD (Feb-2025) – all rate statuses show INCOMPLETE until entered.
A13: Not included | B13: Formwork, pumping floor premium, cradle/scaffold for elevations, taxes (toggle), escalation.
A14: Rev07 (2026-09-27) | B14: Reconciled with the SAJ QSCOST dashboard Rate Analysis library: one dated rate per shared resource (cement 1,575, Lawrencepur 240, Sargodha 185, Margalla 180, A-brick 17.5, blocks 140/165, sub-base 100, plaster mason 2,150, tile fixer 2,500, painter 2,100); crew outputs checked against Punjab MRS 2026 labour shares, MAK installation rates and SRC-06 piece rates (13, columns H–S); 35 new analyses; 17 Missing Items Register; 18 Dashboard Reconciliation; 19 Revision Log.
A15: Dashboard link | B15: Every item in 03 is in the dashboard Item Library under the same code, with the same resources and adjusted quantities (Rate Analysis → Item Library, category filter). Shared resources use the dashboard Rate Database line named in 18.

Sheet 02 DASHBOARD
A1: 02 · DASHBOARD
A2: Rate basis: Lahore · Rev07 reconciled with dashboard · Last updated 2026-09-27
A4: Metric | B4: Value
A5: Total rate analyses | B5: =COUNTA('03 MASTER RATE LIBRARY'!A5:A400) -> 160
A6: Complete (no blank inputs) | B6: =COUNTIF('03 MASTER RATE LIBRARY'!W5:W400,0) -> 126
A7: Incomplete (red inputs pending) | B7: =COUNTIF('03 MASTER RATE LIBRARY'!W5:W400,">0") -> 34
A8: Unit = cft | B8: =COUNTIF('03 MASTER RATE LIBRARY'!G5:G400,"cft") -> 39
A9: Unit = Sft | B9: =COUNTIF('03 MASTER RATE LIBRARY'!G5:G400,"Sft") -> 60
A10: Unit = kg | B10: =COUNTIF('03 MASTER RATE LIBRARY'!G5:G400,"kg") -> 1
A11: Selected city | B11: =City -> Lahore
A12: Items fully priced for selected city | B12: =COUNTIF('03 MASTER RATE LIBRARY'!W5:W400,0) -> 126
A13: Red inputs listed in RFQ | B13: =COUNTA('16 VENDOR ENQUIRY (RFQ)'!B5:B500) -> 79
A14: RFQ lines quoted | B14: =COUNT('16 VENDOR ENQUIRY (RFQ)'!H5:H500) -> 0
A15: Sources registered | B15: =COUNTA('09 SOURCE REGISTER'!A5:A50) -> 46
A16: Rates by trade | B16: Count
A17: Concrete (CIV-CON) | B17: =COUNTIF('03 MASTER RATE LIBRARY'!A5:A400,"CIV-CON-*") -> 24
A18: Reinforcement (CIV-RFT) | B18: =COUNTIF('03 MASTER RATE LIBRARY'!A5:A400,"CIV-RFT-*") -> 2
A19: Formwork (CIV-FWK) | B19: =COUNTIF('03 MASTER RATE LIBRARY'!A5:A400,"CIV-FWK-*") -> 6
A20: Masonry (CIV-MAS) | B20: =COUNTIF('03 MASTER RATE LIBRARY'!A5:A400,"CIV-MAS-*") -> 11
A21: Plaster (FIN-PLS) | B21: =COUNTIF('03 MASTER RATE LIBRARY'!A5:A400,"FIN-PLS-*") -> 5
A22: Screed (FIN-SCR) | B22: =COUNTIF('03 MASTER RATE LIBRARY'!A5:A400,"FIN-SCR-*") -> 4
A23: Skirting (FIN-SKT) | B23: =COUNTIF('03 MASTER RATE LIBRARY'!A5:A400,"FIN-SKT-*") -> 1
A24: Waterproofing (FIN-WPF) | B24: =COUNTIF('03 MASTER RATE LIBRARY'!A5:A400,"FIN-WPF-*") -> 3
A25: Flooring (FIN-FLR) | B25: =COUNTIF('03 MASTER RATE LIBRARY'!A5:A400,"FIN-FLR-*") -> 9
A26: Wall finishes (FIN-WAL) | B26: =COUNTIF('03 MASTER RATE LIBRARY'!A5:A400,"FIN-WAL-*") -> 4
A27: Ceilings (FIN-CLG) | B27: =COUNTIF('03 MASTER RATE LIBRARY'!A5:A400,"FIN-CLG-*") -> 5
A28: Painting (FIN-PNT) | B28: =COUNTIF('03 MASTER RATE LIBRARY'!A5:A400,"FIN-PNT-*") -> 2
A29: Prelims (PRE) | B29: =COUNTIF('03 MASTER RATE LIBRARY'!A5:A400,"PRE-*") -> 7
A30: Earthwork (CIV-EW) | B30: =COUNTIF('03 MASTER RATE LIBRARY'!A5:A400,"CIV-EW-*") -> 7
A31: Doors (FIN-DOR) | B31: =COUNTIF('03 MASTER RATE LIBRARY'!A5:A400,"FIN-DOR-*") -> 3
A32: Windows (FIN-WIN) | B32: =COUNTIF('03 MASTER RATE LIBRARY'!A5:A400,"FIN-WIN-*") -> 2
A33: Joinery (FIN-JNR) | B33: =COUNTIF('03 MASTER RATE LIBRARY'!A5:A400,"FIN-JNR-*") -> 1
A34: Façade (FAC) | B34: =COUNTIF('03 MASTER RATE LIBRARY'!A5:A400,"FAC-*") -> 7
A35: External (EXT) | B35: =COUNTIF('03 MASTER RATE LIBRARY'!A5:A400,"EXT-*") -> 7
A36: Plumbing (PLB) | B36: =COUNTIF('03 MASTER RATE LIBRARY'!A5:A400,"PLB-*") -> 17
A37: Fire fighting (FF) | B37: =COUNTIF('03 MASTER RATE LIBRARY'!A5:A400,"FF-*") -> 6
A38: Electrical (ELE) | B38: =COUNTIF('03 MASTER RATE LIBRARY'!A5:A400,"ELE-*") -> 14
A39: ELV | B39: =COUNTIF('03 MASTER RATE LIBRARY'!A5:A400,"ELV-*") -> 2
A40: Life safety (LS) | B40: =COUNTIF('03 MASTER RATE LIBRARY'!A5:A400,"LS-*") -> 2
A41: HVAC | B41: =COUNTIF('03 MASTER RATE LIBRARY'!A5:A400,"MEP-HVAC-*") -> 4
A42: Lifts (LFT) | B42: =COUNTIF('03 MASTER RATE LIBRARY'!A5:A400,"LFT-*") -> 2
A43: Misc (MISC) | B43: =COUNTIF('03 MASTER RATE LIBRARY'!A5:A400,"MISC-*") -> 3
A52: Concrete grade comparison (PKR per cft, final) | B52: Rate | C52: Status
A53: ='03 MASTER RATE LIBRARY'!A5&" "&'03 MASTER RATE LIBRARY'!D5 -> CIV-CON-001 5000 PSI | B53: ='03 MASTER RATE LIBRARY'!S5 -> 1173 | C53: ='03 MASTER RATE LIBRARY'!U5 -> INCOMPLETE – 1 blank/old input(s)
A54: ='03 MASTER RATE LIBRARY'!A6&" "&'03 MASTER RATE LIBRARY'!D6 -> CIV-CON-002 1000 PSI | B54: ='03 MASTER RATE LIBRARY'!S6 -> 795 | C54: ='03 MASTER RATE LIBRARY'!U6 -> Market-derived + assumptions
A55: ='03 MASTER RATE LIBRARY'!A7&" "&'03 MASTER RATE LIBRARY'!D7 -> CIV-CON-003 6000 PSI | B55: ='03 MASTER RATE LIBRARY'!S7 -> 1141 | C55: ='03 MASTER RATE LIBRARY'!U7 -> INCOMPLETE – 1 blank/old input(s)
A56: ='03 MASTER RATE LIBRARY'!A8&" "&'03 MASTER RATE LIBRARY'!D8 -> CIV-CON-004 1:3:6 | B56: ='03 MASTER RATE LIBRARY'!S8 -> 732 | C56: ='03 MASTER RATE LIBRARY'!U8 -> Market-derived + assumptions
A57: ='03 MASTER RATE LIBRARY'!A9&" "&'03 MASTER RATE LIBRARY'!D9 -> CIV-CON-005 4500 PSI | B57: ='03 MASTER RATE LIBRARY'!S9 -> 1073 | C57: ='03 MASTER RATE LIBRARY'!U9 -> INCOMPLETE – 1 blank/old input(s)
A58: ='03 MASTER RATE LIBRARY'!A10&" "&'03 MASTER RATE LIBRARY'!D10 -> CIV-CON-006 4000 PSI | B58: ='03 MASTER RATE LIBRARY'!S10 -> 1049 | C58: ='03 MASTER RATE LIBRARY'!U10 -> INCOMPLETE – 1 blank/old input(s)
A59: ='03 MASTER RATE LIBRARY'!A11&" "&'03 MASTER RATE LIBRARY'!D11 -> CIV-CON-007 1500 PSI | B59: ='03 MASTER RATE LIBRARY'!S11 -> 787 | C59: ='03 MASTER RATE LIBRARY'!U11 -> Market-derived + assumptions
A60: ='03 MASTER RATE LIBRARY'!A12&" "&'03 MASTER RATE LIBRARY'!D12 -> CIV-CON-008 4000 PSI | B60: ='03 MASTER RATE LIBRARY'!S12 -> 967 | C60: ='03 MASTER RATE LIBRARY'!U12 -> INCOMPLETE – 1 blank/old input(s)
A61: ='03 MASTER RATE LIBRARY'!A13&" "&'03 MASTER RATE LIBRARY'!D13 -> CIV-CON-009 4500 PSI | B61: ='03 MASTER RATE LIBRARY'!S13 -> 1014 | C61: ='03 MASTER RATE LIBRARY'!U13 -> INCOMPLETE – 1 blank/old input(s)
A62: ='03 MASTER RATE LIBRARY'!A14&" "&'03 MASTER RATE LIBRARY'!D14 -> CIV-CON-010 6000 PSI | B62: ='03 MASTER RATE LIBRARY'!S14 -> 1132 | C62: ='03 MASTER RATE LIBRARY'!U14 -> INCOMPLETE – 1 blank/old input(s)
A63: ='03 MASTER RATE LIBRARY'!A15&" "&'03 MASTER RATE LIBRARY'!D15 -> CIV-CON-011 3000 PSI | B63: ='03 MASTER RATE LIBRARY'!S15 -> 921 | C63: ='03 MASTER RATE LIBRARY'!U15 -> INCOMPLETE – 1 blank/old input(s)
A64: ='03 MASTER RATE LIBRARY'!A16&" "&'03 MASTER RATE LIBRARY'!D16 -> CIV-CON-012 4000 PSI | B64: ='03 MASTER RATE LIBRARY'!S16 -> 1027 | C64: ='03 MASTER RATE LIBRARY'!U16 -> INCOMPLETE – 1 blank/old input(s)
... A70: ='03 MASTER RATE LIBRARY'!A22&" "&'03 MASTER RATE LIBRARY'!D22 -> CIV-CON-018 Nominal 1:1.5:3 | B70: ='03 MASTER RATE LIBRARY'!S22 -> 873 | C70: ='03 MASTER RATE LIBRARY'!U22 -> Market-derived + assumptions
A71: ='03 MASTER RATE LIBRARY'!A122&" "&'03 MASTER RATE LIBRARY'!D122 -> CIV-CON-019 Nominal 1:3:6 | B71: ='03 MASTER RATE LIBRARY'!S122 -> 684 | C71: ='03 MASTER RATE LIBRARY'!U122 -> Market-derived + assumptions
A72: ='03 MASTER RATE LIBRARY'!A126&" "&'03 MASTER RATE LIBRARY'!D126 -> CIV-CON-020 RMC 4000 PSI (GRN) | B72: ='03 MASTER RATE LIBRARY'!S126 -> 551 | C72: ='03 MASTER RATE LIBRARY'!U126 -> Market-derived + assumptions
A73: ='03 MASTER RATE LIBRARY'!A127&" "&'03 MASTER RATE LIBRARY'!D127 -> CIV-CON-021 RMC 4500 PSI (GRN) | B73: ='03 MASTER RATE LIBRARY'!S127 -> 544 | C73: ='03 MASTER RATE LIBRARY'!U127 -> Market-derived + assumptions
A74: ='03 MASTER RATE LIBRARY'!A128&" "&'03 MASTER RATE LIBRARY'!D128 -> CIV-CON-022 RMC 6500 PSI (GRN) | B74: ='03 MASTER RATE LIBRARY'!S128 -> 660 | C74: ='03 MASTER RATE LIBRARY'!U128 -> Market-derived + assumptions
A75: ='03 MASTER RATE LIBRARY'!A129&" "&'03 MASTER RATE LIBRARY'!D129 -> CIV-CON-023 RMC Lean (GRN) | B75: ='03 MASTER RATE LIBRARY'!S129 -> 471 | C75: ='03 MASTER RATE LIBRARY'!U129 -> Market-derived + assumptions

Sheet 03 MASTER RATE LIBRARY
A1: 03 · MASTER RATE LIBRARY – selected city (links live to 04)
A2: Filter with header arrows. Rate Status turns INCOMPLETE while any red input in the analysis is blank.
A4: Item Code | B4: Trade | C4: Sub Trade | D4: Category | E4: Item Description | F4: Full Specification | G4: Unit | H4: Location | I4: Rate Date | J4: Material Cost | K4: Labour Cost | L4: Equipment Cost | M4: Transport Cost | N4: Wastage Cost | O4: Direct Cost | P4: Overheads | Q4: Profit | R4: Tax | S4: Final Rate PKR | T4: Rate per 100 units | U4: Rate Status | V4: Confidence | W4: Blank Inputs | X4: Source | Y4: Source Date | Z4: Source URL | AA4: Notes | AB4: Dup Code?
A5: CIV-CON-001 | B5: Civil | C5: Concrete | D5: 5000 PSI | E5: Providing and laying 5000 PSI concrete (Lab ACI 211.1 – 5000 PSI (W/C 0.34); mix per Image 1 – ACI 211.1 lab sheet) in structural members, including batching, placing, compacting and curing, complete in all respects; excluding reinforcement and formwork measured separately. | F5: Mix LAB-5000; cement 550 kg per lab batch; source Image 1 – ACI 211.1 lab sheet, dated 2026-04-05 | G5: cft | H5: =City -> Lahore | I5: 2026-09-27 | J5: ='04 DETAILED RATE ANALYSIS'!J17 -> 761.31063 | K5: ='04 DETAILED RATE ANALYSIS'!J20 -> 145.04 | L5: ='04 DETAILED RATE ANALYSIS'!J21 -> 65.59 | M5: ='04 DETAILED RATE ANALYSIS'!J22 -> 0 | N5: ='04 DETAILED RATE ANALYSIS'!J18 -> 21.957827 | O5: ='04 DETAILED RATE ANALYSIS'!J23 -> 993.89846 | P5: ='04 DETAILED RATE ANALYSIS'!J24+'04 DETAILED RATE ANALYSIS'!J25 -> 79.511877 | Q5: ='04 DETAILED RATE ANALYSIS'!J26 -> 99.389846 | R5: ='04 DETAILED RATE ANALYSIS'!J28 -> 0 | S5: ='04 DETAILED RATE ANALYSIS'!J29 -> 1173 | T5: =S5*100 -> 117300 | U5: =IF(W5>0,"INCOMPLETE – "&W5&" blank/old input(s)","Market-derived + assumptions") -> INCOMPLETE – 1 blank/old input(s) | V5: Low | W5: ='04 DETAILED RATE ANALYSIS'!J30 -> 1 | X5: See 09 SOURCE REGISTER (SRC-01…08) | Y5: 2026-04-25 to 2026-09-19 | Z5: see 09 | AA5: Admixture 7.69 kg = 1.2 L/100kg × 550 × SG 1.165 ✓. Required strength cell (20% extra) blank on sheet. | AB5: =IF(COUNTIF($A$5:$A$999,A5)>1,"DUPLICATE","")
A6: CIV-CON-002 | B6: Civil | C6: PCC / Lean concrete | D6: 1000 PSI | E6: Providing and laying 1000 PSI concrete (Lab – 1000 PSI (lean); mix per Image 2 – lab mix sheet) in sub-structure/PCC, including batching, placing, compacting and curing, complete in all respects; excluding reinforcement and formwork measured separately. | F6: Mix LAB-1000; cement 200 kg per lab batch; source Image 2 – lab mix sheet, dated Not visible | G6: cft | H6: =City -> Lahore | I6: 2026-09-27 | J6: ='04 DETAILED RATE ANALYSIS'!J44 -> 439.1663 | K6: ='04 DETAILED RATE ANALYSIS'!J47 -> 142.85 | L6: ='04 DETAILED RATE ANALYSIS'!J48 -> 74.9075 | M6: ='04 DETAILED RATE ANALYSIS'!J49 -> 0 | N6: ='04 DETAILED RATE ANALYSIS'!J45 -> 16.402517 | O6: ='04 DETAILED RATE ANALYSIS'!J50 -> 673.32632 | P6: ='04 DETAILED RATE ANALYSIS'!J51+'04 DETAILED RATE ANALYSIS'!J52 -> 53.866106 | Q6: ='04 DETAILED RATE ANALYSIS'!J53 -> 67.332632 | R6: ='04 DETAILED RATE ANALYSIS'!J55 -> 0 | S6: ='04 DETAILED RATE ANALYSIS'!J56 -> 795 | T6: =S6*100 -> 79500 | U6: =IF(W6>0,"INCOMPLETE – "&W6&" blank/old input(s)","Market-derived + assumptions") -> Market-derived + assumptions | V6: Low | W6: ='04 DETAILED RATE ANALYSIS'!J57 -> 0 | X6: See 09 SOURCE REGISTER (SRC-01…08) | Y6: 2026-04-25 to 2026-09-19 | Z6: see 09 | AA6: W/C 1.05 – very high; no admixture. Coarse source options Margalla/Sargodha/Sakhi Sarwar – Margalla (first listed) priced. | AB6: =IF(COUNTIF($A$5:$A$999,A6)>1,"DUPLICATE","")
A7: CIV-CON-003 | B7: Civil | C7: Concrete | D7: 6000 PSI | E7: Providing and laying 6000 PSI concrete (Lab – 6000 PSI (DHA Multan sheet); mix per Image 3 – lab mix sheet) in structural members, including batching, placing, compacting and curing, complete in all respects; excluding reinforcement and formwork measured separately. | F7: Mix LAB-6000; cement 550 kg per lab batch; source Image 3 – lab mix sheet, dated Not visible | G7: cft | H7: =City -> Lahore | I7: 2026-09-27 | J7: ='04 DETAILED RATE ANALYSIS'!J72 -> 735.20447 | K7: ='04 DETAILED RATE ANALYSIS'!J75 -> 145.04 | L7: ='04 DETAILED RATE ANALYSIS'!J76 -> 65.59 | M7: ='04 DETAILED RATE ANALYSIS'!J77 -> 0 | N7: ='04 DETAILED RATE ANALYSIS'!J73 -> 21.050989 | O7: ='04 DETAILED RATE ANALYSIS'!J78 -> 966.88546 | P7: ='04 DETAILED RATE ANALYSIS'!J79+'04 DETAILED RATE ANALYSIS'!J80 -> 77.350836 | Q7: ='04 DETAILED RATE ANALYSIS'!J81 -> 96.688546 | R7: ='04 DETAILED RATE ANALYSIS'!J83 -> 0 | S7: ='04 DETAILED RATE ANALYSIS'!J84 -> 1141 | T7: =S7*100 -> 114100 | U7: =IF(W7>0,"INCOMPLETE – "&W7&" blank/old input(s)","Market-derived + assumptions") -> INCOMPLETE – 1 blank/old input(s) | V7: Low | W7: ='04 DETAILED RATE ANALYSIS'!J85 -> 1 | X7: See 09 SOURCE REGISTER (SRC-01…08) | Y7: 2026-04-25 to 2026-09-19 | Z7: see 09 | AA7: Admixture entered in 'Admixture-2' row, Sika 512 row blank – product not identified. Slump 175 initial / 85 at 90 min. | AB7: =IF(COUNTIF($A$5:$A$999,A7)>1,"DUPLICATE","")
A8: CIV-CON-004 | B8: Civil | C8: PCC / Lean concrete | D8: 1:3:6 | E8: Providing and laying 1:3:6 concrete (Lab – 1:3:6 ratio (PCC); mix per Image 5 – lab mix sheet) in sub-structure/PCC, including batching, placing, compacting and curing, complete in all respects; excluding reinforcement and formwork measured separately. | F8: Mix LAB-136; cement 250 kg per lab batch; source Image 5 – lab mix sheet, dated Not visible | G8: cft | H8: =City -> Lahore | I8: 2026-09-27 | J8: ='04 DETAILED RATE ANALYSIS'!J99 -> 390.17416 | K8: ='04 DETAILED RATE ANALYSIS'!J102 -> 142.85 | L8: ='04 DETAILED RATE ANALYSIS'!J103 -> 74.9075 | M8: ='04 DETAILED RATE ANALYSIS'!J104 -> 0 | N8: ='04 DETAILED RATE ANALYSIS'!J100 -> 12.612038 | O8: ='04 DETAILED RATE ANALYSIS'!J105 -> 620.54369 | P8: ='04 DETAILED RATE ANALYSIS'!J106+'04 DETAILED RATE ANALYSIS'!J107 -> 49.643496 | Q8: ='04 DETAILED RATE ANALYSIS'!J108 -> 62.054369 | R8: ='04 DETAILED RATE ANALYSIS'!J110 -> 0 | S8: ='04 DETAILED RATE ANALYSIS'!J111 -> 732 | T8: =S8*100 -> 73200 | U8: =IF(W8>0,"INCOMPLETE – "&W8&" blank/old input(s)","Market-derived + assumptions") -> Market-derived + assumptions | V8: Low | W8: ='04 DETAILED RATE ANALYSIS'!J112 -> 0 | X8: See 09 SOURCE REGISTER (SRC-01…08) | Y8: 2026-04-25 to 2026-09-19 | Z8: see 09 | AA8: Labelled by ratio, not strength. Zinda Pir sand has no dated rate – item incomplete until entered. | AB8: =IF(COUNTIF($A$5:$A$999,A8)>1,"DUPLICATE","")
A9: CIV-CON-005 | B9: Civil | C9: Concrete | D9: 4500 PSI | E9: Providing and laying 4500 PSI concrete (Lab – 4500 PSI; mix per Image 6 – lab mix sheet) in structural members, including batching, placing, compacting and curing, complete in all respects; excluding reinforcement and formwork measured separately. | F9: Mix LAB-4500; cement 475 kg per lab batch; source Image 6 – lab mix sheet, dated Not visible | G9: cft | H9: =City -> Lahore | I9: 2026-09-27 | J9: ='04 DETAILED RATE ANALYSIS'!J127 -> 678.25042 | K9: ='04 DETAILED RATE ANALYSIS'!J130 -> 145.04 | L9: ='04 DETAILED RATE ANALYSIS'!J131 -> 65.59 | M9: ='04 DETAILED RATE ANALYSIS'!J132 -> 0 | N9: ='04 DETAILED RATE ANALYSIS'!J128 -> 20.261257 | O9: ='04 DETAILED RATE ANALYSIS'!J133 -> 909.14167 | P9: ='04 DETAILED RATE ANALYSIS'!J134+'04 DETAILED RATE ANALYSIS'!J135 -> 72.731334 | Q9: ='04 DETAILED RATE ANALYSIS'!J136 -> 90.914167 | R9: ='04 DETAILED RATE ANALYSIS'!J138 -> 0 | S9: ='04 DETAILED RATE ANALYSIS'!J139 -> 1073 | T9: =S9*100 -> 107300 | U9: =IF(W9>0,"INCOMPLETE – "&W9&" blank/old input(s)","Market-derived + assumptions") -> INCOMPLETE – 1 blank/old input(s) | V9: Low | W9: ='04 DETAILED RATE ANALYSIS'!J140 -> 1 | X9: See 09 SOURCE REGISTER (SRC-01…08) | Y9: 2026-04-25 to 2026-09-19 | Z9: see 09 | AA9: Slump 190 initial / 90 at 90 min. | AB9: =IF(COUNTIF($A$5:$A$999,A9)>1,"DUPLICATE","")
A10: CIV-CON-006 | B10: Civil | C10: Concrete | D10: 4000 PSI | E10: Providing and laying 4000 PSI concrete (Lab – 4000 PSI; mix per Image 8 – lab mix sheet) in structural members, including batching, placing, compacting and curing, complete in all respects; excluding reinforcement and formwork measured separately. | F10: Mix LAB-4000; cement 450 kg per lab batch; source Image 8 – lab mix sheet, dated Not visible | G10: cft | H10: =City -> Lahore | I10: 2026-09-27 | J10: ='04 DETAILED RATE ANALYSIS'!J155 -> 658.04544 | K10: ='04 DETAILED RATE ANALYSIS'!J158 -> 145.04 | L10: ='04 DETAILED RATE ANALYSIS'!J159 -> 65.59 | M10: ='04 DETAILED RATE ANALYSIS'!J160 -> 0 | N10: ='04 DETAILED RATE ANALYSIS'!J156 -> 19.984792 | O10: ='04 DETAILED RATE ANALYSIS'!J161 -> 888.66024 | P10: ='04 DETAILED RATE ANALYSIS'!J162+'04 DETAILED RATE ANALYSIS'!J163 -> 71.092819 | Q10: ='04 DETAILED RATE ANALYSIS'!J164 -> 88.866024 | R10: ='04 DETAILED RATE ANALYSIS'!J166 -> 0 | S10: ='04 DETAILED RATE ANALYSIS'!J167 -> 1049 | T10: =S10*100 -> 104900 | U10: =IF(W10>0,"INCOMPLETE – "&W10&" blank/old input(s)","Market-derived + assumptions") -> INCOMPLETE – 1 blank/old input(s) | V10: Low | W10: ='04 DETAILED RATE ANALYSIS'!J168 -> 1 | X10: See 09 SOURCE REGISTER (SRC-01…08) | Y10: 2026-04-25 to 2026-09-19 | Z10: see 09 | AA10: Slump 185 initial / 100 at 90 min. | AB10: =IF(COUNTIF($A$5:$A$999,A10)>1,"DUPLICATE","")
A11: CIV-CON-007 | B11: Civil | C11: PCC / Lean concrete | D11: 1500 PSI | E11: Providing and laying 1500 PSI concrete (ACI-211 batch sheet – 1500 PSI; mix per Image 4 – ACI-211 summary (QA/QC)) in sub-structure/PCC, including batching, placing, compacting and curing, complete in all respects; excluding reinforcement and formwork measured separately. | F11: Mix ACI-1500; cement 180 kg per lab batch; source Image 4 – ACI-211 summary (QA/QC), dated Not dated | G11: cft | H11: =City -> Lahore | I11: 2026-09-27 | J11: ='04 DETAILED RATE ANALYSIS'!J181 -> 432.69259 | K11: ='04 DETAILED RATE ANALYSIS'!J184 -> 142.85 | L11: ='04 DETAILED RATE ANALYSIS'!J185 -> 74.9075 | M11: ='04 DETAILED RATE ANALYSIS'!J186 -> 0 | N11: ='04 DETAILED RATE ANALYSIS'!J182 -> 16.643153 | O11: ='04 DETAILED RATE ANALYSIS'!J187 -> 667.09324 | P11: ='04 DETAILED RATE ANALYSIS'!J188+'04 DETAILED RATE ANALYSIS'!J189 -> 53.367459 | Q11: ='04 DETAILED RATE ANALYSIS'!J190 -> 66.709324 | R11: ='04 DETAILED RATE ANALYSIS'!J192 -> 0 | S11: ='04 DETAILED RATE ANALYSIS'!J193 -> 787 | T11: =S11*100 -> 78700 | U11: =IF(W11>0,"INCOMPLETE – "&W11&" blank/old input(s)","Market-derived + assumptions") -> Market-derived + assumptions | V11: Low | W11: ='04 DETAILED RATE ANALYSIS'!J194 -> 0 | X11: See 09 SOURCE REGISTER (SRC-01…08) | Y11: 2026-04-25 to 2026-09-19 | Z11: see 09 | AA11: Crush given as combined 1220 kg. Sheet unsigned/undated. | AB11: =IF(COUNTIF($A$5:$A$999,A11)>1,"DUPLICATE","")
A12: CIV-CON-008 | B12: Civil | C12: Concrete | D12: 4000 PSI | E12: Providing and laying 4000 PSI concrete (ACI-211 batch sheet – 4000 PSI; mix per Image 4 – ACI-211 summary) in structural members, including batching, placing, compacting and curing, complete in all respects; excluding reinforcement and formwork measured separately. | F12: Mix ACI-4000; cement 350 kg per lab batch; source Image 4 – ACI-211 summary, dated Not dated | G12: cft | H12: =City -> Lahore | I12: 2026-09-27 | J12: ='04 DETAILED RATE ANALYSIS'!J210 -> 589.95414 | K12: ='04 DETAILED RATE ANALYSIS'!J213 -> 145.04 | L12: ='04 DETAILED RATE ANALYSIS'!J214 -> 65.59 | M12: ='04 DETAILED RATE ANALYSIS'!J215 -> 0 | N12: ='04 DETAILED RATE ANALYSIS'!J211 -> 19.253675 | O12: ='04 DETAILED RATE ANALYSIS'!J216 -> 819.83782 | P12: ='04 DETAILED RATE ANALYSIS'!J217+'04 DETAILED RATE ANALYSIS'!J218 -> 65.587025 | Q12: ='04 DETAILED RATE ANALYSIS'!J219 -> 81.983782 | R12: ='04 DETAILED RATE ANALYSIS'!J221 -> 0 | S12: ='04 DETAILED RATE ANALYSIS'!J222 -> 967 | T12: =S12*100 -> 96700 | U12: =IF(W12>0,"INCOMPLETE – "&W12&" blank/old input(s)","Market-derived + assumptions") -> INCOMPLETE – 1 blank/old input(s) | V12: Low | W12: ='04 DETAILED RATE ANALYSIS'!J223 -> 1 | X12: See 09 SOURCE REGISTER (SRC-01…08) | Y12: 2026-04-25 to 2026-09-19 | Z12: see 09 | AA12: Cement 350 kg is 22% below lab 4000 (450) and 18% below J7 4000 (425) – verify trial-mix results. | AB12: =IF(COUNTIF($A$5:$A$999,A12)>1,"DUPLICATE","")
A13: CIV-CON-009 | B13: Civil | C13: Concrete | D13: 4500 PSI | E13: Providing and laying 4500 PSI concrete (ACI-211 batch sheet – 4500 PSI; mix per Image 4 – ACI-211 summary) in structural members, including batching, placing, compacting and curing, complete in all respects; excluding reinforcement and formwork measured separately. | F13: Mix ACI-4500; cement 400 kg per lab batch; source Image 4 – ACI-211 summary, dated Not dated | G13: cft | H13: =City -> Lahore | I13: 2026-09-27 | J13: ='04 DETAILED RATE ANALYSIS'!J239 -> 628.8755 | K13: ='04 DETAILED RATE ANALYSIS'!J242 -> 145.04 | L13: ='04 DETAILED RATE ANALYSIS'!J243 -> 65.59 | M13: ='04 DETAILED RATE ANALYSIS'!J244 -> 0 | N13: ='04 DETAILED RATE ANALYSIS'!J240 -> 19.822583 | O13: ='04 DETAILED RATE ANALYSIS'!J245 -> 859.32808 | P13: ='04 DETAILED RATE ANALYSIS'!J246+'04 DETAILED RATE ANALYSIS'!J247 -> 68.746246 | Q13: ='04 DETAILED RATE ANALYSIS'!J248 -> 85.932808 | R13: ='04 DETAILED RATE ANALYSIS'!J250 -> 0 | S13: ='04 DETAILED RATE ANALYSIS'!J251 -> 1014 | T13: =S13*100 -> 101400 | U13: =IF(W13>0,"INCOMPLETE – "&W13&" blank/old input(s)","Market-derived + assumptions") -> INCOMPLETE – 1 blank/old input(s) | V13: Low | W13: ='04 DETAILED RATE ANALYSIS'!J252 -> 1 | X13: See 09 SOURCE REGISTER (SRC-01…08) | Y13: 2026-04-25 to 2026-09-19 | Z13: see 09 | AB13: =IF(COUNTIF($A$5:$A$999,A13)>1,"DUPLICATE","")
A14: CIV-CON-010 | B14: Civil | C14: Concrete | D14: 6000 PSI | E14: Providing and laying 6000 PSI concrete (ACI-211 batch sheet – 6000 PSI; mix per Image 4 – ACI-211 summary) in structural members, including batching, placing, compacting and curing, complete in all respects; excluding reinforcement and formwork measured separately. | F14: Mix ACI-6000; cement 520 kg per lab batch; source Image 4 – ACI-211 summary, dated Not dated | G14: cft | H14: =City -> Lahore | I14: 2026-09-27 | J14: ='04 DETAILED RATE ANALYSIS'!J268 -> 727.64087 | K14: ='04 DETAILED RATE ANALYSIS'!J271 -> 145.04 | L14: ='04 DETAILED RATE ANALYSIS'!J272 -> 65.59 | M14: ='04 DETAILED RATE ANALYSIS'!J273 -> 0 | N14: ='04 DETAILED RATE ANALYSIS'!J269 -> 21.320019 | O14: ='04 DETAILED RATE ANALYSIS'!J274 -> 959.59089 | P14: ='04 DETAILED RATE ANALYSIS'!J275+'04 DETAILED RATE ANALYSIS'!J276 -> 76.767271 | Q14: ='04 DETAILED RATE ANALYSIS'!J277 -> 95.959089 | R14: ='04 DETAILED RATE ANALYSIS'!J279 -> 0 | S14: ='04 DETAILED RATE ANALYSIS'!J280 -> 1132 | T14: =S14*100 -> 113200 | U14: =IF(W14>0,"INCOMPLETE – "&W14&" blank/old input(s)","Market-derived + assumptions") -> INCOMPLETE – 1 blank/old input(s) | V14: Low | W14: ='04 DETAILED RATE ANALYSIS'!J281 -> 1 | X14: See 09 SOURCE REGISTER (SRC-01…08) | Y14: 2026-04-25 to 2026-09-19 | Z14: see 09 | AB14: =IF(COUNTIF($A$5:$A$999,A14)>1,"DUPLICATE","")
A15: CIV-CON-011 | B15: Civil | C15: Concrete | D15: 3000 PSI | E15: Providing and laying 3000 PSI concrete (J7 Emporium Mall B-17 batching plant – 3000 PSI; mix per Image 7 – J7 Group summary of batch weights) in structural members, including batching, placing, compacting and curing, complete in all respects; excluding reinforcement and formwork measured separately. | F15: Mix J7-3000; cement 325 kg per lab batch; source Image 7 – J7 Group summary of batch weights, dated 2024-03-08 (trials Jan-2024) | G15: cft | H15: =City -> Lahore | I15: 2026-09-27 | J15: ='04 DETAILED RATE ANALYSIS'!J297 -> 551.8277 | K15: ='04 DETAILED RATE ANALYSIS'!J300 -> 145.04 | L15: ='04 DETAILED RATE ANALYSIS'!J301 -> 65.59 | M15: ='04 DETAILED RATE ANALYSIS'!J302 -> 0 | N15: ='04 DETAILED RATE ANALYSIS'!J298 -> 18.197414 | O15: ='04 DETAILED RATE ANALYSIS'!J303 -> 780.65512 | P15: ='04 DETAILED RATE ANALYSIS'!J304+'04 DETAILED RATE ANALYSIS'!J305 -> 62.452409 | Q15: ='04 DETAILED RATE ANALYSIS'!J306 -> 78.065512 | R15: ='04 DETAILED RATE ANALYSIS'!J308 -> 0 | S15: ='04 DETAILED RATE ANALYSIS'!J309 -> 921 | T15: =S15*100 -> 92100 | U15: =IF(W15>0,"INCOMPLETE – "&W15&" blank/old input(s)","Market-derived + assumptions") -> INCOMPLETE – 1 blank/old input(s) | V15: Low | W15: ='04 DETAILED RATE ANALYSIS'!J310 -> 1 | X15: See 09 SOURCE REGISTER (SRC-01…08) | Y15: 2026-04-25 to 2026-09-19 | Z15: see 09 | AA15: Trial mix TM#16 17-01-2024. Sheet dated 2024 – older than other mixes. Crush 1/2" only 105 kg vs 3/8" 738 kg (fine-graded coarse). | AB15: =IF(COUNTIF($A$5:$A$999,A15)>1,"DUPLICATE","")
A16: CIV-CON-012 | B16: Civil | C16: Concrete | D16: 4000 PSI | E16: Providing and laying 4000 PSI concrete (J7 Emporium Mall B-17 batching plant – 4000 PSI; mix per Image 7 – J7 Group summary of batch weights) in structural members, including batching, placing, compacting and curing, complete in all respects; excluding reinforcement and formwork measured separately. | F16: Mix J7-4000; cement 425 kg per lab batch; source Image 7 – J7 Group summary of batch weights, dated 2024-03-08 (trials Jan-2024) | G16: cft | H16: =City -> Lahore | I16: 2026-09-27 | J16: ='04 DETAILED RATE ANALYSIS'!J326 -> 639.94701 | K16: ='04 DETAILED RATE ANALYSIS'!J329 -> 145.04 | L16: ='04 DETAILED RATE ANALYSIS'!J330 -> 65.59 | M16: ='04 DETAILED RATE ANALYSIS'!J331 -> 0 | N16: ='04 DETAILED RATE ANALYSIS'!J327 -> 19.556572 | O16: ='04 DETAILED RATE ANALYSIS'!J332 -> 870.13358 | P16: ='04 DETAILED RATE ANALYSIS'!J333+'04 DETAILED RATE ANALYSIS'!J334 -> 69.610687 | Q16: ='04 DETAILED RATE ANALYSIS'!J335 -> 87.013358 | R16: ='04 DETAILED RATE ANALYSIS'!J337 -> 0 | S16: ='04 DETAILED RATE ANALYSIS'!J338 -> 1027 | T16: =S16*100 -> 102700 | U16: =IF(W16>0,"INCOMPLETE – "&W16&" blank/old input(s)","Market-derived + assumptions") -> INCOMPLETE – 1 blank/old input(s) | V16: Low | W16: ='04 DETAILED RATE ANALYSIS'!J339 -> 1 | X16: See 09 SOURCE REGISTER (SRC-01…08) | Y16: 2026-04-25 to 2026-09-19 | Z16: see 09 | AA16: Trial mix TM#11 13-01-2024. Sheet dated 2024 – older than other mixes. Crush 1/2" only 105 kg vs 3/8" 738 kg (fine-graded coarse). | AB16: =IF(COUNTIF($A$5:$A$999,A16)>1,"DUPLICATE","")
A17: CIV-CON-013 | B17: Civil | C17: Concrete | D17: 4500 PSI | E17: Providing and laying 4500 PSI concrete (J7 Emporium Mall B-17 batching plant – 4500 PSI; mix per Image 7 – J7 Group summary of batch weights) in structural members, including batching, placing, compacting and curing, complete in all respects; excluding reinforcement and formwork measured separately. | F17: Mix J7-4500; cement 465 kg per lab batch; source Image 7 – J7 Group summary of batch weights, dated 2024-03-08 (trials Jan-2024) | G17: cft | H17: =City -> Lahore | I17: 2026-09-27 | J17: ='04 DETAILED RATE ANALYSIS'!J355 -> 676.90158 | K17: ='04 DETAILED RATE ANALYSIS'!J358 -> 145.04 | L17: ='04 DETAILED RATE ANALYSIS'!J359 -> 65.59 | M17: ='04 DETAILED RATE ANALYSIS'!J360 -> 0 | N17: ='04 DETAILED RATE ANALYSIS'!J356 -> 20.19832 | O17: ='04 DETAILED RATE ANALYSIS'!J361 -> 907.7299 | P17: ='04 DETAILED RATE ANALYSIS'!J362+'04 DETAILED RATE ANALYSIS'!J363 -> 72.618392 | Q17: ='04 DETAILED RATE ANALYSIS'!J364 -> 90.77299 | R17: ='04 DETAILED RATE ANALYSIS'!J366 -> 0 | S17: ='04 DETAILED RATE ANALYSIS'!J367 -> 1071 | T17: =S17*100 -> 107100 | U17: =IF(W17>0,"INCOMPLETE – "&W17&" blank/old input(s)","Market-derived + assumptions") -> INCOMPLETE – 1 blank/old input(s) | V17: Low | W17: ='04 DETAILED RATE ANALYSIS'!J368 -> 1 | X17: See 09 SOURCE REGISTER (SRC-01…08) | Y17: 2026-04-25 to 2026-09-19 | Z17: see 09 | AA17: Trial mix TM#15 17-01-2024. Sheet dated 2024 – older than other mixes. Crush 1/2" only 105 kg vs 3/8" 738 kg (fine-graded coarse). | AB17: =IF(COUNTIF($A$5:$A$999,A17)>1,"DUPLICATE","")
A18: CIV-CON-014 | B18: Civil | C18: Concrete | D18: 5000 PSI | E18: Providing and laying 5000 PSI concrete (J7 Emporium Mall B-17 batching plant – 5000 PSI; mix per Image 7 – J7 Group summary of batch weights) in structural members, including batching, placing, compacting and curing, complete in all respects; excluding reinforcement and formwork measured separately. | F18: Mix J7-5000; cement 515 kg per lab batch; source Image 7 – J7 Group summary of batch weights, dated 2024-03-08 (trials Jan-2024) | G18: cft | H18: =City -> Lahore | I18: 2026-09-27 | J18: ='04 DETAILED RATE ANALYSIS'!J384 -> 717.22618 | K18: ='04 DETAILED RATE ANALYSIS'!J387 -> 145.04 | L18: ='04 DETAILED RATE ANALYSIS'!J388 -> 65.59 | M18: ='04 DETAILED RATE ANALYSIS'!J389 -> 0 | N18: ='04 DETAILED RATE ANALYSIS'!J385 -> 20.749153 | O18: ='04 DETAILED RATE ANALYSIS'!J390 -> 948.60534 | P18: ='04 DETAILED RATE ANALYSIS'!J391+'04 DETAILED RATE ANALYSIS'!J392 -> 75.888427 | Q18: ='04 DETAILED RATE ANALYSIS'!J393 -> 94.860534 | R18: ='04 DETAILED RATE ANALYSIS'!J395 -> 0 | S18: ='04 DETAILED RATE ANALYSIS'!J396 -> 1119 | T18: =S18*100 -> 111900 | U18: =IF(W18>0,"INCOMPLETE – "&W18&" blank/old input(s)","Market-derived + assumptions") -> INCOMPLETE – 1 blank/old input(s) | V18: Low | W18: ='04 DETAILED RATE ANALYSIS'!J397 -> 1 | X18: See 09 SOURCE REGISTER (SRC-01…08) | Y18: 2026-04-25 to 2026-09-19 | Z18: see 09 | AA18: Trial mix TM#12 15-01-2024. Sheet dated 2024 – older than other mixes. Crush 1/2" only 105 kg vs 3/8" 738 kg (fine-graded coarse). Admixture check: 1.42%×515=7.31 vs 7.29 stated (minor). | AB18: =IF(COUNTIF($A$5:$A$999,A18)>1,"DUPLICATE","")
A19: CIV-CON-015 | B19: Civil | C19: Concrete | D19: 5500 PSI | E19: Providing and laying 5500 PSI concrete (J7 Emporium Mall B-17 batching plant – 5500 PSI; mix per Image 7 – J7 Group summary of batch weights) in structural members, including batching, placing, compacting and curing, complete in all respects; excluding reinforcement and formwork measured separately. | F19: Mix J7-5500; cement 530 kg per lab batch; source Image 7 – J7 Group summary of batch weights, dated 2024-03-08 (trials Jan-2024) | G19: cft | H19: =City -> Lahore | I19: 2026-09-27 | J19: ='04 DETAILED RATE ANALYSIS'!J413 -> 729.59156 | K19: ='04 DETAILED RATE ANALYSIS'!J416 -> 145.04 | L19: ='04 DETAILED RATE ANALYSIS'!J417 -> 65.59 | M19: ='04 DETAILED RATE ANALYSIS'!J418 -> 0 | N19: ='04 DETAILED RATE ANALYSIS'!J414 -> 20.933031 | O19: ='04 DETAILED RATE ANALYSIS'!J419 -> 961.15459 | P19: ='04 DETAILED RATE ANALYSIS'!J420+'04 DETAILED RATE ANALYSIS'!J421 -> 76.892367 | Q19: ='04 DETAILED RATE ANALYSIS'!J422 -> 96.115459 | R19: ='04 DETAILED RATE ANALYSIS'!J424 -> 0 | S19: ='04 DETAILED RATE ANALYSIS'!J425 -> 1134 | T19: =S19*100 -> 113400 | U19: =IF(W19>0,"INCOMPLETE – "&W19&" blank/old input(s)","Market-derived + assumptions") -> INCOMPLETE – 1 blank/old input(s) | V19: Low | W19: ='04 DETAILED RATE ANALYSIS'!J426 -> 1 | X19: See 09 SOURCE REGISTER (SRC-01…08) | Y19: 2026-04-25 to 2026-09-19 | Z19: see 09 | AA19: Trial mix TM#13 15-01-2024. Sheet dated 2024 – older than other mixes. Crush 1/2" only 105 kg vs 3/8" 738 kg (fine-graded coarse). | AB19: =IF(COUNTIF($A$5:$A$999,A19)>1,"DUPLICATE","")
A20: CIV-CON-016 | B20: Civil | C20: PCC / Lean concrete | D20: Nominal 1:4:8 | E20: Providing and laying plain cement concrete 1:4:8 (nominal volumetric, site-mixed) using OPC, Chenab sand and Margalla crush, including mixing, placing, compacting and curing, complete in all respects; excluding reinforcement and formwork measured separately. | F20: Nominal volumetric 1:4:8, dry factor 1.54, 1 bag = 1.25 cft (house standard); Lahore basis sand | G20: cft | H20: =City -> Lahore | I20: 2026-09-27 | J20: ='04 DETAILED RATE ANALYSIS'!J438 -> 359.37914 | K20: ='04 DETAILED RATE ANALYSIS'!J441 -> 142.85 | L20: ='04 DETAILED RATE ANALYSIS'!J442 -> 46.5875 | M20: ='04 DETAILED RATE ANALYSIS'!J443 -> 0 | N20: ='04 DETAILED RATE ANALYSIS'!J439 -> 13.409846 | O20: ='04 DETAILED RATE ANALYSIS'!J444 -> 562.22648 | P20: ='04 DETAILED RATE ANALYSIS'!J445+'04 DETAILED RATE ANALYSIS'!J446 -> 44.978119 | Q20: ='04 DETAILED RATE ANALYSIS'!J447 -> 56.222648 | R20: ='04 DETAILED RATE ANALYSIS'!J449 -> 0 | S20: ='04 DETAILED RATE ANALYSIS'!J450 -> 663 | T20: =S20*100 -> 66300 | U20: =IF(W20>0,"INCOMPLETE – "&W20&" blank/old input(s)","Market-derived + assumptions") -> Market-derived + assumptions | V20: Medium | W20: ='04 DETAILED RATE ANALYSIS'!J451 -> 0 | X20: See 09 SOURCE REGISTER (SRC-01…08) | Y20: 2026-04-25 to 2026-09-19 | Z20: see 09 | AA20: House nominal-mix consumption; site-batched. | AB20: =IF(COUNTIF($A$5:$A$999,A20)>1,"DUPLICATE","")
A21: CIV-CON-017 | B21: Civil | C21: Concrete | D21: Nominal 1:2:4 | E21: Providing and laying reinforced cement concrete 1:2:4 (nominal volumetric, site-mixed) using OPC, Chenab sand and Margalla crush, including mixing, placing, compacting and curing, complete in all respects; excluding reinforcement and formwork measured separately. | F21: Nominal volumetric 1:2:4, dry factor 1.54, 1 bag = 1.25 cft (house standard); Lahore basis sand | G21: cft | H21: =City -> Lahore | I21: 2026-09-27 | J21: ='04 DETAILED RATE ANALYSIS'!J463 -> 473.8184 | K21: ='04 DETAILED RATE ANALYSIS'!J466 -> 145.04 | L21: ='04 DETAILED RATE ANALYSIS'!J467 -> 37.27 | M21: ='04 DETAILED RATE ANALYSIS'!J468 -> 0 | N21: ='04 DETAILED RATE ANALYSIS'!J464 -> 15.224 | O21: ='04 DETAILED RATE ANALYSIS'!J469 -> 671.3524 | P21: ='04 DETAILED RATE ANALYSIS'!J470+'04 DETAILED RATE ANALYSIS'!J471 -> 53.708192 | Q21: ='04 DETAILED RATE ANALYSIS'!J472 -> 67.13524 | R21: ='04 DETAILED RATE ANALYSIS'!J474 -> 0 | S21: ='04 DETAILED RATE ANALYSIS'!J475 -> 792 | T21: =S21*100 -> 79200 | U21: =IF(W21>0,"INCOMPLETE – "&W21&" blank/old input(s)","Market-derived + assumptions") -> Market-derived + assumptions | V21: Medium | W21: ='04 DETAILED RATE ANALYSIS'!J476 -> 0 | X21: See 09 SOURCE REGISTER (SRC-01…08) | Y21: 2026-04-25 to 2026-09-19 | Z21: see 09 | AA21: House nominal-mix consumption; site-batched. | AB21: =IF(COUNTIF($A$5:$A$999,A21)>1,"DUPLICATE","")
A22: CIV-CON-018 | B22: Civil | C22: Concrete | D22: Nominal 1:1.5:3 | E22: Providing and laying reinforced cement concrete 1:1.5:3 (nominal volumetric, site-mixed) using OPC, Chenab sand and Margalla crush, including mixing, placing, compacting and curing, complete in all respects; excluding reinforcement and formwork measured separately. | F22: Nominal volumetric 1:1.5:3, dry factor 1.54, 1 bag = 1.25 cft (house standard); Lahore basis sand | G22: cft | H22: =City -> Lahore | I22: 2026-09-27 | J22: ='04 DETAILED RATE ANALYSIS'!J488 -> 541.4416 | K22: ='04 DETAILED RATE ANALYSIS'!J491 -> 145.04 | L22: ='04 DETAILED RATE ANALYSIS'!J492 -> 37.27 | M22: ='04 DETAILED RATE ANALYSIS'!J493 -> 0 | N22: ='04 DETAILED RATE ANALYSIS'!J489 -> 16.296 | O22: ='04 DETAILED RATE ANALYSIS'!J494 -> 740.0476 | P22: ='04 DETAILED RATE ANALYSIS'!J495+'04 DETAILED RATE ANALYSIS'!J496 -> 59.203808 | Q22: ='04 DETAILED RATE ANALYSIS'!J497 -> 74.00476 | R22: ='04 DETAILED RATE ANALYSIS'!J499 -> 0 | S22: ='04 DETAILED RATE ANALYSIS'!J500 -> 873 | T22: =S22*100 -> 87300 | U22: =IF(W22>0,"INCOMPLETE – "&W22&" blank/old input(s)","Market-derived + assumptions") -> Market-derived + assumptions | V22: Medium | W22: ='04 DETAILED RATE ANALYSIS'!J501 -> 0 | X22: See 09 SOURCE REGISTER (SRC-01…08) | Y22: 2026-04-25 to 2026-09-19 | Z22: see 09 | AA22: House nominal-mix consumption; site-batched. | AB22: =IF(COUNTIF($A$5:$A$999,A22)>1,"DUPLICATE","")
A23: CIV-RFT-001 | B23: Civil | C23: Reinforcement | D23: Gr.60 deformed | E23: Providing, cutting, bending and fixing Grade 60 deformed steel reinforcement including binding wire, chairs and spacers, complete in all respects. | F23: ASTM A615 Gr.60; laps measured in BBS; 3% cutting wastage | G23: kg | H23: =City -> Lahore | I23: 2026-09-27 | J23: ='04 DETAILED RATE ANALYSIS'!J509 -> 245.45 | K23: ='04 DETAILED RATE ANALYSIS'!J512 -> 11.077778 | L23: ='04 DETAILED RATE ANALYSIS'!J513 -> 0 | M23: ='04 DETAILED RATE ANALYSIS'!J514 -> 0 | N23: ='04 DETAILED RATE ANALYSIS'!J510 -> 7.26 | O23: ='04 DETAILED RATE ANALYSIS'!J515 -> 263.78778 | P23: ='04 DETAILED RATE ANALYSIS'!J516+'04 DETAILED RATE ANALYSIS'!J517 -> 21.103022 | Q23: ='04 DETAILED RATE ANALYSIS'!J518 -> 26.378778 | R23: ='04 DETAILED RATE ANALYSIS'!J520 -> 0 | S23: ='04 DETAILED RATE ANALYSIS'!J521 -> 311 | T23: =S23*100 -> 31100 | U23: =IF(W23>0,"INCOMPLETE – "&W23&" blank/old input(s)","Market-derived + assumptions") -> Market-derived + assumptions | V23: Medium | W23: ='04 DETAILED RATE ANALYSIS'!J522 -> 0 | X23: See 09 SOURCE REGISTER (SRC-01…08) | Y23: 2026-04-25 to 2026-09-19 | Z23: see 09 | AA23: Binding-wire rate blank. | AB23: =IF(COUNTIF($A$5:$A$999,A23)>1,"DUPLICATE","")
A24: CIV-MAS-001 | B24: Civil | C24: Masonry | D24: Brick 9" & above | E24: Providing and laying first class burnt brick masonry 9" thick and above in cement sand mortar 1:6 in superstructure, including scaffolding, curing, complete in all respects. | F24: Brick 9"×4.5"×3"; 13.5 bricks/cft; wet mortar 0.25 cft/cft × DryF_Mortar | G24: cft | H24: =City -> Lahore | I24: 2026-09-27 | J24: ='04 DETAILED RATE ANALYSIS'!J531 -> 317.03571 | K24: ='04 DETAILED RATE ANALYSIS'!J534 -> 90.14 | L24: ='04 DETAILED RATE ANALYSIS'!J535 -> 0 | M24: ='04 DETAILED RATE ANALYSIS'!J536 -> 0 | N24: ='04 DETAILED RATE ANALYSIS'!J532 -> 14.096786 | O24: ='04 DETAILED RATE ANALYSIS'!J537 -> 421.2725 | P24: ='04 DETAILED RATE ANALYSIS'!J538+'04 DETAILED RATE ANALYSIS'!J539 -> 33.7018 | Q24: ='04 DETAILED RATE ANALYSIS'!J540 -> 42.12725 | R24: ='04 DETAILED RATE ANALYSIS'!J542 -> 0 | S24: ='04 DETAILED RATE ANALYSIS'!J543 -> 497 | T24: =S24*100 -> 49700 | U24: =IF(W24>0,"INCOMPLETE – "&W24&" blank/old input(s)","Market-derived + assumptions") -> Market-derived + assumptions | V24: Medium | W24: ='04 DETAILED RATE ANALYSIS'!J544 -> 0 | X24: See 09 SOURCE REGISTER (SRC-01…08) | Y24: 2026-04-25 to 2026-09-19 | Z24: see 09 | AA24: Scaffolding for elevation work above GF to be added separately (house rule). | AB24: =IF(COUNTIF($A$5:$A$999,A24)>1,"DUPLICATE","")
A25: FIN-PLS-001 | B25: Finishes | C25: Plaster | D25: 0.5" cement plaster 1:4 | E25: Providing and applying 0.5" thick cement sand plaster 1:4 to walls, internal, including curing, complete in all respects. | F25: Thickness 0.0417 ft + 20% for undulations; dry factor 1.30 | G25: Sft | H25: =City -> Lahore | I25: 2026-09-27 | J25: ='04 DETAILED RATE ANALYSIS'!J552 -> 20.54 | K25: ='04 DETAILED RATE ANALYSIS'!J555 -> 36.88 | L25: ='04 DETAILED RATE ANALYSIS'!J556 -> 0 | M25: ='04 DETAILED RATE ANALYSIS'!J557 -> 0 | N25: ='04 DETAILED RATE ANALYSIS'!J553 -> 0.5356 | O25: ='04 DETAILED RATE ANALYSIS'!J558 -> 57.9556 | P25: ='04 DETAILED RATE ANALYSIS'!J559+'04 DETAILED RATE ANALYSIS'!J560 -> 4.636448 | Q25: ='04 DETAILED RATE ANALYSIS'!J561 -> 5.79556 | R25: ='04 DETAILED RATE ANALYSIS'!J563 -> 0 | S25: ='04 DETAILED RATE ANALYSIS'!J564 -> 68 | T25: =S25*100 -> 6800 | U25: =IF(W25>0,"INCOMPLETE – "&W25&" blank/old input(s)","Market-derived + assumptions") -> Market-derived + assumptions | V25: Medium | W25: ='04 DETAILED RATE ANALYSIS'!J565 -> 0 | X25: See 09 SOURCE REGISTER (SRC-01…08) | Y25: 2026-04-25 to 2026-09-19 | Z25: see 09 | AA25: Internal only – external elevation adds scaffold/cradle item. | AB25: =IF(COUNTIF($A$5:$A$999,A25)>1,"DUPLICATE","")
A26: FIN-PLS-002 | B26: Finishes | C26: Plaster | D26: 0.75" cement plaster 1:6 | E26: Providing and applying 0.75" thick cement sand plaster 1:6 to walls, internal, including curing, complete in all respects. | F26: Thickness 0.0625 ft + 20% for undulations; dry factor 1.30 | G26: Sft | H26: =City -> Lahore | I26: 2026-09-27 | J26: ='04 DETAILED RATE ANALYSIS'!J573 -> 24.235714 | K26: ='04 DETAILED RATE ANALYSIS'!J576 -> 46.1 | L26: ='04 DETAILED RATE ANALYSIS'!J577 -> 0 | M26: ='04 DETAILED RATE ANALYSIS'!J578 -> 0 | N26: ='04 DETAILED RATE ANALYSIS'!J574 -> 0.68528571 | O26: ='04 DETAILED RATE ANALYSIS'!J579 -> 71.021 | P26: ='04 DETAILED RATE ANALYSIS'!J580+'04 DETAILED RATE ANALYSIS'!J581 -> 5.68168 | Q26: ='04 DETAILED RATE ANALYSIS'!J582 -> 7.1021 | R26: ='04 DETAILED RATE ANALYSIS'!J584 -> 0 | S26: ='04 DETAILED RATE ANALYSIS'!J585 -> 84 | T26: =S26*100 -> 8400 | U26: =IF(W26>0,"INCOMPLETE – "&W26&" blank/old input(s)","Market-derived + assumptions") -> Market-derived + assumptions | V26: Medium | W26: ='04 DETAILED RATE ANALYSIS'!J586 -> 0 | X26: See 09 SOURCE REGISTER (SRC-01…08) | Y26: 2026-04-25 to 2026-09-19 | Z26: see 09 | AA26: Internal only – external elevation adds scaffold/cradle item. | AB26: =IF(COUNTIF($A$5:$A$999,A26)>1,"DUPLICATE","")
A27: CIV-FWK-001 | B27: Civil | C27: Formwork | D27: Slab soffit | E27: Providing, erecting and stripping plywood formwork to horizontal soffit of slabs incl. staging/props, including release oil, cleaning and repairs, complete in all respects; measured as contact area. | F27: 3/4" plywood, Reuse_Ply uses; timber Reuse_Tim uses; ground-floor base, no floor premium | G27: Sft | H27: =City -> Lahore | I27: 2026-09-27 | J27: ='04 DETAILED RATE ANALYSIS'!J597 -> 50.835833 | K27: ='04 DETAILED RATE ANALYSIS'!J600 -> 26.253333 | L27: ='04 DETAILED RATE ANALYSIS'!J601 -> 10 | M27: ='04 DETAILED RATE ANALYSIS'!J602 -> 0 | N27: ='04 DETAILED RATE ANALYSIS'!J598 -> 2.8645833 | O27: ='04 DETAILED RATE ANALYSIS'!J603 -> 89.95375 | P27: ='04 DETAILED RATE ANALYSIS'!J604+'04 DETAILED RATE ANALYSIS'!J605 -> 7.1963 | Q27: ='04 DETAILED RATE ANALYSIS'!J606 -> 8.995375 | R27: ='04 DETAILED RATE ANALYSIS'!J608 -> 0 | S27: ='04 DETAILED RATE ANALYSIS'!J609 -> 106 | T27: =S27*100 -> 10600 | U27: =IF(W27>0,"INCOMPLETE – "&W27&" blank/old input(s)","Market-derived + assumptions") -> Market-derived + assumptions | V27: Low | W27: ='04 DETAILED RATE ANALYSIS'!J610 -> 0 | X27: See 09 SOURCE REGISTER (SRC-01…08) | Y27: 2026-04-25 to 2026-09-19 | Z27: see 09 | AA27: Rate depends on repetitions (10 ASSUMPTIONS). Timber rate is OLD (Feb-2025). | AB27: =IF(COUNTIF($A$5:$A$999,A27)>1,"DUPLICATE","")
A28: CIV-FWK-002 | B28: Civil | C28: Formwork | D28: Beam sides & soffit | E28: Providing, erecting and stripping plywood formwork to beam sides and soffits incl. props, including release oil, cleaning and repairs, complete in all respects; measured as contact area. | F28: 3/4" plywood, Reuse_Ply uses; timber Reuse_Tim uses; ground-floor base, no floor premium | G28: Sft | H28: =City -> Lahore | I28: 2026-09-27 | J28: ='04 DETAILED RATE ANALYSIS'!J621 -> 54.515833 | K28: ='04 DETAILED RATE ANALYSIS'!J624 -> 39.38 | L28: ='04 DETAILED RATE ANALYSIS'!J625 -> 10 | M28: ='04 DETAILED RATE ANALYSIS'!J626 -> 0 | N28: ='04 DETAILED RATE ANALYSIS'!J622 -> 2.8645833 | O28: ='04 DETAILED RATE ANALYSIS'!J627 -> 106.76042 | P28: ='04 DETAILED RATE ANALYSIS'!J628+'04 DETAILED RATE ANALYSIS'!J629 -> 8.5408333 | Q28: ='04 DETAILED RATE ANALYSIS'!J630 -> 10.676042 | R28: ='04 DETAILED RATE ANALYSIS'!J632 -> 0 | S28: ='04 DETAILED RATE ANALYSIS'!J633 -> 126 | T28: =S28*100 -> 12600 | U28: =IF(W28>0,"INCOMPLETE – "&W28&" blank/old input(s)","Market-derived + assumptions") -> Market-derived + assumptions | V28: Low | W28: ='04 DETAILED RATE ANALYSIS'!J634 -> 0 | X28: See 09 SOURCE REGISTER (SRC-01…08) | Y28: 2026-04-25 to 2026-09-19 | Z28: see 09 | AA28: Rate depends on repetitions (10 ASSUMPTIONS). Timber rate is OLD (Feb-2025). | AB28: =IF(COUNTIF($A$5:$A$999,A28)>1,"DUPLICATE","")
A29: CIV-FWK-003 | B29: Civil | C29: Formwork | D29: Columns | E29: Providing, erecting and stripping plywood formwork to column faces incl. yokes, ties and bracing, including release oil, cleaning and repairs, complete in all respects; measured as contact area. | F29: 3/4" plywood, Reuse_Ply uses; timber Reuse_Tim uses; ground-floor base, no floor premium | G29: Sft | H29: =City -> Lahore | I29: 2026-09-27 | J29: ='04 DETAILED RATE ANALYSIS'!J644 -> 52.675833 | K29: ='04 DETAILED RATE ANALYSIS'!J647 -> 32.816667 | L29: ='04 DETAILED RATE ANALYSIS'!J648 -> 0 | M29: ='04 DETAILED RATE ANALYSIS'!J649 -> 0 | N29: ='04 DETAILED RATE ANALYSIS'!J645 -> 2.8645833 | O29: ='04 DETAILED RATE ANALYSIS'!J650 -> 88.357083 | P29: ='04 DETAILED RATE ANALYSIS'!J651+'04 DETAILED RATE ANALYSIS'!J652 -> 7.0685667 | Q29: ='04 DETAILED RATE ANALYSIS'!J653 -> 8.8357083 | R29: ='04 DETAILED RATE ANALYSIS'!J655 -> 0 | S29: ='04 DETAILED RATE ANALYSIS'!J656 -> 104 | T29: =S29*100 -> 10400 | U29: =IF(W29>0,"INCOMPLETE – "&W29&" blank/old input(s)","Market-derived + assumptions") -> Market-derived + assumptions | V29: Low | W29: ='04 DETAILED RATE ANALYSIS'!J657 -> 0 | X29: See 09 SOURCE REGISTER (SRC-01…08) | Y29: 2026-04-25 to 2026-09-19 | Z29: see 09 | AA29: Rate depends on repetitions (10 ASSUMPTIONS). Timber rate is OLD (Feb-2025). | AB29: =IF(COUNTIF($A$5:$A$999,A29)>1,"DUPLICATE","")
A30: CIV-FWK-004 | B30: Civil | C30: Formwork | D30: Walls / shear walls / lift core | E30: Providing, erecting and stripping plywood formwork to wall faces (each face measured) incl. ties and bracing, including release oil, cleaning and repairs, complete in all respects; measured as contact area. | F30: 3/4" plywood, Reuse_Ply uses; timber Reuse_Tim uses; ground-floor base, no floor premium | G30: Sft | H30: =City -> Lahore | I30: 2026-09-27 | J30: ='04 DETAILED RATE ANALYSIS'!J667 -> 54.515833 | K30: ='04 DETAILED RATE ANALYSIS'!J670 -> 30.292308 | L30: ='04 DETAILED RATE ANALYSIS'!J671 -> 0 | M30: ='04 DETAILED RATE ANALYSIS'!J672 -> 0 | N30: ='04 DETAILED RATE ANALYSIS'!J668 -> 2.8645833 | O30: ='04 DETAILED RATE ANALYSIS'!J673 -> 87.672724 | P30: ='04 DETAILED RATE ANALYSIS'!J674+'04 DETAILED RATE ANALYSIS'!J675 -> 7.0138179 | Q30: ='04 DETAILED RATE ANALYSIS'!J676 -> 8.7672724 | R30: ='04 DETAILED RATE ANALYSIS'!J678 -> 0 | S30: ='04 DETAILED RATE ANALYSIS'!J679 -> 103 | T30: =S30*100 -> 10300 | U30: =IF(W30>0,"INCOMPLETE – "&W30&" blank/old input(s)","Market-derived + assumptions") -> Market-derived + assumptions | V30: Low | W30: ='04 DETAILED RATE ANALYSIS'!J680 -> 0 | X30: See 09 SOURCE REGISTER (SRC-01…08) | Y30: 2026-04-25 to 2026-09-19 | Z30: see 09 | AA30: Rate depends on repetitions (10 ASSUMPTIONS). Timber rate is OLD (Feb-2025). | AB30: =IF(COUNTIF($A$5:$A$999,A30)>1,"DUPLICATE","")
A31: CIV-MAS-003 | B31: Civil | C31: Masonry | D31: 8" hollow block | E31: Providing and laying 8" hollow block masonry 8" thick in cement sand mortar 1:6 in walls and partitions, including curing, complete in all respects; openings >1.0 Sft deducted. | F31: Block 16"x8"x8"; 3/8" joints; hollow cores unfilled; lintels/bond beams measured separately | G31: Sft | H31: =City -> Lahore | I31: 2026-09-27 | J31: ='04 DETAILED RATE ANALYSIS'!J689 -> 234.86222 | K31: ='04 DETAILED RATE ANALYSIS'!J692 -> 37.38 | L31: ='04 DETAILED RATE ANALYSIS'!J693 -> 0 | M31: ='04 DETAILED RATE ANALYSIS'!J694 -> 0 | N31: ='04 DETAILED RATE ANALYSIS'!J690 -> 11.431182 | O31: ='04 DETAILED RATE ANALYSIS'!J695 -> 283.6734 | P31: ='04 DETAILED RATE ANALYSIS'!J696+'04 DETAILED RATE ANALYSIS'!J697 -> 22.693872 | Q31: ='04 DETAILED RATE ANALYSIS'!J698 -> 28.36734 | R31: ='04 DETAILED RATE ANALYSIS'!J700 -> 0 | S31: ='04 DETAILED RATE ANALYSIS'!J701 -> 335 | T31: =S31*100 -> 33500 | U31: =IF(W31>0,"INCOMPLETE – "&W31&" blank/old input(s)","Market-derived + assumptions") -> Market-derived + assumptions | V31: Medium | W31: ='04 DETAILED RATE ANALYSIS'!J702 -> 0 | X31: See 09 SOURCE REGISTER (SRC-01…08) | Y31: 2026-04-25 to 2026-09-19 | Z31: see 09 | AA31: Block rate ex-factory per SRC-09 – check freight. Scaffold for elevation work extra. | AB31: =IF(COUNTIF($A$5:$A$999,A31)>1,"DUPLICATE","")
A32: CIV-MAS-004 | B32: Civil | C32: Masonry | D32: 6" hollow block | E32: Providing and laying 6" hollow block masonry 6" thick in cement sand mortar 1:6 in walls and partitions, including curing, complete in all respects; openings >1.0 Sft deducted. | F32: Block 16"x6"x8"; 3/8" joints; hollow cores unfilled; lintels/bond beams measured separately | G32: Sft | H32: =City -> Lahore | I32: 2026-09-27 | J32: ='04 DETAILED RATE ANALYSIS'!J711 -> 184.02179 | K32: ='04 DETAILED RATE ANALYSIS'!J714 -> 31.15 | L32: ='04 DETAILED RATE ANALYSIS'!J715 -> 0 | M32: ='04 DETAILED RATE ANALYSIS'!J716 -> 0 | N32: ='04 DETAILED RATE ANALYSIS'!J712 -> 8.967143 | O32: ='04 DETAILED RATE ANALYSIS'!J717 -> 224.13894 | P32: ='04 DETAILED RATE ANALYSIS'!J718+'04 DETAILED RATE ANALYSIS'!J719 -> 17.931115 | Q32: ='04 DETAILED RATE ANALYSIS'!J720 -> 22.413894 | R32: ='04 DETAILED RATE ANALYSIS'!J722 -> 0 | S32: ='04 DETAILED RATE ANALYSIS'!J723 -> 264 | T32: =S32*100 -> 26400 | U32: =IF(W32>0,"INCOMPLETE – "&W32&" blank/old input(s)","Market-derived + assumptions") -> Market-derived + assumptions | V32: Medium | W32: ='04 DETAILED RATE ANALYSIS'!J724 -> 0 | X32: See 09 SOURCE REGISTER (SRC-01…08) | Y32: 2026-04-25 to 2026-09-19 | Z32: see 09 | AA32: Block rate ex-factory per SRC-09 – check freight. Scaffold for elevation work extra. | AB32: =IF(COUNTIF($A$5:$A$999,A32)>1,"DUPLICATE","")
A33: CIV-MAS-005 | B33: Civil | C33: Masonry | D33: 4" solid block | E33: Providing and laying 4" solid block masonry 4" thick in cement sand mortar 1:6 in walls and partitions, including curing, complete in all respects; openings >1.0 Sft deducted. | F33: Block 12"x4"x8"; 3/8" joints; hollow cores unfilled; lintels/bond beams measured separately | G33: Sft | H33: =City -> Lahore | I33: 2026-09-27 | J33: ='04 DETAILED RATE ANALYSIS'!J733 -> 202.45926 | K33: ='04 DETAILED RATE ANALYSIS'!J736 -> 24.92 | L33: ='04 DETAILED RATE ANALYSIS'!J737 -> 0 | M33: ='04 DETAILED RATE ANALYSIS'!J738 -> 0 | N33: ='04 DETAILED RATE ANALYSIS'!J734 -> 9.9504529 | O33: ='04 DETAILED RATE ANALYSIS'!J739 -> 237.32972 | P33: ='04 DETAILED RATE ANALYSIS'!J740+'04 DETAILED RATE ANALYSIS'!J741 -> 18.986377 | Q33: ='04 DETAILED RATE ANALYSIS'!J742 -> 23.732972 | R33: ='04 DETAILED RATE ANALYSIS'!J744 -> 0 | S33: ='04 DETAILED RATE ANALYSIS'!J745 -> 280 | T33: =S33*100 -> 28000 | U33: =IF(W33>0,"INCOMPLETE – "&W33&" blank/old input(s)","Market-derived + assumptions") -> Market-derived + assumptions | V33: Medium | W33: ='04 DETAILED RATE ANALYSIS'!J746 -> 0 | X33: See 09 SOURCE REGISTER (SRC-01…08) | Y33: 2026-04-25 to 2026-09-19 | Z33: see 09 | AA33: Block rate ex-factory per SRC-09 – check freight. Scaffold for elevation work extra. | AB33: =IF(COUNTIF($A$5:$A$999,A33)>1,"DUPLICATE","")
A34: CIV-MAS-002 | B34: Civil | C34: Masonry | D34: Brick 4.5" | E34: Providing and laying first class burnt brick masonry 4.5" thick in cement sand mortar 1:4 in partitions, including curing, complete in all respects. | F34: 0.375 ft thick; 13.5 bricks/cft; wet mortar 0.25 cft/cft | G34: Sft | H34: =City -> Lahore | I34: 2026-09-27 | J34: ='04 DETAILED RATE ANALYSIS'!J755 -> 127.10625 | K34: ='04 DETAILED RATE ANALYSIS'!J758 -> 31.15 | L34: ='04 DETAILED RATE ANALYSIS'!J759 -> 0 | M34: ='04 DETAILED RATE ANALYSIS'!J760 -> 0 | N34: ='04 DETAILED RATE ANALYSIS'!J756 -> 5.4339375 | O34: ='04 DETAILED RATE ANALYSIS'!J761 -> 163.69019 | P34: ='04 DETAILED RATE ANALYSIS'!J762+'04 DETAILED RATE ANALYSIS'!J763 -> 13.095215 | Q34: ='04 DETAILED RATE ANALYSIS'!J764 -> 16.369019 | R34: ='04 DETAILED RATE ANALYSIS'!J766 -> 0 | S34: ='04 DETAILED RATE ANALYSIS'!J767 -> 193 | T34: =S34*100 -> 19300 | U34: =IF(W34>0,"INCOMPLETE – "&W34&" blank/old input(s)","Market-derived + assumptions") -> Market-derived + assumptions | V34: Medium | W34: ='04 DETAILED RATE ANALYSIS'!J768 -> 0 | X34: See 09 SOURCE REGISTER (SRC-01…08) | Y34: 2026-04-25 to 2026-09-19 | Z34: see 09 | AB34: =IF(COUNTIF($A$5:$A$999,A34)>1,"DUPLICATE","")
A35: FIN-SCR-001 | B35: Finishes | C35: Screed | D35: 1.5" screed 1:4 | E35: Providing and laying 1.5" thick cement sand screed 1:4 to floors/roofs, laid to level or falls, including bonding slurry and curing, complete in all respects. | F35: Thickness 0.1250 ft + 5% for level tolerance; dry factor 1.30 | G35: Sft | H35: =City -> Lahore | I35: 2026-09-27 | J35: ='04 DETAILED RATE ANALYSIS'!J776 -> 53.9175 | K35: ='04 DETAILED RATE ANALYSIS'!J779 -> 55.536842 | L35: ='04 DETAILED RATE ANALYSIS'!J780 -> 0 | M35: ='04 DETAILED RATE ANALYSIS'!J781 -> 0 | N35: ='04 DETAILED RATE ANALYSIS'!J777 -> 1.40595 | O35: ='04 DETAILED RATE ANALYSIS'!J782 -> 110.86029 | P35: ='04 DETAILED RATE ANALYSIS'!J783+'04 DETAILED RATE ANALYSIS'!J784 -> 8.8688234 | Q35: ='04 DETAILED RATE ANALYSIS'!J785 -> 11.086029 | R35: ='04 DETAILED RATE ANALYSIS'!J787 -> 0 | S35: ='04 DETAILED RATE ANALYSIS'!J788 -> 131 | T35: =S35*100 -> 13100 | U35: =IF(W35>0,"INCOMPLETE – "&W35&" blank/old input(s)","Market-derived + assumptions") -> Market-derived + assumptions | V35: Medium | W35: ='04 DETAILED RATE ANALYSIS'!J789 -> 0 | X35: See 09 SOURCE REGISTER (SRC-01…08) | Y35: 2026-04-25 to 2026-09-19 | Z35: see 09 | AA35: Bonding slurry cement included in 5% tolerance. Screed >2" on roofs usually priced as concrete. | AB35: =IF(COUNTIF($A$5:$A$999,A35)>1,"DUPLICATE","")
A36: FIN-SCR-002 | B36: Finishes | C36: Screed | D36: 2.0" screed 1:4 | E36: Providing and laying 2.0" thick cement sand screed 1:4 to floors/roofs, laid to level or falls, including bonding slurry and curing, complete in all respects. | F36: Thickness 0.1667 ft + 5% for level tolerance; dry factor 1.30 | G36: Sft | H36: =City -> Lahore | I36: 2026-09-27 | J36: ='04 DETAILED RATE ANALYSIS'!J797 -> 71.89 | K36: ='04 DETAILED RATE ANALYSIS'!J800 -> 65.95 | L36: ='04 DETAILED RATE ANALYSIS'!J801 -> 0 | M36: ='04 DETAILED RATE ANALYSIS'!J802 -> 0 | N36: ='04 DETAILED RATE ANALYSIS'!J798 -> 1.8746 | O36: ='04 DETAILED RATE ANALYSIS'!J803 -> 139.7146 | P36: ='04 DETAILED RATE ANALYSIS'!J804+'04 DETAILED RATE ANALYSIS'!J805 -> 11.177168 | Q36: ='04 DETAILED RATE ANALYSIS'!J806 -> 13.97146 | R36: ='04 DETAILED RATE ANALYSIS'!J808 -> 0 | S36: ='04 DETAILED RATE ANALYSIS'!J809 -> 165 | T36: =S36*100 -> 16500 | U36: =IF(W36>0,"INCOMPLETE – "&W36&" blank/old input(s)","Market-derived + assumptions") -> Market-derived + assumptions | V36: Medium | W36: ='04 DETAILED RATE ANALYSIS'!J810 -> 0 | X36: See 09 SOURCE REGISTER (SRC-01…08) | Y36: 2026-04-25 to 2026-09-19 | Z36: see 09 | AA36: Bonding slurry cement included in 5% tolerance. Screed >2" on roofs usually priced as concrete. | AB36: =IF(COUNTIF($A$5:$A$999,A36)>1,"DUPLICATE","")
A37: FIN-SCR-003 | B37: Finishes | C37: Screed | D37: 3.0" screed 1:3 | E37: Providing and laying 3.0" thick cement sand screed 1:3 to floors/roofs, laid to level or falls, including bonding slurry and curing, complete in all respects. | F37: Thickness 0.2500 ft + 5% for level tolerance; dry factor 1.30 | G37: Sft | H37: =City -> Lahore | I37: 2026-09-27 | J37: ='04 DETAILED RATE ANALYSIS'!J818 -> 127.96875 | K37: ='04 DETAILED RATE ANALYSIS'!J821 -> 81.169231 | L37: ='04 DETAILED RATE ANALYSIS'!J822 -> 0 | M37: ='04 DETAILED RATE ANALYSIS'!J823 -> 0 | N37: ='04 DETAILED RATE ANALYSIS'!J819 -> 3.173625 | O37: ='04 DETAILED RATE ANALYSIS'!J824 -> 212.31161 | P37: ='04 DETAILED RATE ANALYSIS'!J825+'04 DETAILED RATE ANALYSIS'!J826 -> 16.984928 | Q37: ='04 DETAILED RATE ANALYSIS'!J827 -> 21.231161 | R37: ='04 DETAILED RATE ANALYSIS'!J829 -> 0 | S37: ='04 DETAILED RATE ANALYSIS'!J830 -> 251 | T37: =S37*100 -> 25100 | U37: =IF(W37>0,"INCOMPLETE – "&W37&" blank/old input(s)","Market-derived + assumptions") -> Market-derived + assumptions | V37: Medium | W37: ='04 DETAILED RATE ANALYSIS'!J831 -> 0 | X37: See 09 SOURCE REGISTER (SRC-01…08) | Y37: 2026-04-25 to 2026-09-19 | Z37: see 09 | AA37: Bonding slurry cement included in 5% tolerance. Screed >2" on roofs usually priced as concrete. | AB37: =IF(COUNTIF($A$5:$A$999,A37)>1,"DUPLICATE","")
A38: FIN-WPF-001 | B38: Finishes | C38: Waterproofing | D38: Torch-on APP membrane | E38: Providing and applying one layer 4-thick APP modified bitumen membrane, torch-applied over bitumen primer on roof/terrace slabs incl. upstands, laps and angle fillets, complete in all respects. | F38: Primer 0.023 litre/Sft; membrane with W_Mem laps; protection screed measured separately | G38: Sft | H38: =City -> Lahore | I38: 2026-09-27 | J38: ='04 DETAILED RATE ANALYSIS'!J841 -> 100.5865 | K38: ='04 DETAILED RATE ANALYSIS'!J844 -> 20.766667 | L38: ='04 DETAILED RATE ANALYSIS'!J845 -> 4.4444444 | M38: ='04 DETAILED RATE ANALYSIS'!J846 -> 0 | N38: ='04 DETAILED RATE ANALYSIS'!J842 -> 11.76 | O38: ='04 DETAILED RATE ANALYSIS'!J847 -> 137.55761 | P38: ='04 DETAILED RATE ANALYSIS'!J848+'04 DETAILED RATE ANALYSIS'!J849 -> 11.004609 | Q38: ='04 DETAILED RATE ANALYSIS'!J850 -> 13.755761 | R38: ='04 DETAILED RATE ANALYSIS'!J852 -> 0 | S38: ='04 DETAILED RATE ANALYSIS'!J853 -> 162 | T38: =S38*100 -> 16200 | U38: =IF(W38>0,"INCOMPLETE – "&W38&" blank/old input(s)","Market-derived + assumptions") -> INCOMPLETE – 1 blank/old input(s) | V38: Low | W38: ='04 DETAILED RATE ANALYSIS'!J854 -> 1 | X38: See 09 SOURCE REGISTER (SRC-01…08) | Y38: 2026-04-25 to 2026-09-19 | Z38: see 09 | AA38: Membrane often client-supplied – set MAT-MEM-APP consumption to 0 in that case. | AB38: =IF(COUNTIF($A$5:$A$999,A38)>1,"DUPLICATE","")
A39: FIN-WPF-002 | B39: Finishes | C39: Waterproofing | D39: Cementitious 2 coats | E39: Providing and applying two-coat polymer-modified cementitious waterproofing to toilets, wet areas and tanks, including surface preparation and corner reinforcement, complete in all respects. | F39: Total consumption 0.19 kg/Sft (2 coats) – confirm with product data sheet | G39: Sft | H39: =City -> Lahore | I39: 2026-09-27 | J39: ='04 DETAILED RATE ANALYSIS'!J861 -> 47 | K39: ='04 DETAILED RATE ANALYSIS'!J864 -> 12.46 | L39: ='04 DETAILED RATE ANALYSIS'!J865 -> 0 | M39: ='04 DETAILED RATE ANALYSIS'!J866 -> 0 | N39: ='04 DETAILED RATE ANALYSIS'!J862 -> 2.35 | O39: ='04 DETAILED RATE ANALYSIS'!J867 -> 61.81 | P39: ='04 DETAILED RATE ANALYSIS'!J868+'04 DETAILED RATE ANALYSIS'!J869 -> 4.9448 | Q39: ='04 DETAILED RATE ANALYSIS'!J870 -> 6.181 | R39: ='04 DETAILED RATE ANALYSIS'!J872 -> 0 | S39: ='04 DETAILED RATE ANALYSIS'!J873 -> 73 | T39: =S39*100 -> 7300 | U39: =IF(W39>0,"INCOMPLETE – "&W39&" blank/old input(s)","Market-derived + assumptions") -> INCOMPLETE – 1 blank/old input(s) | V39: Low | W39: ='04 DETAILED RATE ANALYSIS'!J874 -> 1 | X39: See 09 SOURCE REGISTER (SRC-01…08) | Y39: 2026-04-25 to 2026-09-19 | Z39: see 09 | AB39: =IF(COUNTIF($A$5:$A$999,A39)>1,"DUPLICATE","")
A40: FIN-WPF-003 | B40: Finishes | C40: Waterproofing | D40: DPC 1.5" + bitumen | E40: Providing and laying 1.5" thick damp proof course in cement concrete 1:2:4 with two coats of hot bitumen at plinth level, complete in all respects. | F40: 0.125 cft concrete per Sft; hot bitumen 0.10 kg/Sft (2 coats) | G40: Sft | H40: =City -> Lahore | I40: 2026-09-27 | J40: ='04 DETAILED RATE ANALYSIS'!J884 -> 78.6 | K40: ='04 DETAILED RATE ANALYSIS'!J887 -> 42.208 | L40: ='04 DETAILED RATE ANALYSIS'!J888 -> 0 | M40: ='04 DETAILED RATE ANALYSIS'!J889 -> 0 | N40: ='04 DETAILED RATE ANALYSIS'!J885 -> 1.903 | O40: ='04 DETAILED RATE ANALYSIS'!J890 -> 122.711 | P40: ='04 DETAILED RATE ANALYSIS'!J891+'04 DETAILED RATE ANALYSIS'!J892 -> 9.81688 | Q40: ='04 DETAILED RATE ANALYSIS'!J893 -> 12.2711 | R40: ='04 DETAILED RATE ANALYSIS'!J895 -> 0 | S40: ='04 DETAILED RATE ANALYSIS'!J896 -> 145 | T40: =S40*100 -> 14500 | U40: =IF(W40>0,"INCOMPLETE – "&W40&" blank/old input(s)","Market-derived + assumptions") -> Market-derived + assumptions | V40: Low | W40: ='04 DETAILED RATE ANALYSIS'!J897 -> 0 | X40: See 09 SOURCE REGISTER (SRC-01…08) | Y40: 2026-04-25 to 2026-09-19 | Z40: see 09 | AB40: =IF(COUNTIF($A$5:$A$999,A40)>1,"DUPLICATE","")
A41: FIN-FLR-001 | B41: Finishes | C41: Flooring | D41: Porcelain 24"x24" | E41: Providing and laying 24"x24" porcelain floor tiles of approved make on cementitious tile adhesive over prepared screed, including grouting, cleaning and protection, complete in all respects. | F41: Tile per selected product (PC); adhesive 1/60; 1/8" joints | G41: Sft | H41: =City -> Lahore | I41: 2026-09-27 | J41: ='04 DETAILED RATE ANALYSIS'!J906 -> 225.83333 | K41: ='04 DETAILED RATE ANALYSIS'!J909 -> 33.65 | L41: ='04 DETAILED RATE ANALYSIS'!J910 -> 0 | M41: ='04 DETAILED RATE ANALYSIS'!J911 -> 0 | N41: ='04 DETAILED RATE ANALYSIS'!J907 -> 15.171667 | O41: ='04 DETAILED RATE ANALYSIS'!J912 -> 274.655 | P41: ='04 DETAILED RATE ANALYSIS'!J913+'04 DETAILED RATE ANALYSIS'!J914 -> 21.9724 | Q41: ='04 DETAILED RATE ANALYSIS'!J915 -> 27.4655 | R41: ='04 DETAILED RATE ANALYSIS'!J917 -> 0 | S41: ='04 DETAILED RATE ANALYSIS'!J918 -> 324 | T41: =S41*100 -> 32400 | U41: =IF(W41>0,"INCOMPLETE – "&W41&" blank/old input(s)","Market-derived + assumptions") -> Market-derived + assumptions | V41: Medium | W41: ='04 DETAILED RATE ANALYSIS'!J919 -> 0 | X41: See 09 SOURCE REGISTER (SRC-01…08) | Y41: 2026-04-25 to 2026-09-19 | Z41: see 09 | AA41: Tile rate is a PC rate – set to selected series. Screed measured separately. | AB41: =IF(COUNTIF($A$5:$A$999,A41)>1,"DUPLICATE","")
A42: FIN-FLR-002 | B42: Finishes | C42: Flooring | D42: Ceramic floor tile | E42: Providing and laying ceramic floor tiles of approved make on cementitious tile adhesive over prepared screed, including grouting, cleaning and protection, complete in all respects. | F42: Tile per selected product (PC); adhesive 1/60; 1/8" joints | G42: Sft | H42: =City -> Lahore | I42: 2026-09-27 | J42: ='04 DETAILED RATE ANALYSIS'!J928 -> 141.83333 | K42: ='04 DETAILED RATE ANALYSIS'!J931 -> 33.65 | L42: ='04 DETAILED RATE ANALYSIS'!J932 -> 0 | M42: ='04 DETAILED RATE ANALYSIS'!J933 -> 0 | N42: ='04 DETAILED RATE ANALYSIS'!J929 -> 9.2916667 | O42: ='04 DETAILED RATE ANALYSIS'!J934 -> 184.775 | P42: ='04 DETAILED RATE ANALYSIS'!J935+'04 DETAILED RATE ANALYSIS'!J936 -> 14.782 | Q42: ='04 DETAILED RATE ANALYSIS'!J937 -> 18.4775 | R42: ='04 DETAILED RATE ANALYSIS'!J939 -> 0 | S42: ='04 DETAILED RATE ANALYSIS'!J940 -> 218 | T42: =S42*100 -> 21800 | U42: =IF(W42>0,"INCOMPLETE – "&W42&" blank/old input(s)","Market-derived + assumptions") -> Market-derived + assumptions | V42: Medium | W42: ='04 DETAILED RATE ANALYSIS'!J941 -> 0 | X42: See 09 SOURCE REGISTER (SRC-01…08) | Y42: 2026-04-25 to 2026-09-19 | Z42: see 09 | AA42: Tile rate is a PC rate – set to selected series. Screed measured separately. | AB42: =IF(COUNTIF($A$5:$A$999,A42)>1,"DUPLICATE","")
A43: FIN-WAL-001 | B43: Finishes | C43: Wall finishes | D43: Ceramic wall tile | E43: Providing and fixing ceramic wall tiles of approved make on cementitious tile adhesive over plastered surface, including grouting, cutting around fixtures and cleaning, complete in all respects. | F43: Tile per selected product (PC); adhesive 1/90; 1/8" joints | G43: Sft | H43: =City -> Lahore | I43: 2026-09-27 | J43: ='04 DETAILED RATE ANALYSIS'!J950 -> 138.22222 | K43: ='04 DETAILED RATE ANALYSIS'!J953 -> 40.38 | L43: ='04 DETAILED RATE ANALYSIS'!J954 -> 0 | M43: ='04 DETAILED RATE ANALYSIS'!J955 -> 0 | N43: ='04 DETAILED RATE ANALYSIS'!J951 -> 9.1111111 | O43: ='04 DETAILED RATE ANALYSIS'!J956 -> 187.71333 | P43: ='04 DETAILED RATE ANALYSIS'!J957+'04 DETAILED RATE ANALYSIS'!J958 -> 15.017067 | Q43: ='04 DETAILED RATE ANALYSIS'!J959 -> 18.771333 | R43: ='04 DETAILED RATE ANALYSIS'!J961 -> 0 | S43: ='04 DETAILED RATE ANALYSIS'!J962 -> 222 | T43: =S43*100 -> 22200 | U43: =IF(W43>0,"INCOMPLETE – "&W43&" blank/old input(s)","Market-derived + assumptions") -> Market-derived + assumptions | V43: Medium | W43: ='04 DETAILED RATE ANALYSIS'!J963 -> 0 | X43: See 09 SOURCE REGISTER (SRC-01…08) | Y43: 2026-04-25 to 2026-09-19 | Z43: see 09 | AA43: Tile rate is a PC rate – set to selected series. Screed measured separately. | AB43: =IF(COUNTIF($A$5:$A$999,A43)>1,"DUPLICATE","")
A44: FIN-WAL-002 | B44: Finishes | C44: Wall finishes | D44: Porcelain wall tile | E44: Providing and fixing porcelain wall tiles of approved make on cementitious tile adhesive, including grouting and cleaning, complete in all respects. | F44: Tile per selected product (PC); adhesive 1/90; 1/8" joints | G44: Sft | H44: =City -> Lahore | I44: 2026-09-27 | J44: ='04 DETAILED RATE ANALYSIS'!J972 -> 222.22222 | K44: ='04 DETAILED RATE ANALYSIS'!J975 -> 40.38 | L44: ='04 DETAILED RATE ANALYSIS'!J976 -> 0 | M44: ='04 DETAILED RATE ANALYSIS'!J977 -> 0 | N44: ='04 DETAILED RATE ANALYSIS'!J973 -> 14.991111 | O44: ='04 DETAILED RATE ANALYSIS'!J978 -> 277.59333 | P44: ='04 DETAILED RATE ANALYSIS'!J979+'04 DETAILED RATE ANALYSIS'!J980 -> 22.207467 | Q44: ='04 DETAILED RATE ANALYSIS'!J981 -> 27.759333 | R44: ='04 DETAILED RATE ANALYSIS'!J983 -> 0 | S44: ='04 DETAILED RATE ANALYSIS'!J984 -> 328 | T44: =S44*100 -> 32800 | U44: =IF(W44>0,"INCOMPLETE – "&W44&" blank/old input(s)","Market-derived + assumptions") -> Market-derived + assumptions | V44: Medium | W44: ='04 DETAILED RATE ANALYSIS'!J985 -> 0 | X44: See 09 SOURCE REGISTER (SRC-01…08) | Y44: 2026-04-25 to 2026-09-19 | Z44: see 09 | AA44: Tile rate is a PC rate – set to selected series. Screed measured separately. | AB44: =IF(COUNTIF($A$5:$A$999,A44)>1,"DUPLICATE","")
A45: FIN-FLR-003 | B45: Finishes | C45: Flooring | D45: Marble Ziarat White 3/4" | E45: Providing and laying Marble Ziarat White 3/4" marble flooring in 1" thick cement sand mortar 1:4 with cement slurry, including jointing and curing, complete in all respects; grinding and polishing measured separately. | F45: Mortar bed 0.0833 ft × DryF_Mortar; cement slurry 0.005 bag/Sft | G45: Sft | H45: =City -> Lahore | I45: 2026-09-27 | J45: ='04 DETAILED RATE ANALYSIS'!J994 -> 379.59464 | K45: ='04 DETAILED RATE ANALYSIS'!J997 -> 50.475 | L45: ='04 DETAILED RATE ANALYSIS'!J998 -> 0 | M45: ='04 DETAILED RATE ANALYSIS'!J999 -> 0 | N45: ='04 DETAILED RATE ANALYSIS'!J995 -> 24.67481 | O45: ='04 DETAILED RATE ANALYSIS'!J1000 -> 454.74445 | P45: ='04 DETAILED RATE ANALYSIS'!J1001+'04 DETAILED RATE ANALYSIS'!J1002 -> 36.379556 | Q45: ='04 DETAILED RATE ANALYSIS'!J1003 -> 45.474445 | R45: ='04 DETAILED RATE ANALYSIS'!J1005 -> 0 | S45: ='04 DETAILED RATE ANALYSIS'!J1006 -> 537 | T45: =S45*100 -> 53700 | U45: =IF(W45>0,"INCOMPLETE – "&W45&" blank/old input(s)","Market-derived + assumptions") -> Market-derived + assumptions | V45: Low | W45: ='04 DETAILED RATE ANALYSIS'!J1007 -> 0 | X45: See 09 SOURCE REGISTER (SRC-01…08) | Y45: 2026-04-25 to 2026-09-19 | Z45: see 09 | AA45: Marble rate from UNDATED source – flagged OLD RATE until verified. | AB45: =IF(COUNTIF($A$5:$A$999,A45)>1,"DUPLICATE","")
A46: FIN-FLR-004 | B46: Finishes | C46: Flooring | D46: Marble Tavera 3/4" | E46: Providing and laying Marble Tavera 3/4" marble flooring in 1" thick cement sand mortar 1:4 with cement slurry, including jointing and curing, complete in all respects; grinding and polishing measured separately. | F46: Mortar bed 0.0833 ft × DryF_Mortar; cement slurry 0.005 bag/Sft | G46: Sft | H46: =City -> Lahore | I46: 2026-09-27 | J46: ='04 DETAILED RATE ANALYSIS'!J1016 -> 134.59464 | K46: ='04 DETAILED RATE ANALYSIS'!J1019 -> 50.475 | L46: ='04 DETAILED RATE ANALYSIS'!J1020 -> 0 | M46: ='04 DETAILED RATE ANALYSIS'!J1021 -> 0 | N46: ='04 DETAILED RATE ANALYSIS'!J1017 -> 7.5248096 | O46: ='04 DETAILED RATE ANALYSIS'!J1022 -> 192.59445 | P46: ='04 DETAILED RATE ANALYSIS'!J1023+'04 DETAILED RATE ANALYSIS'!J1024 -> 15.407556 | Q46: ='04 DETAILED RATE ANALYSIS'!J1025 -> 19.259445 | R46: ='04 DETAILED RATE ANALYSIS'!J1027 -> 0 | S46: ='04 DETAILED RATE ANALYSIS'!J1028 -> 227 | T46: =S46*100 -> 22700 | U46: =IF(W46>0,"INCOMPLETE – "&W46&" blank/old input(s)","Market-derived + assumptions") -> Market-derived + assumptions | V46: Low | W46: ='04 DETAILED RATE ANALYSIS'!J1029 -> 0 | X46: See 09 SOURCE REGISTER (SRC-01…08) | Y46: 2026-04-25 to 2026-09-19 | Z46: see 09 | AA46: Marble rate from UNDATED source – flagged OLD RATE until verified. | AB46: =IF(COUNTIF($A$5:$A$999,A46)>1,"DUPLICATE","")
A47: FIN-CLG-001 | B47: Finishes | C47: Ceilings | D47: Gypsum 1/2" standard | E47: Providing and fixing concealed-grid suspended ceiling of Gypsum 1/2" standard gypsum board on GI main and furring channels with hangers, wall angle, screws, joint tape and compound, ready to receive paint, complete in all respects; painting measured separately. | F47: Component qty per Sft (for procurement): board 1/32 sheet; main channel 0.25 Rft; furring 0.50 Rft; wall angle 0.20 Rft; hangers 1/16 Nos; screws 1.56 Nos; tape 0.35 Rft; compound 0.042 kg. Priced as Punjab MRS system material (Ch.9 item 49). | G47: Sft | H47: =City -> Lahore | I47: 2026-09-27 | J47: ='04 DETAILED RATE ANALYSIS'!J1036 -> 176.1 | K47: ='04 DETAILED RATE ANALYSIS'!J1039 -> 39.586667 | L47: ='04 DETAILED RATE ANALYSIS'!J1040 -> 0 | M47: ='04 DETAILED RATE ANALYSIS'!J1041 -> 0 | N47: ='04 DETAILED RATE ANALYSIS'!J1037 -> 0 | O47: ='04 DETAILED RATE ANALYSIS'!J1042 -> 215.68667 | P47: ='04 DETAILED RATE ANALYSIS'!J1043+'04 DETAILED RATE ANALYSIS'!J1044 -> 17.254933 | Q47: ='04 DETAILED RATE ANALYSIS'!J1045 -> 21.568667 | R47: ='04 DETAILED RATE ANALYSIS'!J1047 -> 0 | S47: ='04 DETAILED RATE ANALYSIS'!J1048 -> 255 | T47: =S47*100 -> 25500 | U47: =IF(W47>0,"INCOMPLETE – "&W47&" blank/old input(s)","Market-derived + assumptions") -> Market-derived + assumptions | V47: Low | W47: ='04 DETAILED RATE ANALYSIS'!J1049 -> 0 | X47: See 09 SOURCE REGISTER (SRC-01…08) | Y47: 2026-04-25 to 2026-09-19 | Z47: see 09 | AA47: Benchmark supply+fix Rs220–350/Sft (SRC-18) / Rs250–400 (SRC-19) – compare once red inputs are filled. Access scaffold extra above 12 ft. | AB47: =IF(COUNTIF($A$5:$A$999,A47)>1,"DUPLICATE","")
A48: FIN-CLG-002 | B48: Finishes | C48: Ceilings | D48: Gypsum 1/2" moisture-resistant | E48: Providing and fixing concealed-grid suspended ceiling of Gypsum 1/2" moisture-resistant gypsum board on GI main and furring channels with hangers, wall angle, screws, joint tape and compound, ready to receive paint, complete in all respects; painting measured separately. | F48: Component qty per Sft (for procurement): board 1/32 sheet; main channel 0.25 Rft; furring 0.50 Rft; wall angle 0.20 Rft; hangers 1/16 Nos; screws 1.56 Nos; tape 0.35 Rft; compound 0.042 kg. Priced as Punjab MRS system material (Ch.9 item 49). | G48: Sft | H48: =City -> Lahore | I48: 2026-09-27 | J48: ='04 DETAILED RATE ANALYSIS'!J1056 -> 212.19 | K48: ='04 DETAILED RATE ANALYSIS'!J1059 -> 39.586667 | L48: ='04 DETAILED RATE ANALYSIS'!J1060 -> 0 | M48: ='04 DETAILED RATE ANALYSIS'!J1061 -> 0 | N48: ='04 DETAILED RATE ANALYSIS'!J1057 -> 0 | O48: ='04 DETAILED RATE ANALYSIS'!J1062 -> 251.77667 | P48: ='04 DETAILED RATE ANALYSIS'!J1063+'04 DETAILED RATE ANALYSIS'!J1064 -> 20.142133 | Q48: ='04 DETAILED RATE ANALYSIS'!J1065 -> 25.177667 | R48: ='04 DETAILED RATE ANALYSIS'!J1067 -> 0 | S48: ='04 DETAILED RATE ANALYSIS'!J1068 -> 297 | T48: =S48*100 -> 29700 | U48: =IF(W48>0,"INCOMPLETE – "&W48&" blank/old input(s)","Market-derived + assumptions") -> Market-derived + assumptions | V48: Low | W48: ='04 DETAILED RATE ANALYSIS'!J1069 -> 0 | X48: See 09 SOURCE REGISTER (SRC-01…08) | Y48: 2026-04-25 to 2026-09-19 | Z48: see 09 | AA48: Benchmark supply+fix Rs220–350/Sft (SRC-18) / Rs250–400 (SRC-19) – compare once red inputs are filled. Access scaffold extra above 12 ft. | AB48: =IF(COUNTIF($A$5:$A$999,A48)>1,"DUPLICATE","")
A49: FIN-PNT-001 | B49: Finishes | C49: Painting | D49: Plastic emulsion – internal | E49: Providing and applying plastic emulsion paint to internal plastered walls/ceilings: one coat primer, two coats putty sanded smooth and two finish coats, complete in all respects. | F49: Primer 1 coat @350 Sft/gal; putty 0.10 kg/Sft (2 coats); emulsion 2 coats @350 Sft/gal/coat | G49: Sft | H49: =City -> Lahore | I49: 2026-09-27 | J49: ='04 DETAILED RATE ANALYSIS'!J1078 -> 28.5076 | K49: ='04 DETAILED RATE ANALYSIS'!J1081 -> 19.126667 | L49: ='04 DETAILED RATE ANALYSIS'!J1082 -> 0 | M49: ='04 DETAILED RATE ANALYSIS'!J1083 -> 0 | N49: ='04 DETAILED RATE ANALYSIS'!J1079 -> 1.42538 | O49: ='04 DETAILED RATE ANALYSIS'!J1084 -> 49.059647 | P49: ='04 DETAILED RATE ANALYSIS'!J1085+'04 DETAILED RATE ANALYSIS'!J1086 -> 3.9247717 | Q49: ='04 DETAILED RATE ANALYSIS'!J1087 -> 4.9059647 | R49: ='04 DETAILED RATE ANALYSIS'!J1089 -> 0 | S49: ='04 DETAILED RATE ANALYSIS'!J1090 -> 58 | T49: =S49*100 -> 5800 | U49: =IF(W49>0,"INCOMPLETE – "&W49&" blank/old input(s)","Market-derived + assumptions") -> Market-derived + assumptions | V49: Medium | W49: ='04 DETAILED RATE ANALYSIS'!J1091 -> 0 | X49: See 09 SOURCE REGISTER (SRC-01…08) | Y49: 2026-04-25 to 2026-09-19 | Z49: see 09 | AA49: Coverage 350 Sft/gallon/coat is an assumption – check product data sheet. | AB49: =IF(COUNTIF($A$5:$A$999,A49)>1,"DUPLICATE","")
A50: FIN-PNT-002 | B50: Finishes | C50: Painting | D50: Weather shield – external | E50: Providing and applying exterior weather-shield acrylic paint to external plastered surfaces: one coat alkali-resistant primer and two finish coats, complete in all respects; scaffolding/cradle measured separately. | F50: Primer @350 Sft/gal; 2 finish coats @300 Sft/gal/coat | G50: Sft | H50: =City -> Lahore | I50: 2026-09-27 | J50: ='04 DETAILED RATE ANALYSIS'!J1099 -> 42.807552 | K50: ='04 DETAILED RATE ANALYSIS'!J1102 -> 40.985714 | L50: ='04 DETAILED RATE ANALYSIS'!J1103 -> 0 | M50: ='04 DETAILED RATE ANALYSIS'!J1104 -> 0 | N50: ='04 DETAILED RATE ANALYSIS'!J1100 -> 2.1403776 | O50: ='04 DETAILED RATE ANALYSIS'!J1105 -> 85.933644 | P50: ='04 DETAILED RATE ANALYSIS'!J1106+'04 DETAILED RATE ANALYSIS'!J1107 -> 6.8746915 | Q50: ='04 DETAILED RATE ANALYSIS'!J1108 -> 8.5933644 | R50: ='04 DETAILED RATE ANALYSIS'!J1110 -> 0 | S50: ='04 DETAILED RATE ANALYSIS'!J1111 -> 101 | T50: =S50*100 -> 10100 | U50: =IF(W50>0,"INCOMPLETE – "&W50&" blank/old input(s)","Market-derived + assumptions") -> Market-derived + assumptions | V50: Low | W50: ='04 DETAILED RATE ANALYSIS'!J1112 -> 0 | X50: See 09 SOURCE REGISTER (SRC-01…08) | Y50: 2026-04-25 to 2026-09-19 | Z50: see 09 | AA50: Elevation access (scaffold/cradle) is a separate item per house rule. | AB50: =IF(COUNTIF($A$5:$A$999,A50)>1,"DUPLICATE","")
A51: PRE-GEN-001 | B51: Prelims | C51: Scaffolding | D51: External scaffold / month | E51: Providing, erecting, maintaining for one month and dismantling steel tubular scaffolding to external elevations, complete in all respects. | F51: Per Sft of elevation per month; erection+dismantle 1 scaffolder + 2 helpers 400 Sft/day (assumption) | G51: Sft | H51: =City -> Lahore | I51: 2026-09-27 | J51: ='04 DETAILED RATE ANALYSIS'!J1119 -> 0 | K51: ='04 DETAILED RATE ANALYSIS'!J1122 -> 0 | L51: ='04 DETAILED RATE ANALYSIS'!J1123 -> 75 | M51: ='04 DETAILED RATE ANALYSIS'!J1124 -> 0 | N51: ='04 DETAILED RATE ANALYSIS'!J1120 -> 0 | O51: ='04 DETAILED RATE ANALYSIS'!J1125 -> 75 | P51: ='04 DETAILED RATE ANALYSIS'!J1126+'04 DETAILED RATE ANALYSIS'!J1127 -> 6 | Q51: ='04 DETAILED RATE ANALYSIS'!J1128 -> 7.5 | R51: ='04 DETAILED RATE ANALYSIS'!J1130 -> 0 | S51: ='04 DETAILED RATE ANALYSIS'!J1131 -> 89 | T51: =S51*100 -> 8900 | U51: =IF(W51>0,"INCOMPLETE – "&W51&" blank/old input(s)","Market-derived + assumptions") -> Market-derived + assumptions | V51: Low | W51: ='04 DETAILED RATE ANALYSIS'!J1132 -> 0 | X51: See 09 SOURCE REGISTER (SRC-01…08) | Y51: 2026-04-25 to 2026-09-19 | Z51: see 09 | AB51: =IF(COUNTIF($A$5:$A$999,A51)>1,"DUPLICATE","")
A52: PRE-GEN-002 | B52: Prelims | C52: Debris | D52: Debris removal off-site | E52: Collecting, loading and carting away construction debris to approved dump, complete in all respects. | F52: Per cft loose; 2 helpers load 150 cft/day (assumption) | G52: cft | H52: =City -> Lahore | I52: 2026-09-27 | J52: ='04 DETAILED RATE ANALYSIS'!J1138 -> 0 | K52: ='04 DETAILED RATE ANALYSIS'!J1141 -> 20.506667 | L52: ='04 DETAILED RATE ANALYSIS'!J1142 -> 45 | M52: ='04 DETAILED RATE ANALYSIS'!J1143 -> 0 | N52: ='04 DETAILED RATE ANALYSIS'!J1139 -> 0 | O52: ='04 DETAILED RATE ANALYSIS'!J1144 -> 65.506667 | P52: ='04 DETAILED RATE ANALYSIS'!J1145+'04 DETAILED RATE ANALYSIS'!J1146 -> 5.2405333 | Q52: ='04 DETAILED RATE ANALYSIS'!J1147 -> 6.5506667 | R52: ='04 DETAILED RATE ANALYSIS'!J1149 -> 0 | S52: ='04 DETAILED RATE ANALYSIS'!J1150 -> 77 | T52: =S52*100 -> 7700 | U52: =IF(W52>0,"INCOMPLETE – "&W52&" blank/old input(s)","Market-derived + assumptions") -> Market-derived + assumptions | V52: Low | W52: ='04 DETAILED RATE ANALYSIS'!J1151 -> 0 | X52: See 09 SOURCE REGISTER (SRC-01…08) | Y52: 2026-04-25 to 2026-09-19 | Z52: see 09 | AB52: =IF(COUNTIF($A$5:$A$999,A52)>1,"DUPLICATE","")
A53: CIV-EW-001 | B53: Civil | C53: Earthwork | D53: Machine – ordinary soil | E53: Excavation in ordinary soil by excavator for foundations/basement, including trimming, dressing and stacking within 150 ft, complete in all respects; disposal measured separately. | F53: Excavator output 350 cft/hour (assumption); 1 helper per 1,000 cft trimming | G53: cft | H53: =City -> Lahore | I53: 2026-09-27 | J53: ='04 DETAILED RATE ANALYSIS'!J1157 -> 0 | K53: ='04 DETAILED RATE ANALYSIS'!J1160 -> 0 | L53: ='04 DETAILED RATE ANALYSIS'!J1161 -> 9.523 | M53: ='04 DETAILED RATE ANALYSIS'!J1162 -> 0 | N53: ='04 DETAILED RATE ANALYSIS'!J1158 -> 0 | O53: ='04 DETAILED RATE ANALYSIS'!J1163 -> 9.523 | P53: ='04 DETAILED RATE ANALYSIS'!J1164+'04 DETAILED RATE ANALYSIS'!J1165 -> 0.76184 | Q53: ='04 DETAILED RATE ANALYSIS'!J1166 -> 0.9523 | R53: ='04 DETAILED RATE ANALYSIS'!J1168 -> 0 | S53: ='04 DETAILED RATE ANALYSIS'!J1169 -> 11 | T53: =S53*100 -> 1100 | U53: =IF(W53>0,"INCOMPLETE – "&W53&" blank/old input(s)","Market-derived + assumptions") -> Market-derived + assumptions | V53: Low | W53: ='04 DETAILED RATE ANALYSIS'!J1170 -> 0 | X53: See 09 SOURCE REGISTER (SRC-01…08) | Y53: 2026-04-25 to 2026-09-19 | Z53: see 09 | AB53: =IF(COUNTIF($A$5:$A$999,A53)>1,"DUPLICATE","")
A54: CIV-EW-002 | B54: Civil | C54: Earthwork | D54: Machine – hard soil | E54: Excavation in hard soil by excavator for foundations/basement, including trimming, dressing and stacking within 150 ft, complete in all respects; disposal measured separately. | F54: Excavator output 200 cft/hour (assumption); 1 helper per 1,000 cft trimming | G54: cft | H54: =City -> Lahore | I54: 2026-09-27 | J54: ='04 DETAILED RATE ANALYSIS'!J1176 -> 0 | K54: ='04 DETAILED RATE ANALYSIS'!J1179 -> 0 | L54: ='04 DETAILED RATE ANALYSIS'!J1180 -> 11.164 | M54: ='04 DETAILED RATE ANALYSIS'!J1181 -> 0 | N54: ='04 DETAILED RATE ANALYSIS'!J1177 -> 0 | O54: ='04 DETAILED RATE ANALYSIS'!J1182 -> 11.164 | P54: ='04 DETAILED RATE ANALYSIS'!J1183+'04 DETAILED RATE ANALYSIS'!J1184 -> 0.89312 | Q54: ='04 DETAILED RATE ANALYSIS'!J1185 -> 1.1164 | R54: ='04 DETAILED RATE ANALYSIS'!J1187 -> 0 | S54: ='04 DETAILED RATE ANALYSIS'!J1188 -> 13 | T54: =S54*100 -> 1300 | U54: =IF(W54>0,"INCOMPLETE – "&W54&" blank/old input(s)","Market-derived + assumptions") -> Market-derived + assumptions | V54: Low | W54: ='04 DETAILED RATE ANALYSIS'!J1189 -> 0 | X54: See 09 SOURCE REGISTER (SRC-01…08) | Y54: 2026-04-25 to 2026-09-19 | Z54: see 09 | AB54: =IF(COUNTIF($A$5:$A$999,A54)>1,"DUPLICATE","")
A55: CIV-EW-003 | B55: Civil | C55: Earthwork | D55: Manual – ordinary soil | E55: Excavation by manual labour in ordinary soil in trenches up to 5 ft deep, including trimming and stacking, complete in all respects. | F55: 1 helper excavates 80 cft/day (assumption) | G55: cft | H55: =City -> Lahore | I55: 2026-09-27 | J55: ='04 DETAILED RATE ANALYSIS'!J1194 -> 0 | K55: ='04 DETAILED RATE ANALYSIS'!J1197 -> 19.225 | L55: ='04 DETAILED RATE ANALYSIS'!J1198 -> 0 | M55: ='04 DETAILED RATE ANALYSIS'!J1199 -> 0 | N55: ='04 DETAILED RATE ANALYSIS'!J1195 -> 0 | O55: ='04 DETAILED RATE ANALYSIS'!J1200 -> 19.225 | P55: ='04 DETAILED RATE ANALYSIS'!J1201+'04 DETAILED RATE ANALYSIS'!J1202 -> 1.538 | Q55: ='04 DETAILED RATE ANALYSIS'!J1203 -> 1.9225 | R55: ='04 DETAILED RATE ANALYSIS'!J1205 -> 0 | S55: ='04 DETAILED RATE ANALYSIS'!J1206 -> 23 | T55: =S55*100 -> 2300 | U55: =IF(W55>0,"INCOMPLETE – "&W55&" blank/old input(s)","Market-derived + assumptions") -> Market-derived + assumptions | V55: Medium | W55: ='04 DETAILED RATE ANALYSIS'!J1207 -> 0 | X55: See 09 SOURCE REGISTER (SRC-01…08) | Y55: 2026-04-25 to 2026-09-19 | Z55: see 09 | AB55: =IF(COUNTIF($A$5:$A$999,A55)>1,"DUPLICATE","")
A56: CIV-EW-004 | B56: Civil | C56: Earthwork | D56: Backfill – excavated material | E56: Backfilling with selected excavated material in 6" layers, watered and compacted with plate compactor to 95% MDD, complete in all respects. | F56: 2 helpers + 1 compactor 200 cft/day; water 1.0 litre/cft (assumption) | G56: cft | H56: =City -> Lahore | I56: 2026-09-27 | J56: ='04 DETAILED RATE ANALYSIS'!J1214 -> 0.686 | K56: ='04 DETAILED RATE ANALYSIS'!J1217 -> 8.2026667 | L56: ='04 DETAILED RATE ANALYSIS'!J1218 -> 2.011 | M56: ='04 DETAILED RATE ANALYSIS'!J1219 -> 0 | N56: ='04 DETAILED RATE ANALYSIS'!J1215 -> 0 | O56: ='04 DETAILED RATE ANALYSIS'!J1220 -> 10.899667 | P56: ='04 DETAILED RATE ANALYSIS'!J1221+'04 DETAILED RATE ANALYSIS'!J1222 -> 0.87197333 | Q56: ='04 DETAILED RATE ANALYSIS'!J1223 -> 1.0899667 | R56: ='04 DETAILED RATE ANALYSIS'!J1225 -> 0 | S56: ='04 DETAILED RATE ANALYSIS'!J1226 -> 13 | T56: =S56*100 -> 1300 | U56: =IF(W56>0,"INCOMPLETE – "&W56&" blank/old input(s)","Market-derived + assumptions") -> Market-derived + assumptions | V56: Low | W56: ='04 DETAILED RATE ANALYSIS'!J1227 -> 0 | X56: See 09 SOURCE REGISTER (SRC-01…08) | Y56: 2026-04-25 to 2026-09-19 | Z56: see 09 | AB56: =IF(COUNTIF($A$5:$A$999,A56)>1,"DUPLICATE","")
A57: CIV-EW-005 | B57: Civil | C57: Earthwork | D57: Imported sand fill | E57: Providing and filling Ravi sand under floors in 6" layers, watered and compacted, complete in all respects. | F57: 1.20 cft loose per cft compacted | G57: cft | H57: =City -> Lahore | I57: 2026-09-27 | J57: ='04 DETAILED RATE ANALYSIS'!J1235 -> 63.086 | K57: ='04 DETAILED RATE ANALYSIS'!J1238 -> 6.8355556 | L57: ='04 DETAILED RATE ANALYSIS'!J1239 -> 2.011 | M57: ='04 DETAILED RATE ANALYSIS'!J1240 -> 0 | N57: ='04 DETAILED RATE ANALYSIS'!J1236 -> 0 | O57: ='04 DETAILED RATE ANALYSIS'!J1241 -> 71.932556 | P57: ='04 DETAILED RATE ANALYSIS'!J1242+'04 DETAILED RATE ANALYSIS'!J1243 -> 5.7546044 | Q57: ='04 DETAILED RATE ANALYSIS'!J1244 -> 7.1932556 | R57: ='04 DETAILED RATE ANALYSIS'!J1246 -> 0 | S57: ='04 DETAILED RATE ANALYSIS'!J1247 -> 85 | T57: =S57*100 -> 8500 | U57: =IF(W57>0,"INCOMPLETE – "&W57&" blank/old input(s)","Market-derived + assumptions") -> Market-derived + assumptions | V57: Low | W57: ='04 DETAILED RATE ANALYSIS'!J1248 -> 0 | X57: See 09 SOURCE REGISTER (SRC-01…08) | Y57: 2026-04-25 to 2026-09-19 | Z57: see 09 | AB57: =IF(COUNTIF($A$5:$A$999,A57)>1,"DUPLICATE","")
A58: CIV-EW-006 | B58: Civil | C58: Earthwork | D58: Disposal of surplus earth | E58: Loading surplus excavated earth by machine and disposing within 5-mile lead, complete in all respects. | F58: Bulking 1.25; loading 500 cft/hour | G58: cft | H58: =City -> Lahore | I58: 2026-09-27 | J58: ='04 DETAILED RATE ANALYSIS'!J1254 -> 0 | K58: ='04 DETAILED RATE ANALYSIS'!J1257 -> 0 | L58: ='04 DETAILED RATE ANALYSIS'!J1258 -> 45 | M58: ='04 DETAILED RATE ANALYSIS'!J1259 -> 0 | N58: ='04 DETAILED RATE ANALYSIS'!J1255 -> 0 | O58: ='04 DETAILED RATE ANALYSIS'!J1260 -> 45 | P58: ='04 DETAILED RATE ANALYSIS'!J1261+'04 DETAILED RATE ANALYSIS'!J1262 -> 3.6 | Q58: ='04 DETAILED RATE ANALYSIS'!J1263 -> 4.5 | R58: ='04 DETAILED RATE ANALYSIS'!J1265 -> 0 | S58: ='04 DETAILED RATE ANALYSIS'!J1266 -> 53 | T58: =S58*100 -> 5300 | U58: =IF(W58>0,"INCOMPLETE – "&W58&" blank/old input(s)","Market-derived + assumptions") -> Market-derived + assumptions | V58: Low | W58: ='04 DETAILED RATE ANALYSIS'!J1267 -> 0 | X58: See 09 SOURCE REGISTER (SRC-01…08) | Y58: 2026-04-25 to 2026-09-19 | Z58: see 09 | AB58: =IF(COUNTIF($A$5:$A$999,A58)>1,"DUPLICATE","")
A59: CIV-EW-007 | B59: Civil | C59: Earthwork | D59: Anti-termite treatment | E59: Providing anti-termite treatment to foundation bottoms, sides and under floors with approved chemical emulsion, complete in all respects. | F59: Concentrate 0.005 litre/Sft (assumption – follow product label) | G59: Sft | H59: =City -> Lahore | I59: 2026-09-27 | J59: ='04 DETAILED RATE ANALYSIS'!J1273 -> 7.5 | K59: ='04 DETAILED RATE ANALYSIS'!J1276 -> 1.538 | L59: ='04 DETAILED RATE ANALYSIS'!J1277 -> 0 | M59: ='04 DETAILED RATE ANALYSIS'!J1278 -> 0 | N59: ='04 DETAILED RATE ANALYSIS'!J1274 -> 0 | O59: ='04 DETAILED RATE ANALYSIS'!J1279 -> 9.038 | P59: ='04 DETAILED RATE ANALYSIS'!J1280+'04 DETAILED RATE ANALYSIS'!J1281 -> 0.72304 | Q59: ='04 DETAILED RATE ANALYSIS'!J1282 -> 0.9038 | R59: ='04 DETAILED RATE ANALYSIS'!J1284 -> 0 | S59: ='04 DETAILED RATE ANALYSIS'!J1285 -> 11 | T59: =S59*100 -> 1100 | U59: =IF(W59>0,"INCOMPLETE – "&W59&" blank/old input(s)","Market-derived + assumptions") -> Market-derived + assumptions | V59: Low | W59: ='04 DETAILED RATE ANALYSIS'!J1286 -> 0 | X59: See 09 SOURCE REGISTER (SRC-01…08) | Y59: 2026-04-25 to 2026-09-19 | Z59: see 09 | AB59: =IF(COUNTIF($A$5:$A$999,A59)>1,"DUPLICATE","")
A60: FIN-DOR-001 | B60: Finishes | C60: Doors | D60: Flush door 3'x7' complete | E60: Providing and fixing 1.75" solid-core veneered flush door 3'x7' in deodar frame 3"x5" with SS hinges, mortice lock, stopper and polish, complete in all respects. | F60: Leaf 21 Sft; frame 17 Rft × 0.1042 Sft section = 1.77 cft; polish 50 Sft | G60: Nos | H60: =City -> Lahore | I60: 2026-09-27 | J60: ='04 DETAILED RATE ANALYSIS'!J1299 -> 42743.184 | K60: ='04 DETAILED RATE ANALYSIS'!J1302 -> 3169 | L60: ='04 DETAILED RATE ANALYSIS'!J1303 -> 0 | M60: ='04 DETAILED RATE ANALYSIS'!J1304 -> 0 | N60: ='04 DETAILED RATE ANALYSIS'!J1300 -> 1823.8434 | O60: ='04 DETAILED RATE ANALYSIS'!J1305 -> 47736.027 | P60: ='04 DETAILED RATE ANALYSIS'!J1306+'04 DETAILED RATE ANALYSIS'!J1307 -> 3818.8822 | Q60: ='04 DETAILED RATE ANALYSIS'!J1308 -> 4773.6027 | R60: ='04 DETAILED RATE ANALYSIS'!J1310 -> 0 | S60: ='04 DETAILED RATE ANALYSIS'!J1311 -> 56329 | T60: =S60*100 -> 5632900 | U60: =IF(W60>0,"INCOMPLETE – "&W60&" blank/old input(s)","Market-derived + assumptions") -> Market-derived + assumptions | V60: Low | W60: ='04 DETAILED RATE ANALYSIS'!J1312 -> 0 | X60: See 09 SOURCE REGISTER (SRC-01…08) | Y60: 2026-04-25 to 2026-09-19 | Z60: see 09 | AB60: =IF(COUNTIF($A$5:$A$999,A60)>1,"DUPLICATE","")
A61: FIN-DOR-002 | B61: Finishes | C61: Doors | D61: Fire door 90 min 3'x7' | E61: Supplying and installing 90-minute fire-rated steel door set 3'x7' complete with frame and certified ironmongery, complete in all respects. | F61: Vendor supply; installation labour 0.5 carpenter-day | G61: Nos | H61: =City -> Lahore | I61: 2026-09-27 | J61: ='04 DETAILED RATE ANALYSIS'!J1319 -> 59000 | K61: ='04 DETAILED RATE ANALYSIS'!J1322 -> 1969 | L61: ='04 DETAILED RATE ANALYSIS'!J1323 -> 0 | M61: ='04 DETAILED RATE ANALYSIS'!J1324 -> 0 | N61: ='04 DETAILED RATE ANALYSIS'!J1320 -> 0 | O61: ='04 DETAILED RATE ANALYSIS'!J1325 -> 60969 | P61: ='04 DETAILED RATE ANALYSIS'!J1326+'04 DETAILED RATE ANALYSIS'!J1327 -> 4877.52 | Q61: ='04 DETAILED RATE ANALYSIS'!J1328 -> 6096.9 | R61: ='04 DETAILED RATE ANALYSIS'!J1330 -> 0 | S61: ='04 DETAILED RATE ANALYSIS'!J1331 -> 71943 | T61: =S61*100 -> 7194300 | U61: =IF(W61>0,"INCOMPLETE – "&W61&" blank/old input(s)","Market-derived + assumptions") -> Market-derived + assumptions | V61: Low | W61: ='04 DETAILED RATE ANALYSIS'!J1332 -> 0 | X61: See 09 SOURCE REGISTER (SRC-01…08) | Y61: 2026-04-25 to 2026-09-19 | Z61: see 09 | AB61: =IF(COUNTIF($A$5:$A$999,A61)>1,"DUPLICATE","")
A62: FIN-WIN-001 | B62: Finishes | C62: Windows | D62: Aluminium sliding window | E62: Supplying, fabricating and installing aluminium sliding window with glazing and hardware, sealed with silicone, complete in all respects. | F62: Perimeter sealant 1 cartridge per 75 Sft (assumption); installation 50 Sft/day glazier + helper | G62: Sft | H62: =City -> Lahore | I62: 2026-09-27 | J62: ='04 DETAILED RATE ANALYSIS'!J1340 -> 1405.9333 | K62: ='04 DETAILED RATE ANALYSIS'!J1343 -> 0 | L62: ='04 DETAILED RATE ANALYSIS'!J1344 -> 0 | M62: ='04 DETAILED RATE ANALYSIS'!J1345 -> 0 | N62: ='04 DETAILED RATE ANALYSIS'!J1341 -> 0 | O62: ='04 DETAILED RATE ANALYSIS'!J1346 -> 1405.9333 | P62: ='04 DETAILED RATE ANALYSIS'!J1347+'04 DETAILED RATE ANALYSIS'!J1348 -> 112.47467 | Q62: ='04 DETAILED RATE ANALYSIS'!J1349 -> 140.59333 | R62: ='04 DETAILED RATE ANALYSIS'!J1351 -> 0 | S62: ='04 DETAILED RATE ANALYSIS'!J1352 -> 1659 | T62: =S62*100 -> 165900 | U62: =IF(W62>0,"INCOMPLETE – "&W62&" blank/old input(s)","Market-derived + assumptions") -> Market-derived + assumptions | V62: Low | W62: ='04 DETAILED RATE ANALYSIS'!J1353 -> 0 | X62: See 09 SOURCE REGISTER (SRC-01…08) | Y62: 2026-04-25 to 2026-09-19 | Z62: see 09 | AB62: =IF(COUNTIF($A$5:$A$999,A62)>1,"DUPLICATE","")
A63: FIN-WIN-002 | B63: Finishes | C63: Windows | D63: uPVC window | E63: Supplying, fabricating and installing upvc window with glazing and hardware, sealed with silicone, complete in all respects. | F63: Perimeter sealant 1 cartridge per 75 Sft (assumption); installation 50 Sft/day glazier + helper | G63: Sft | H63: =City -> Lahore | I63: 2026-09-27 | J63: ='04 DETAILED RATE ANALYSIS'!J1361 -> 2855.9333 | K63: ='04 DETAILED RATE ANALYSIS'!J1364 -> 0 | L63: ='04 DETAILED RATE ANALYSIS'!J1365 -> 0 | M63: ='04 DETAILED RATE ANALYSIS'!J1366 -> 0 | N63: ='04 DETAILED RATE ANALYSIS'!J1362 -> 0 | O63: ='04 DETAILED RATE ANALYSIS'!J1367 -> 2855.9333 | P63: ='04 DETAILED RATE ANALYSIS'!J1368+'04 DETAILED RATE ANALYSIS'!J1369 -> 228.47467 | Q63: ='04 DETAILED RATE ANALYSIS'!J1370 -> 285.59333 | R63: ='04 DETAILED RATE ANALYSIS'!J1372 -> 0 | S63: ='04 DETAILED RATE ANALYSIS'!J1373 -> 3370 | T63: =S63*100 -> 337000 | U63: =IF(W63>0,"INCOMPLETE – "&W63&" blank/old input(s)","Market-derived + assumptions") -> Market-derived + assumptions | V63: Low | W63: ='04 DETAILED RATE ANALYSIS'!J1374 -> 0 | X63: See 09 SOURCE REGISTER (SRC-01…08) | Y63: 2026-04-25 to 2026-09-19 | Z63: see 09 | AB63: =IF(COUNTIF($A$5:$A$999,A63)>1,"DUPLICATE","")
A64: FIN-JNR-001 | B64: Finishes | C64: Joinery | D64: Kitchen base cabinet | E64: Providing and fixing kitchen base cabinet 2'-0" deep x 2'-10" high in laminated 3/4" board with hardware, excluding worktop, complete in all respects. | F64: Carcass & shutters 12 Sft board per Rft = 0.375 sheet | G64: Rft | H64: =City -> Lahore | I64: 2026-09-27 | J64: ='04 DETAILED RATE ANALYSIS'!J1382 -> 4671 | K64: ='04 DETAILED RATE ANALYSIS'!J1385 -> 950.7 | L64: ='04 DETAILED RATE ANALYSIS'!J1386 -> 0 | M64: ='04 DETAILED RATE ANALYSIS'!J1387 -> 0 | N64: ='04 DETAILED RATE ANALYSIS'!J1383 -> 412.5 | O64: ='04 DETAILED RATE ANALYSIS'!J1388 -> 6034.2 | P64: ='04 DETAILED RATE ANALYSIS'!J1389+'04 DETAILED RATE ANALYSIS'!J1390 -> 482.736 | Q64: ='04 DETAILED RATE ANALYSIS'!J1391 -> 603.42 | R64: ='04 DETAILED RATE ANALYSIS'!J1393 -> 0 | S64: ='04 DETAILED RATE ANALYSIS'!J1394 -> 7120 | T64: =S64*100 -> 712000 | U64: =IF(W64>0,"INCOMPLETE – "&W64&" blank/old input(s)","Market-derived + assumptions") -> Market-derived + assumptions | V64: Low | W64: ='04 DETAILED RATE ANALYSIS'!J1395 -> 0 | X64: See 09 SOURCE REGISTER (SRC-01…08) | Y64: 2026-04-25 to 2026-09-19 | Z64: see 09 | AB64: =IF(COUNTIF($A$5:$A$999,A64)>1,"DUPLICATE","")
A65: FAC-CW-001 | B65: Façade | C65: Curtain wall | D65: Unitized curtain wall | E65: Supplying and installing unitized aluminium curtain wall with DGU, brackets, fire-stop and sealants, complete in all respects. | F65: Vendor system rate; fire-stop 0.10 Rft/Sft; access by cradle | G65: Sft | H65: =City -> Lahore | I65: 2026-09-27 | J65: ='04 DETAILED RATE ANALYSIS'!J1402 -> 4535 | K65: ='04 DETAILED RATE ANALYSIS'!J1405 -> 0 | L65: ='04 DETAILED RATE ANALYSIS'!J1406 -> 3.75 | M65: ='04 DETAILED RATE ANALYSIS'!J1407 -> 0 | N65: ='04 DETAILED RATE ANALYSIS'!J1403 -> 0 | O65: ='04 DETAILED RATE ANALYSIS'!J1408 -> 4538.75 | P65: ='04 DETAILED RATE ANALYSIS'!J1409+'04 DETAILED RATE ANALYSIS'!J1410 -> 363.1 | Q65: ='04 DETAILED RATE ANALYSIS'!J1411 -> 453.875 | R65: ='04 DETAILED RATE ANALYSIS'!J1413 -> 0 | S65: ='04 DETAILED RATE ANALYSIS'!J1414 -> 5356 | T65: =S65*100 -> 535600 | U65: =IF(W65>0,"INCOMPLETE – "&W65&" blank/old input(s)","Market-derived + assumptions") -> Market-derived + assumptions | V65: Low | W65: ='04 DETAILED RATE ANALYSIS'!J1415 -> 0 | X65: See 09 SOURCE REGISTER (SRC-01…08) | Y65: 2026-04-25 to 2026-09-19 | Z65: see 09 | AB65: =IF(COUNTIF($A$5:$A$999,A65)>1,"DUPLICATE","")
A66: FAC-ACP-001 | B66: Façade | C66: Cladding | D66: ACP cladding | E66: Providing and fixing PVDF aluminium composite panel cladding on aluminium subframe with brackets, anchors and weather-seal, complete in all respects. | F66: Panel 1.15 Sft/Sft (folds+waste); subframe 0.8 kg/Sft; brackets 0.25/Sft; 1 cartridge/40 Sft (assumptions) | G66: Sft | H66: =City -> Lahore | I66: 2026-09-27 | J66: ='04 DETAILED RATE ANALYSIS'!J1426 -> 1713.625 | K66: ='04 DETAILED RATE ANALYSIS'!J1429 -> 93.45 | L66: ='04 DETAILED RATE ANALYSIS'!J1430 -> 3.75 | M66: ='04 DETAILED RATE ANALYSIS'!J1431 -> 0 | N66: ='04 DETAILED RATE ANALYSIS'!J1427 -> 0 | O66: ='04 DETAILED RATE ANALYSIS'!J1432 -> 1810.825 | P66: ='04 DETAILED RATE ANALYSIS'!J1433+'04 DETAILED RATE ANALYSIS'!J1434 -> 144.866 | Q66: ='04 DETAILED RATE ANALYSIS'!J1435 -> 181.0825 | R66: ='04 DETAILED RATE ANALYSIS'!J1437 -> 0 | S66: ='04 DETAILED RATE ANALYSIS'!J1438 -> 2137 | T66: =S66*100 -> 213700 | U66: =IF(W66>0,"INCOMPLETE – "&W66&" blank/old input(s)","Market-derived + assumptions") -> Market-derived + assumptions | V66: Low | W66: ='04 DETAILED RATE ANALYSIS'!J1439 -> 0 | X66: See 09 SOURCE REGISTER (SRC-01…08) | Y66: 2026-04-25 to 2026-09-19 | Z66: see 09 | AB66: =IF(COUNTIF($A$5:$A$999,A66)>1,"DUPLICATE","")
A67: FAC-STN-001 | B67: Façade | C67: Cladding | D67: Granite dry cladding | E67: Providing and fixing 1.25" granite cladding with SS 316 anchors, open/sealed joints, complete in all respects. | F67: Stone 1.07 Sft/Sft; anchors 1.0/Sft (4 per 2'x2' slab shared); 30 Sft/day | G67: Sft | H67: =City -> Lahore | I67: 2026-09-27 | J67: ='04 DETAILED RATE ANALYSIS'!J1449 -> 1586.4807 | K67: ='04 DETAILED RATE ANALYSIS'!J1452 -> 124.6 | L67: ='04 DETAILED RATE ANALYSIS'!J1453 -> 3.75 | M67: ='04 DETAILED RATE ANALYSIS'!J1454 -> 0 | N67: ='04 DETAILED RATE ANALYSIS'!J1450 -> 0 | O67: ='04 DETAILED RATE ANALYSIS'!J1455 -> 1714.8307 | P67: ='04 DETAILED RATE ANALYSIS'!J1456+'04 DETAILED RATE ANALYSIS'!J1457 -> 137.18645 | Q67: ='04 DETAILED RATE ANALYSIS'!J1458 -> 171.48307 | R67: ='04 DETAILED RATE ANALYSIS'!J1460 -> 0 | S67: ='04 DETAILED RATE ANALYSIS'!J1461 -> 2024 | T67: =S67*100 -> 202400 | U67: =IF(W67>0,"INCOMPLETE – "&W67&" blank/old input(s)","Market-derived + assumptions") -> Market-derived + assumptions | V67: Low | W67: ='04 DETAILED RATE ANALYSIS'!J1462 -> 0 | X67: See 09 SOURCE REGISTER (SRC-01…08) | Y67: 2026-04-25 to 2026-09-19 | Z67: see 09 | AB67: =IF(COUNTIF($A$5:$A$999,A67)>1,"DUPLICATE","")
A68: EXT-PAV-001 | B68: External | C68: Paving | D68: Tuff tile on sand bed | E68: Providing and laying grey tuff tiles on 2" compacted sand bed with sand-filled joints, compacted with plate compactor, complete in all respects; edge restraint measured separately. | F68: Tile 1.03 Sft/Sft; Ravi sand 0.1667 ft × 1.20; 1 mason + 2 helpers 300 Sft/day | G68: Sft | H68: =City -> Lahore | I68: 2026-09-27 | J68: ='04 DETAILED RATE ANALYSIS'!J1471 -> 160.40208 | K68: ='04 DETAILED RATE ANALYSIS'!J1474 -> 17.586667 | L68: ='04 DETAILED RATE ANALYSIS'!J1475 -> 0.3352337 | M68: ='04 DETAILED RATE ANALYSIS'!J1476 -> 0 | N68: ='04 DETAILED RATE ANALYSIS'!J1472 -> 10.5 | O68: ='04 DETAILED RATE ANALYSIS'!J1477 -> 188.82398 | P68: ='04 DETAILED RATE ANALYSIS'!J1478+'04 DETAILED RATE ANALYSIS'!J1479 -> 15.105918 | Q68: ='04 DETAILED RATE ANALYSIS'!J1480 -> 18.882398 | R68: ='04 DETAILED RATE ANALYSIS'!J1482 -> 0 | S68: ='04 DETAILED RATE ANALYSIS'!J1483 -> 223 | T68: =S68*100 -> 22300 | U68: =IF(W68>0,"INCOMPLETE – "&W68&" blank/old input(s)","Market-derived + assumptions") -> Market-derived + assumptions | V68: Medium | W68: ='04 DETAILED RATE ANALYSIS'!J1484 -> 0 | X68: See 09 SOURCE REGISTER (SRC-01…08) | Y68: 2026-04-25 to 2026-09-19 | Z68: see 09 | AB68: =IF(COUNTIF($A$5:$A$999,A68)>1,"DUPLICATE","")
A69: EXT-KRB-001 | B69: External | C69: Kerbs | D69: Precast kerb | E69: Providing and laying precast concrete kerb on 1:4:8 PCC bedding and haunching, pointed in 1:3 mortar, complete in all respects. | F69: PCC 0.25 cft/Rft (nominal 1:4:8 materials); 60 Rft/day | G69: Rft | H69: =City -> Lahore | I69: 2026-09-27 | J69: ='04 DETAILED RATE ANALYSIS'!J1494 -> 468.5 | K69: ='04 DETAILED RATE ANALYSIS'!J1497 -> 87.933333 | L69: ='04 DETAILED RATE ANALYSIS'!J1498 -> 0 | M69: ='04 DETAILED RATE ANALYSIS'!J1499 -> 0 | N69: ='04 DETAILED RATE ANALYSIS'!J1495 -> 23.425 | O69: ='04 DETAILED RATE ANALYSIS'!J1500 -> 579.85833 | P69: ='04 DETAILED RATE ANALYSIS'!J1501+'04 DETAILED RATE ANALYSIS'!J1502 -> 46.388667 | Q69: ='04 DETAILED RATE ANALYSIS'!J1503 -> 57.985833 | R69: ='04 DETAILED RATE ANALYSIS'!J1505 -> 0 | S69: ='04 DETAILED RATE ANALYSIS'!J1506 -> 684 | T69: =S69*100 -> 68400 | U69: =IF(W69>0,"INCOMPLETE – "&W69&" blank/old input(s)","Market-derived + assumptions") -> Market-derived + assumptions | V69: Low | W69: ='04 DETAILED RATE ANALYSIS'!J1507 -> 0 | X69: See 09 SOURCE REGISTER (SRC-01…08) | Y69: 2026-04-25 to 2026-09-19 | Z69: see 09 | AB69: =IF(COUNTIF($A$5:$A$999,A69)>1,"DUPLICATE","")
A70: EXT-RD-001 | B70: External | C70: Roads | D70: Granular subbase | E70: Providing, laying and compacting granular subbase in 6" layers to 98% MDD, complete in all respects. | F70: 1.25 cft loose per cft compacted; roller 3,000 cft/day | G70: cft | H70: =City -> Lahore | I70: 2026-09-27 | J70: ='04 DETAILED RATE ANALYSIS'!J1515 -> 126.029 | K70: ='04 DETAILED RATE ANALYSIS'!J1518 -> 1.538 | L70: ='04 DETAILED RATE ANALYSIS'!J1519 -> 2.011 | M70: ='04 DETAILED RATE ANALYSIS'!J1520 -> 0 | N70: ='04 DETAILED RATE ANALYSIS'!J1516 -> 0 | O70: ='04 DETAILED RATE ANALYSIS'!J1521 -> 129.578 | P70: ='04 DETAILED RATE ANALYSIS'!J1522+'04 DETAILED RATE ANALYSIS'!J1523 -> 10.36624 | Q70: ='04 DETAILED RATE ANALYSIS'!J1524 -> 12.9578 | R70: ='04 DETAILED RATE ANALYSIS'!J1526 -> 0 | S70: ='04 DETAILED RATE ANALYSIS'!J1527 -> 153 | T70: =S70*100 -> 15300 | U70: =IF(W70>0,"INCOMPLETE – "&W70&" blank/old input(s)","Market-derived + assumptions") -> Market-derived + assumptions | V70: Low | W70: ='04 DETAILED RATE ANALYSIS'!J1528 -> 0 | X70: See 09 SOURCE REGISTER (SRC-01…08) | Y70: 2026-04-25 to 2026-09-19 | Z70: see 09 | AB70: =IF(COUNTIF($A$5:$A$999,A70)>1,"DUPLICATE","")
A71: EXT-RD-002 | B71: External | C71: Roads | D71: Asphalt 2" wearing course | E71: Providing and laying 2" asphaltic concrete wearing course incl. tack coat, compacted, complete in all respects. | F71: Sub-contract supply & lay rate | G71: Sft | H71: =City -> Lahore | I71: 2026-09-27 | J71: ='04 DETAILED RATE ANALYSIS'!J1533 -> 142.31 | K71: ='04 DETAILED RATE ANALYSIS'!J1536 -> 0 | L71: ='04 DETAILED RATE ANALYSIS'!J1537 -> 0 | M71: ='04 DETAILED RATE ANALYSIS'!J1538 -> 0 | N71: ='04 DETAILED RATE ANALYSIS'!J1534 -> 0 | O71: ='04 DETAILED RATE ANALYSIS'!J1539 -> 142.31 | P71: ='04 DETAILED RATE ANALYSIS'!J1540+'04 DETAILED RATE ANALYSIS'!J1541 -> 11.3848 | Q71: ='04 DETAILED RATE ANALYSIS'!J1542 -> 14.231 | R71: ='04 DETAILED RATE ANALYSIS'!J1544 -> 0 | S71: ='04 DETAILED RATE ANALYSIS'!J1545 -> 168 | T71: =S71*100 -> 16800 | U71: =IF(W71>0,"INCOMPLETE – "&W71&" blank/old input(s)","Market-derived + assumptions") -> Market-derived + assumptions | V71: Low | W71: ='04 DETAILED RATE ANALYSIS'!J1546 -> 0 | X71: See 09 SOURCE REGISTER (SRC-01…08) | Y71: 2026-04-25 to 2026-09-19 | Z71: see 09 | AB71: =IF(COUNTIF($A$5:$A$999,A71)>1,"DUPLICATE","")
A72: EXT-DRN-001 | B72: External | C72: Drainage | D72: Brick manhole 3'x3'x5' | E72: Constructing brick manhole 3'x3' internal, 5' deep, 9" walls in 1:6 on 6" PCC 1:4:8 base, ½" plaster 1:3 inside, with cover and frame, complete in all respects; excavation measured separately. | F72: Walls 4×3.75×0.75×5 = 56.25 cft; base 5.25×5.25×0.5 = 13.78 cft; plaster 4×3×5+9 = 69 Sft | G72: Nos | H72: =City -> Lahore | I72: 2026-09-27 | J72: ='04 DETAILED RATE ANALYSIS'!J1557 -> 30534.832 | K72: ='04 DETAILED RATE ANALYSIS'!J1560 -> 15828 | L72: ='04 DETAILED RATE ANALYSIS'!J1561 -> 0 | M72: ='04 DETAILED RATE ANALYSIS'!J1562 -> 0 | N72: ='04 DETAILED RATE ANALYSIS'!J1558 -> 1019.4424 | O72: ='04 DETAILED RATE ANALYSIS'!J1563 -> 47382.274 | P72: ='04 DETAILED RATE ANALYSIS'!J1564+'04 DETAILED RATE ANALYSIS'!J1565 -> 3790.5819 | Q72: ='04 DETAILED RATE ANALYSIS'!J1566 -> 4738.2274 | R72: ='04 DETAILED RATE ANALYSIS'!J1568 -> 0 | S72: ='04 DETAILED RATE ANALYSIS'!J1569 -> 55911 | T72: =S72*100 -> 5591100 | U72: =IF(W72>0,"INCOMPLETE – "&W72&" blank/old input(s)","Market-derived + assumptions") -> Market-derived + assumptions | V72: Medium | W72: ='04 DETAILED RATE ANALYSIS'!J1570 -> 0 | X72: See 09 SOURCE REGISTER (SRC-01…08) | Y72: 2026-04-25 to 2026-09-19 | Z72: see 09 | AB72: =IF(COUNTIF($A$5:$A$999,A72)>1,"DUPLICATE","")
A73: EXT-LND-001 | B73: External | C73: Landscaping | D73: Grass turfing | E73: Providing and laying grass turf on prepared ground, watered and maintained till establishment, complete in all respects. | F73: 1 helper 500 Sft/day | G73: Sft | H73: =City -> Lahore | I73: 2026-09-27 | J73: ='04 DETAILED RATE ANALYSIS'!J1576 -> 9.45 | K73: ='04 DETAILED RATE ANALYSIS'!J1579 -> 3.076 | L73: ='04 DETAILED RATE ANALYSIS'!J1580 -> 0 | M73: ='04 DETAILED RATE ANALYSIS'!J1581 -> 0 | N73: ='04 DETAILED RATE ANALYSIS'!J1577 -> 0 | O73: ='04 DETAILED RATE ANALYSIS'!J1582 -> 12.526 | P73: ='04 DETAILED RATE ANALYSIS'!J1583+'04 DETAILED RATE ANALYSIS'!J1584 -> 1.00208 | Q73: ='04 DETAILED RATE ANALYSIS'!J1585 -> 1.2526 | R73: ='04 DETAILED RATE ANALYSIS'!J1587 -> 0 | S73: ='04 DETAILED RATE ANALYSIS'!J1588 -> 15 | T73: =S73*100 -> 1500 | U73: =IF(W73>0,"INCOMPLETE – "&W73&" blank/old input(s)","Market-derived + assumptions") -> Market-derived + assumptions | V73: Low | W73: ='04 DETAILED RATE ANALYSIS'!J1589 -> 0 | X73: See 09 SOURCE REGISTER (SRC-01…08) | Y73: 2026-04-25 to 2026-09-19 | Z73: see 09 | AB73: =IF(COUNTIF($A$5:$A$999,A73)>1,"DUPLICATE","")
A74: PLB-PPR-075 | B74: Plumbing | C74: Water supply | D74: PPR PN-20 1/2" | E74: Providing and fixing PPR PN-20 pipe 1/2" with fusion-welded fittings and clamps, concealed or exposed, pressure-tested, complete in all respects. | F74: Fittings per Rft: elbow 0.15, socket 1/13.12, tee 0.08 (assumptions); fittings column mapping to verify | G74: Rft | H74: =City -> Lahore | I74: 2026-09-27 | J74: ='04 DETAILED RATE ANALYSIS'!J1600 -> 151.54126 | K74: ='04 DETAILED RATE ANALYSIS'!J1603 -> 91.955556 | L74: ='04 DETAILED RATE ANALYSIS'!J1604 -> 0 | M74: ='04 DETAILED RATE ANALYSIS'!J1605 -> 0 | N74: ='04 DETAILED RATE ANALYSIS'!J1601 -> 4.9375 | O74: ='04 DETAILED RATE ANALYSIS'!J1606 -> 248.43432 | P74: ='04 DETAILED RATE ANALYSIS'!J1607+'04 DETAILED RATE ANALYSIS'!J1608 -> 19.874745 | Q74: ='04 DETAILED RATE ANALYSIS'!J1609 -> 24.843432 | R74: ='04 DETAILED RATE ANALYSIS'!J1611 -> 0 | S74: ='04 DETAILED RATE ANALYSIS'!J1612 -> 293 | T74: =S74*100 -> 29300 | U74: =IF(W74>0,"INCOMPLETE – "&W74&" blank/old input(s)","Market-derived + assumptions") -> INCOMPLETE – 1 blank/old input(s) | V74: Low | W74: ='04 DETAILED RATE ANALYSIS'!J1613 -> 1 | X74: See 09 SOURCE REGISTER (SRC-01…08) | Y74: 2026-04-25 to 2026-09-19 | Z74: see 09 | AB74: =IF(COUNTIF($A$5:$A$999,A74)>1,"DUPLICATE","")
A75: PLB-PPR-100 | B75: Plumbing | C75: Water supply | D75: PPR PN-20 3/4" | E75: Providing and fixing PPR PN-20 pipe 3/4" with fusion-welded fittings and clamps, concealed or exposed, pressure-tested, complete in all respects. | F75: Fittings per Rft: elbow 0.15, socket 1/13.12, tee 0.08 (assumptions); fittings column mapping to verify | G75: Rft | H75: =City -> Lahore | I75: 2026-09-27 | J75: ='04 DETAILED RATE ANALYSIS'!J1624 -> 203.24278 | K75: ='04 DETAILED RATE ANALYSIS'!J1627 -> 91.955556 | L75: ='04 DETAILED RATE ANALYSIS'!J1628 -> 0 | M75: ='04 DETAILED RATE ANALYSIS'!J1629 -> 0 | N75: ='04 DETAILED RATE ANALYSIS'!J1625 -> 7.269 | O75: ='04 DETAILED RATE ANALYSIS'!J1630 -> 302.46734 | P75: ='04 DETAILED RATE ANALYSIS'!J1631+'04 DETAILED RATE ANALYSIS'!J1632 -> 24.197387 | Q75: ='04 DETAILED RATE ANALYSIS'!J1633 -> 30.246734 | R75: ='04 DETAILED RATE ANALYSIS'!J1635 -> 0 | S75: ='04 DETAILED RATE ANALYSIS'!J1636 -> 357 | T75: =S75*100 -> 35700 | U75: =IF(W75>0,"INCOMPLETE – "&W75&" blank/old input(s)","Market-derived + assumptions") -> INCOMPLETE – 1 blank/old input(s) | V75: Low | W75: ='04 DETAILED RATE ANALYSIS'!J1637 -> 1 | X75: See 09 SOURCE REGISTER (SRC-01…08) | Y75: 2026-04-25 to 2026-09-19 | Z75: see 09 | AB75: =IF(COUNTIF($A$5:$A$999,A75)>1,"DUPLICATE","")
A76: PLB-PPR-125 | B76: Plumbing | C76: Water supply | D76: PPR PN-20 1" | E76: Providing and fixing PPR PN-20 pipe 1" with fusion-welded fittings and clamps, concealed or exposed, pressure-tested, complete in all respects. | F76: Fittings per Rft: elbow 0.15, socket 1/13.12, tee 0.08 (assumptions); fittings column mapping to verify | G76: Rft | H76: =City -> Lahore | I76: 2026-09-27 | J76: ='04 DETAILED RATE ANALYSIS'!J1648 -> 313.62949 | K76: ='04 DETAILED RATE ANALYSIS'!J1651 -> 91.955556 | L76: ='04 DETAILED RATE ANALYSIS'!J1652 -> 0 | M76: ='04 DETAILED RATE ANALYSIS'!J1653 -> 0 | N76: ='04 DETAILED RATE ANALYSIS'!J1649 -> 12.1305 | O76: ='04 DETAILED RATE ANALYSIS'!J1654 -> 417.71555 | P76: ='04 DETAILED RATE ANALYSIS'!J1655+'04 DETAILED RATE ANALYSIS'!J1656 -> 33.417244 | Q76: ='04 DETAILED RATE ANALYSIS'!J1657 -> 41.771555 | R76: ='04 DETAILED RATE ANALYSIS'!J1659 -> 0 | S76: ='04 DETAILED RATE ANALYSIS'!J1660 -> 493 | T76: =S76*100 -> 49300 | U76: =IF(W76>0,"INCOMPLETE – "&W76&" blank/old input(s)","Market-derived + assumptions") -> INCOMPLETE – 1 blank/old input(s) | V76: Low | W76: ='04 DETAILED RATE ANALYSIS'!J1661 -> 1 | X76: See 09 SOURCE REGISTER (SRC-01…08) | Y76: 2026-04-25 to 2026-09-19 | Z76: see 09 | AB76: =IF(COUNTIF($A$5:$A$999,A76)>1,"DUPLICATE","")
A77: PLB-PPR-150 | B77: Plumbing | C77: Water supply | D77: PPR PN-20 1-1/4" | E77: Providing and fixing PPR PN-20 pipe 1-1/4" with fusion-welded fittings and clamps, concealed or exposed, pressure-tested, complete in all respects. | F77: Fittings per Rft: elbow 0.15, socket 1/13.12, tee 0.08 (assumptions); fittings column mapping to verify | G77: Rft | H77: =City -> Lahore | I77: 2026-09-27 | J77: ='04 DETAILED RATE ANALYSIS'!J1672 -> 456.6937 | K77: ='04 DETAILED RATE ANALYSIS'!J1675 -> 118.22857 | L77: ='04 DETAILED RATE ANALYSIS'!J1676 -> 0 | M77: ='04 DETAILED RATE ANALYSIS'!J1677 -> 0 | N77: ='04 DETAILED RATE ANALYSIS'!J1673 -> 18.348 | O77: ='04 DETAILED RATE ANALYSIS'!J1678 -> 593.27027 | P77: ='04 DETAILED RATE ANALYSIS'!J1679+'04 DETAILED RATE ANALYSIS'!J1680 -> 47.461622 | Q77: ='04 DETAILED RATE ANALYSIS'!J1681 -> 59.327027 | R77: ='04 DETAILED RATE ANALYSIS'!J1683 -> 0 | S77: ='04 DETAILED RATE ANALYSIS'!J1684 -> 700 | T77: =S77*100 -> 70000 | U77: =IF(W77>0,"INCOMPLETE – "&W77&" blank/old input(s)","Market-derived + assumptions") -> INCOMPLETE – 1 blank/old input(s) | V77: Low | W77: ='04 DETAILED RATE ANALYSIS'!J1685 -> 1 | X77: See 09 SOURCE REGISTER (SRC-01…08) | Y77: 2026-04-25 to 2026-09-19 | Z77: see 09 | AB77: =IF(COUNTIF($A$5:$A$999,A77)>1,"DUPLICATE","")
A78: PLB-PPR-175 | B78: Plumbing | C78: Water supply | D78: PPR PN-20 1-1/2" | E78: Providing and fixing PPR PN-20 pipe 1-1/2" with fusion-welded fittings and clamps, concealed or exposed, pressure-tested, complete in all respects. | F78: Fittings per Rft: elbow 0.15, socket 1/13.12, tee 0.08 (assumptions); fittings column mapping to verify | G78: Rft | H78: =City -> Lahore | I78: 2026-09-27 | J78: ='04 DETAILED RATE ANALYSIS'!J1696 -> 738.70553 | K78: ='04 DETAILED RATE ANALYSIS'!J1699 -> 118.22857 | L78: ='04 DETAILED RATE ANALYSIS'!J1700 -> 0 | M78: ='04 DETAILED RATE ANALYSIS'!J1701 -> 0 | N78: ='04 DETAILED RATE ANALYSIS'!J1697 -> 29.1525 | O78: ='04 DETAILED RATE ANALYSIS'!J1702 -> 886.0866 | P78: ='04 DETAILED RATE ANALYSIS'!J1703+'04 DETAILED RATE ANALYSIS'!J1704 -> 70.886928 | Q78: ='04 DETAILED RATE ANALYSIS'!J1705 -> 88.60866 | R78: ='04 DETAILED RATE ANALYSIS'!J1707 -> 0 | S78: ='04 DETAILED RATE ANALYSIS'!J1708 -> 1046 | T78: =S78*100 -> 104600 | U78: =IF(W78>0,"INCOMPLETE – "&W78&" blank/old input(s)","Market-derived + assumptions") -> INCOMPLETE – 1 blank/old input(s) | V78: Low | W78: ='04 DETAILED RATE ANALYSIS'!J1709 -> 1 | X78: See 09 SOURCE REGISTER (SRC-01…08) | Y78: 2026-04-25 to 2026-09-19 | Z78: see 09 | AB78: =IF(COUNTIF($A$5:$A$999,A78)>1,"DUPLICATE","")
A79: PLB-PPR-200 | B79: Plumbing | C79: Water supply | D79: PPR PN-20 2" | E79: Providing and fixing PPR PN-20 pipe 2" with fusion-welded fittings and clamps, concealed or exposed, pressure-tested, complete in all respects. | F79: Fittings per Rft: elbow 0.15, socket 1/13.12, tee 0.08 (assumptions); fittings column mapping to verify | G79: Rft | H79: =City -> Lahore | I79: 2026-09-27 | J79: ='04 DETAILED RATE ANALYSIS'!J1720 -> 1201.078 | K79: ='04 DETAILED RATE ANALYSIS'!J1723 -> 118.22857 | L79: ='04 DETAILED RATE ANALYSIS'!J1724 -> 0 | M79: ='04 DETAILED RATE ANALYSIS'!J1725 -> 0 | N79: ='04 DETAILED RATE ANALYSIS'!J1721 -> 47.8815 | O79: ='04 DETAILED RATE ANALYSIS'!J1726 -> 1367.188 | P79: ='04 DETAILED RATE ANALYSIS'!J1727+'04 DETAILED RATE ANALYSIS'!J1728 -> 109.37504 | Q79: ='04 DETAILED RATE ANALYSIS'!J1729 -> 136.7188 | R79: ='04 DETAILED RATE ANALYSIS'!J1731 -> 0 | S79: ='04 DETAILED RATE ANALYSIS'!J1732 -> 1613 | T79: =S79*100 -> 161300 | U79: =IF(W79>0,"INCOMPLETE – "&W79&" blank/old input(s)","Market-derived + assumptions") -> INCOMPLETE – 1 blank/old input(s) | V79: Low | W79: ='04 DETAILED RATE ANALYSIS'!J1733 -> 1 | X79: See 09 SOURCE REGISTER (SRC-01…08) | Y79: 2026-04-25 to 2026-09-19 | Z79: see 09 | AB79: =IF(COUNTIF($A$5:$A$999,A79)>1,"DUPLICATE","")
A80: PLB-PPR-250 | B80: Plumbing | C80: Water supply | D80: PPR PN-20 2-1/2" | E80: Providing and fixing PPR PN-20 pipe 2-1/2" with fusion-welded fittings and clamps, concealed or exposed, pressure-tested, complete in all respects. | F80: Fittings per Rft: elbow 0.15, socket 1/13.12, tee 0.08 (assumptions); fittings column mapping to verify | G80: Rft | H80: =City -> Lahore | I80: 2026-09-27 | J80: ='04 DETAILED RATE ANALYSIS'!J1744 -> 1756.6404 | K80: ='04 DETAILED RATE ANALYSIS'!J1747 -> 165.52 | L80: ='04 DETAILED RATE ANALYSIS'!J1748 -> 0 | M80: ='04 DETAILED RATE ANALYSIS'!J1749 -> 0 | N80: ='04 DETAILED RATE ANALYSIS'!J1745 -> 67.3425 | O80: ='04 DETAILED RATE ANALYSIS'!J1750 -> 1989.5029 | P80: ='04 DETAILED RATE ANALYSIS'!J1751+'04 DETAILED RATE ANALYSIS'!J1752 -> 159.16023 | Q80: ='04 DETAILED RATE ANALYSIS'!J1753 -> 198.95029 | R80: ='04 DETAILED RATE ANALYSIS'!J1755 -> 0 | S80: ='04 DETAILED RATE ANALYSIS'!J1756 -> 2348 | T80: =S80*100 -> 234800 | U80: =IF(W80>0,"INCOMPLETE – "&W80&" blank/old input(s)","Market-derived + assumptions") -> INCOMPLETE – 1 blank/old input(s) | V80: Low | W80: ='04 DETAILED RATE ANALYSIS'!J1757 -> 1 | X80: See 09 SOURCE REGISTER (SRC-01…08) | Y80: 2026-04-25 to 2026-09-19 | Z80: see 09 | AB80: =IF(COUNTIF($A$5:$A$999,A80)>1,"DUPLICATE","")
A81: PLB-PPR-300 | B81: Plumbing | C81: Water supply | D81: PPR PN-20 3" | E81: Providing and fixing PPR PN-20 pipe 3" with fusion-welded fittings and clamps, concealed or exposed, pressure-tested, complete in all respects. | F81: Fittings per Rft: elbow 0.15, socket 1/13.12, tee 0.08 (assumptions); fittings column mapping to verify | G81: Rft | H81: =City -> Lahore | I81: 2026-09-27 | J81: ='04 DETAILED RATE ANALYSIS'!J1768 -> 2680.9892 | K81: ='04 DETAILED RATE ANALYSIS'!J1771 -> 206.9 | L81: ='04 DETAILED RATE ANALYSIS'!J1772 -> 0 | M81: ='04 DETAILED RATE ANALYSIS'!J1773 -> 0 | N81: ='04 DETAILED RATE ANALYSIS'!J1769 -> 99.36 | O81: ='04 DETAILED RATE ANALYSIS'!J1774 -> 2987.2492 | P81: ='04 DETAILED RATE ANALYSIS'!J1775+'04 DETAILED RATE ANALYSIS'!J1776 -> 238.97993 | Q81: ='04 DETAILED RATE ANALYSIS'!J1777 -> 298.72492 | R81: ='04 DETAILED RATE ANALYSIS'!J1779 -> 0 | S81: ='04 DETAILED RATE ANALYSIS'!J1780 -> 3525 | T81: =S81*100 -> 352500 | U81: =IF(W81>0,"INCOMPLETE – "&W81&" blank/old input(s)","Market-derived + assumptions") -> INCOMPLETE – 1 blank/old input(s) | V81: Low | W81: ='04 DETAILED RATE ANALYSIS'!J1781 -> 1 | X81: See 09 SOURCE REGISTER (SRC-01…08) | Y81: 2026-04-25 to 2026-09-19 | Z81: see 09 | AB81: =IF(COUNTIF($A$5:$A$999,A81)>1,"DUPLICATE","")
A82: PLB-PPR-400 | B82: Plumbing | C82: Water supply | D82: PPR PN-20 4" | E82: Providing and fixing PPR PN-20 pipe 4" with fusion-welded fittings and clamps, concealed or exposed, pressure-tested, complete in all respects. | F82: Fittings per Rft: elbow 0.15, socket 1/13.12, tee 0.08 (assumptions); fittings column mapping to verify | G82: Rft | H82: =City -> Lahore | I82: 2026-09-27 | J82: ='04 DETAILED RATE ANALYSIS'!J1792 -> 4125.8067 | K82: ='04 DETAILED RATE ANALYSIS'!J1795 -> 243.41176 | L82: ='04 DETAILED RATE ANALYSIS'!J1796 -> 0 | M82: ='04 DETAILED RATE ANALYSIS'!J1797 -> 0 | N82: ='04 DETAILED RATE ANALYSIS'!J1793 -> 141.8775 | O82: ='04 DETAILED RATE ANALYSIS'!J1798 -> 4511.096 | P82: ='04 DETAILED RATE ANALYSIS'!J1799+'04 DETAILED RATE ANALYSIS'!J1800 -> 360.88768 | Q82: ='04 DETAILED RATE ANALYSIS'!J1801 -> 451.1096 | R82: ='04 DETAILED RATE ANALYSIS'!J1803 -> 0 | S82: ='04 DETAILED RATE ANALYSIS'!J1804 -> 5323 | T82: =S82*100 -> 532300 | U82: =IF(W82>0,"INCOMPLETE – "&W82&" blank/old input(s)","Market-derived + assumptions") -> INCOMPLETE – 1 blank/old input(s) | V82: Low | W82: ='04 DETAILED RATE ANALYSIS'!J1805 -> 1 | X82: See 09 SOURCE REGISTER (SRC-01…08) | Y82: 2026-04-25 to 2026-09-19 | Z82: see 09 | AB82: =IF(COUNTIF($A$5:$A$999,A82)>1,"DUPLICATE","")
A83: PLB-SWV-200 | B83: Plumbing | C83: Drainage | D83: uPVC SWV 2" | E83: Providing and fixing uPVC soil/waste/vent pipe 2" to BS EN 1329 with solvent-welded fittings and clamps, tested, complete in all respects. | F83: Fittings 0.10 elbow + 0.08 tee per Rft; solvent 0.005 kg/Rft; 60 Rft/day (assumptions) | G83: Rft | H83: =City -> Lahore | I83: 2026-09-27 | J83: ='04 DETAILED RATE ANALYSIS'!J1816 -> 219.5556 | K83: ='04 DETAILED RATE ANALYSIS'!J1819 -> 118.22857 | L83: ='04 DETAILED RATE ANALYSIS'!J1820 -> 0 | M83: ='04 DETAILED RATE ANALYSIS'!J1821 -> 0 | N83: ='04 DETAILED RATE ANALYSIS'!J1817 -> 8 | O83: ='04 DETAILED RATE ANALYSIS'!J1822 -> 345.78417 | P83: ='04 DETAILED RATE ANALYSIS'!J1823+'04 DETAILED RATE ANALYSIS'!J1824 -> 27.662734 | Q83: ='04 DETAILED RATE ANALYSIS'!J1825 -> 34.578417 | R83: ='04 DETAILED RATE ANALYSIS'!J1827 -> 0 | S83: ='04 DETAILED RATE ANALYSIS'!J1828 -> 408 | T83: =S83*100 -> 40800 | U83: =IF(W83>0,"INCOMPLETE – "&W83&" blank/old input(s)","Market-derived + assumptions") -> INCOMPLETE – 1 blank/old input(s) | V83: Low | W83: ='04 DETAILED RATE ANALYSIS'!J1829 -> 1 | X83: See 09 SOURCE REGISTER (SRC-01…08) | Y83: 2026-04-25 to 2026-09-19 | Z83: see 09 | AB83: =IF(COUNTIF($A$5:$A$999,A83)>1,"DUPLICATE","")
A84: PLB-SWV-300 | B84: Plumbing | C84: Drainage | D84: uPVC SWV 3" | E84: Providing and fixing uPVC soil/waste/vent pipe 3" to BS EN 1329 with solvent-welded fittings and clamps, tested, complete in all respects. | F84: Fittings 0.10 elbow + 0.08 tee per Rft; solvent 0.005 kg/Rft; 60 Rft/day (assumptions) | G84: Rft | H84: =City -> Lahore | I84: 2026-09-27 | J84: ='04 DETAILED RATE ANALYSIS'!J1840 -> 363.5556 | K84: ='04 DETAILED RATE ANALYSIS'!J1843 -> 258.625 | L84: ='04 DETAILED RATE ANALYSIS'!J1844 -> 0 | M84: ='04 DETAILED RATE ANALYSIS'!J1845 -> 0 | N84: ='04 DETAILED RATE ANALYSIS'!J1841 -> 15.2 | O84: ='04 DETAILED RATE ANALYSIS'!J1846 -> 637.3806 | P84: ='04 DETAILED RATE ANALYSIS'!J1847+'04 DETAILED RATE ANALYSIS'!J1848 -> 50.990448 | Q84: ='04 DETAILED RATE ANALYSIS'!J1849 -> 63.73806 | R84: ='04 DETAILED RATE ANALYSIS'!J1851 -> 0 | S84: ='04 DETAILED RATE ANALYSIS'!J1852 -> 752 | T84: =S84*100 -> 75200 | U84: =IF(W84>0,"INCOMPLETE – "&W84&" blank/old input(s)","Market-derived + assumptions") -> INCOMPLETE – 1 blank/old input(s) | V84: Low | W84: ='04 DETAILED RATE ANALYSIS'!J1853 -> 1 | X84: See 09 SOURCE REGISTER (SRC-01…08) | Y84: 2026-04-25 to 2026-09-19 | Z84: see 09 | AB84: =IF(COUNTIF($A$5:$A$999,A84)>1,"DUPLICATE","")
A85: PLB-SWV-400 | B85: Plumbing | C85: Drainage | D85: uPVC SWV 4" | E85: Providing and fixing uPVC soil/waste/vent pipe 4" to BS EN 1329 with solvent-welded fittings and clamps, tested, complete in all respects. | F85: Fittings 0.10 elbow + 0.08 tee per Rft; solvent 0.005 kg/Rft; 60 Rft/day (assumptions) | G85: Rft | H85: =City -> Lahore | I85: 2026-09-27 | J85: ='04 DETAILED RATE ANALYSIS'!J1864 -> 674.575 | K85: ='04 DETAILED RATE ANALYSIS'!J1867 -> 275.86667 | L85: ='04 DETAILED RATE ANALYSIS'!J1868 -> 0 | M85: ='04 DETAILED RATE ANALYSIS'!J1869 -> 0 | N85: ='04 DETAILED RATE ANALYSIS'!J1865 -> 24.85 | O85: ='04 DETAILED RATE ANALYSIS'!J1870 -> 975.29167 | P85: ='04 DETAILED RATE ANALYSIS'!J1871+'04 DETAILED RATE ANALYSIS'!J1872 -> 78.023333 | Q85: ='04 DETAILED RATE ANALYSIS'!J1873 -> 97.529167 | R85: ='04 DETAILED RATE ANALYSIS'!J1875 -> 0 | S85: ='04 DETAILED RATE ANALYSIS'!J1876 -> 1151 | T85: =S85*100 -> 115100 | U85: =IF(W85>0,"INCOMPLETE – "&W85&" blank/old input(s)","Market-derived + assumptions") -> INCOMPLETE – 1 blank/old input(s) | V85: Low | W85: ='04 DETAILED RATE ANALYSIS'!J1877 -> 1 | X85: See 09 SOURCE REGISTER (SRC-01…08) | Y85: 2026-04-25 to 2026-09-19 | Z85: see 09 | AB85: =IF(COUNTIF($A$5:$A$999,A85)>1,"DUPLICATE","")
A86: PLB-FIX-001 | B86: Plumbing | C86: Fixtures | D86: WC floor-mounted | E86: Supplying and fixing floor-mounted WC with cistern and seat, connected to supply and drainage, complete in all respects. | F86: PC rate fixture | G86: Nos | H86: =City -> Lahore | I86: 2026-09-27 | J86: ='04 DETAILED RATE ANALYSIS'!J1885 -> 31896 | K86: ='04 DETAILED RATE ANALYSIS'!J1888 -> 4985.5422 | L86: ='04 DETAILED RATE ANALYSIS'!J1889 -> 0 | M86: ='04 DETAILED RATE ANALYSIS'!J1890 -> 0 | N86: ='04 DETAILED RATE ANALYSIS'!J1886 -> 0 | O86: ='04 DETAILED RATE ANALYSIS'!J1891 -> 36881.542 | P86: ='04 DETAILED RATE ANALYSIS'!J1892+'04 DETAILED RATE ANALYSIS'!J1893 -> 2950.5234 | Q86: ='04 DETAILED RATE ANALYSIS'!J1894 -> 3688.1542 | R86: ='04 DETAILED RATE ANALYSIS'!J1896 -> 0 | S86: ='04 DETAILED RATE ANALYSIS'!J1897 -> 43520 | T86: =S86*100 -> 4352000 | U86: =IF(W86>0,"INCOMPLETE – "&W86&" blank/old input(s)","Market-derived + assumptions") -> Market-derived + assumptions | V86: Low | W86: ='04 DETAILED RATE ANALYSIS'!J1898 -> 0 | X86: See 09 SOURCE REGISTER (SRC-01…08) | Y86: 2026-04-25 to 2026-09-19 | Z86: see 09 | AB86: =IF(COUNTIF($A$5:$A$999,A86)>1,"DUPLICATE","")
A87: PLB-FIX-002 | B87: Plumbing | C87: Fixtures | D87: Wash basin with mixer | E87: Supplying and fixing wash basin with pedestal and mixer, bottle trap and connections, complete in all respects. | F87: PC rate fixture | G87: Nos | H87: =City -> Lahore | I87: 2026-09-27 | J87: ='04 DETAILED RATE ANALYSIS'!J1906 -> 16364 | K87: ='04 DETAILED RATE ANALYSIS'!J1909 -> 4597.7778 | L87: ='04 DETAILED RATE ANALYSIS'!J1910 -> 0 | M87: ='04 DETAILED RATE ANALYSIS'!J1911 -> 0 | N87: ='04 DETAILED RATE ANALYSIS'!J1907 -> 0 | O87: ='04 DETAILED RATE ANALYSIS'!J1912 -> 20961.778 | P87: ='04 DETAILED RATE ANALYSIS'!J1913+'04 DETAILED RATE ANALYSIS'!J1914 -> 1676.9422 | Q87: ='04 DETAILED RATE ANALYSIS'!J1915 -> 2096.1778 | R87: ='04 DETAILED RATE ANALYSIS'!J1917 -> 0 | S87: ='04 DETAILED RATE ANALYSIS'!J1918 -> 24735 | T87: =S87*100 -> 2473500 | U87: =IF(W87>0,"INCOMPLETE – "&W87&" blank/old input(s)","Market-derived + assumptions") -> Market-derived + assumptions | V87: Low | W87: ='04 DETAILED RATE ANALYSIS'!J1919 -> 0 | X87: See 09 SOURCE REGISTER (SRC-01…08) | Y87: 2026-04-25 to 2026-09-19 | Z87: see 09 | AB87: =IF(COUNTIF($A$5:$A$999,A87)>1,"DUPLICATE","")
A88: FF-PIP-100 | B88: Fire fighting | C88: Piping | D88: Black steel Sch-40 1" | E88: Providing and installing black steel Sch-40 pipe 1" for fire-fighting with fittings, hangers and red enamel, hydro-tested, complete in all respects. | F88: 40 Rft/day pipe fitter + helper (assumption) | G88: Rft | H88: =City -> Lahore | I88: 2026-09-27 | J88: ='04 DETAILED RATE ANALYSIS'!J1929 -> 489.0975 | K88: ='04 DETAILED RATE ANALYSIS'!J1932 -> 179.91304 | L88: ='04 DETAILED RATE ANALYSIS'!J1933 -> 0 | M88: ='04 DETAILED RATE ANALYSIS'!J1934 -> 0 | N88: ='04 DETAILED RATE ANALYSIS'!J1930 -> 15.48 | O88: ='04 DETAILED RATE ANALYSIS'!J1935 -> 684.49054 | P88: ='04 DETAILED RATE ANALYSIS'!J1936+'04 DETAILED RATE ANALYSIS'!J1937 -> 54.759243 | Q88: ='04 DETAILED RATE ANALYSIS'!J1938 -> 68.449054 | R88: ='04 DETAILED RATE ANALYSIS'!J1940 -> 0 | S88: ='04 DETAILED RATE ANALYSIS'!J1941 -> 808 | T88: =S88*100 -> 80800 | U88: =IF(W88>0,"INCOMPLETE – "&W88&" blank/old input(s)","Market-derived + assumptions") -> INCOMPLETE – 2 blank/old input(s) | V88: Low | W88: ='04 DETAILED RATE ANALYSIS'!J1942 -> 2 | X88: See 09 SOURCE REGISTER (SRC-01…08) | Y88: 2026-04-25 to 2026-09-19 | Z88: see 09 | AB88: =IF(COUNTIF($A$5:$A$999,A88)>1,"DUPLICATE","")
A89: FF-PIP-200 | B89: Fire fighting | C89: Piping | D89: Black steel Sch-40 2" | E89: Providing and installing black steel Sch-40 pipe 2" for fire-fighting with fittings, hangers and red enamel, hydro-tested, complete in all respects. | F89: 40 Rft/day pipe fitter + helper (assumption) | G89: Rft | H89: =City -> Lahore | I89: 2026-09-27 | J89: ='04 DETAILED RATE ANALYSIS'!J1952 -> 996.7575 | K89: ='04 DETAILED RATE ANALYSIS'!J1955 -> 295.57143 | L89: ='04 DETAILED RATE ANALYSIS'!J1956 -> 0 | M89: ='04 DETAILED RATE ANALYSIS'!J1957 -> 0 | N89: ='04 DETAILED RATE ANALYSIS'!J1953 -> 32.596 | O89: ='04 DETAILED RATE ANALYSIS'!J1958 -> 1324.9249 | P89: ='04 DETAILED RATE ANALYSIS'!J1959+'04 DETAILED RATE ANALYSIS'!J1960 -> 105.99399 | Q89: ='04 DETAILED RATE ANALYSIS'!J1961 -> 132.49249 | R89: ='04 DETAILED RATE ANALYSIS'!J1963 -> 0 | S89: ='04 DETAILED RATE ANALYSIS'!J1964 -> 1563 | T89: =S89*100 -> 156300 | U89: =IF(W89>0,"INCOMPLETE – "&W89&" blank/old input(s)","Market-derived + assumptions") -> INCOMPLETE – 2 blank/old input(s) | V89: Low | W89: ='04 DETAILED RATE ANALYSIS'!J1965 -> 2 | X89: See 09 SOURCE REGISTER (SRC-01…08) | Y89: 2026-04-25 to 2026-09-19 | Z89: see 09 | AB89: =IF(COUNTIF($A$5:$A$999,A89)>1,"DUPLICATE","")
A90: FF-PIP-400 | B90: Fire fighting | C90: Piping | D90: Black steel Sch-40 4" grooved | E90: Providing and installing black steel Sch-40 pipe 4" grooved for fire-fighting with fittings, hangers and red enamel, hydro-tested, complete in all respects. | F90: 40 Rft/day pipe fitter + helper (assumption) | G90: Rft | H90: =City -> Lahore | I90: 2026-09-27 | J90: ='04 DETAILED RATE ANALYSIS'!J1975 -> 2816.0075 | K90: ='04 DETAILED RATE ANALYSIS'!J1978 -> 551.73333 | L90: ='04 DETAILED RATE ANALYSIS'!J1979 -> 0 | M90: ='04 DETAILED RATE ANALYSIS'!J1980 -> 0 | N90: ='04 DETAILED RATE ANALYSIS'!J1976 -> 93.933 | O90: ='04 DETAILED RATE ANALYSIS'!J1981 -> 3461.6738 | P90: ='04 DETAILED RATE ANALYSIS'!J1982+'04 DETAILED RATE ANALYSIS'!J1983 -> 276.93391 | Q90: ='04 DETAILED RATE ANALYSIS'!J1984 -> 346.16738 | R90: ='04 DETAILED RATE ANALYSIS'!J1986 -> 0 | S90: ='04 DETAILED RATE ANALYSIS'!J1987 -> 4085 | T90: =S90*100 -> 408500 | U90: =IF(W90>0,"INCOMPLETE – "&W90&" blank/old input(s)","Market-derived + assumptions") -> INCOMPLETE – 2 blank/old input(s) | V90: Low | W90: ='04 DETAILED RATE ANALYSIS'!J1988 -> 2 | X90: See 09 SOURCE REGISTER (SRC-01…08) | Y90: 2026-04-25 to 2026-09-19 | Z90: see 09 | AB90: =IF(COUNTIF($A$5:$A$999,A90)>1,"DUPLICATE","")
A91: FF-SPL-001 | B91: Fire fighting | C91: Sprinklers | D91: Pendent sprinkler incl. drop | E91: Supplying and installing pendent sprinkler head with 1" drop (avg 3 Rft), complete in all respects. | F91: Drop 3 Rft of 1" pipe | G91: Nos | H91: =City -> Lahore | I91: 2026-09-27 | J91: ='04 DETAILED RATE ANALYSIS'!J1996 -> 2863.8 | K91: ='04 DETAILED RATE ANALYSIS'!J1999 -> 713.44828 | L91: ='04 DETAILED RATE ANALYSIS'!J2000 -> 0 | M91: ='04 DETAILED RATE ANALYSIS'!J2001 -> 0 | N91: ='04 DETAILED RATE ANALYSIS'!J1997 -> 0 | O91: ='04 DETAILED RATE ANALYSIS'!J2002 -> 3577.2483 | P91: ='04 DETAILED RATE ANALYSIS'!J2003+'04 DETAILED RATE ANALYSIS'!J2004 -> 286.17986 | Q91: ='04 DETAILED RATE ANALYSIS'!J2005 -> 357.72483 | R91: ='04 DETAILED RATE ANALYSIS'!J2007 -> 0 | S91: ='04 DETAILED RATE ANALYSIS'!J2008 -> 4221 | T91: =S91*100 -> 422100 | U91: =IF(W91>0,"INCOMPLETE – "&W91&" blank/old input(s)","Market-derived + assumptions") -> INCOMPLETE – 1 blank/old input(s) | V91: Low | W91: ='04 DETAILED RATE ANALYSIS'!J2009 -> 1 | X91: See 09 SOURCE REGISTER (SRC-01…08) | Y91: 2026-04-25 to 2026-09-19 | Z91: see 09 | AB91: =IF(COUNTIF($A$5:$A$999,A91)>1,"DUPLICATE","")
A92: FF-HR-001 | B92: Fire fighting | C92: Hose reels | D92: Hose reel cabinet | E92: Supplying and installing hose reel cabinet complete with reel, valve and nozzle, complete in all respects. | F92: Vendor supply | G92: Nos | H92: =City -> Lahore | I92: 2026-09-27 | J92: ='04 DETAILED RATE ANALYSIS'!J2016 -> 103085 | K92: ='04 DETAILED RATE ANALYSIS'!J2019 -> 2069 | L92: ='04 DETAILED RATE ANALYSIS'!J2020 -> 0 | M92: ='04 DETAILED RATE ANALYSIS'!J2021 -> 0 | N92: ='04 DETAILED RATE ANALYSIS'!J2017 -> 0 | O92: ='04 DETAILED RATE ANALYSIS'!J2022 -> 105154 | P92: ='04 DETAILED RATE ANALYSIS'!J2023+'04 DETAILED RATE ANALYSIS'!J2024 -> 8412.32 | Q92: ='04 DETAILED RATE ANALYSIS'!J2025 -> 10515.4 | R92: ='04 DETAILED RATE ANALYSIS'!J2027 -> 0 | S92: ='04 DETAILED RATE ANALYSIS'!J2028 -> 124082 | T92: =S92*100 -> 12408200 | U92: =IF(W92>0,"INCOMPLETE – "&W92&" blank/old input(s)","Market-derived + assumptions") -> Market-derived + assumptions | V92: Low | W92: ='04 DETAILED RATE ANALYSIS'!J2029 -> 0 | X92: See 09 SOURCE REGISTER (SRC-01…08) | Y92: 2026-04-25 to 2026-09-19 | Z92: see 09 | AB92: =IF(COUNTIF($A$5:$A$999,A92)>1,"DUPLICATE","")
A93: ELE-CND-075 | B93: Electrical | C93: Conduits | D93: uPVC conduit 3/4" concealed | E93: Providing and laying uPVC conduit 3/4" concealed in walls/slabs including chasing and making good, sockets and bends, complete in all respects. | F93: 1 socket per 10 ft length; 1 bend per 10 Rft; 100 Rft/day incl. chasing (assumption) | G93: Rft | H93: =City -> Lahore | I93: 2026-09-27 | J93: ='04 DETAILED RATE ANALYSIS'!J2038 -> 48.58 | K93: ='04 DETAILED RATE ANALYSIS'!J2041 -> 43.38 | L93: ='04 DETAILED RATE ANALYSIS'!J2042 -> 0 | M93: ='04 DETAILED RATE ANALYSIS'!J2043 -> 0 | N93: ='04 DETAILED RATE ANALYSIS'!J2039 -> 2.2 | O93: ='04 DETAILED RATE ANALYSIS'!J2044 -> 94.16 | P93: ='04 DETAILED RATE ANALYSIS'!J2045+'04 DETAILED RATE ANALYSIS'!J2046 -> 7.5328 | Q93: ='04 DETAILED RATE ANALYSIS'!J2047 -> 9.416 | R93: ='04 DETAILED RATE ANALYSIS'!J2049 -> 0 | S93: ='04 DETAILED RATE ANALYSIS'!J2050 -> 111 | T93: =S93*100 -> 11100 | U93: =IF(W93>0,"INCOMPLETE – "&W93&" blank/old input(s)","Market-derived + assumptions") -> Market-derived + assumptions | V93: Low | W93: ='04 DETAILED RATE ANALYSIS'!J2051 -> 0 | X93: See 09 SOURCE REGISTER (SRC-01…08) | Y93: 2026-04-25 to 2026-09-19 | Z93: see 09 | AB93: =IF(COUNTIF($A$5:$A$999,A93)>1,"DUPLICATE","")
A94: ELE-CND-100 | B94: Electrical | C94: Conduits | D94: uPVC conduit 1" concealed | E94: Providing and laying uPVC conduit 1" concealed in walls/slabs including chasing and making good, sockets and bends, complete in all respects. | F94: 1 socket per 10 ft length; 1 bend per 10 Rft; 100 Rft/day incl. chasing (assumption) | G94: Rft | H94: =City -> Lahore | I94: 2026-09-27 | J94: ='04 DETAILED RATE ANALYSIS'!J2060 -> 67.1 | K94: ='04 DETAILED RATE ANALYSIS'!J2063 -> 43.38 | L94: ='04 DETAILED RATE ANALYSIS'!J2064 -> 0 | M94: ='04 DETAILED RATE ANALYSIS'!J2065 -> 0 | N94: ='04 DETAILED RATE ANALYSIS'!J2061 -> 3.02 | O94: ='04 DETAILED RATE ANALYSIS'!J2066 -> 113.5 | P94: ='04 DETAILED RATE ANALYSIS'!J2067+'04 DETAILED RATE ANALYSIS'!J2068 -> 9.08 | Q94: ='04 DETAILED RATE ANALYSIS'!J2069 -> 11.35 | R94: ='04 DETAILED RATE ANALYSIS'!J2071 -> 0 | S94: ='04 DETAILED RATE ANALYSIS'!J2072 -> 134 | T94: =S94*100 -> 13400 | U94: =IF(W94>0,"INCOMPLETE – "&W94&" blank/old input(s)","Market-derived + assumptions") -> Market-derived + assumptions | V94: Low | W94: ='04 DETAILED RATE ANALYSIS'!J2073 -> 0 | X94: See 09 SOURCE REGISTER (SRC-01…08) | Y94: 2026-04-25 to 2026-09-19 | Z94: see 09 | AB94: =IF(COUNTIF($A$5:$A$999,A94)>1,"DUPLICATE","")
A95: ELE-CBL-329 | B95: Electrical | C95: Wiring | D95: Wire 3/.029 in conduit | E95: Providing and drawing single-core PVC copper wire 3/.029 (BS-2004) in conduit, complete in all respects. | F95: 800 Rft/day (assumption) | G95: Rft | H95: =City -> Lahore | I95: 2026-09-27 | J95: ='04 DETAILED RATE ANALYSIS'!J2080 -> 25.56 | K95: ='04 DETAILED RATE ANALYSIS'!J2083 -> 5.4225 | L95: ='04 DETAILED RATE ANALYSIS'!J2084 -> 0 | M95: ='04 DETAILED RATE ANALYSIS'!J2085 -> 0 | N95: ='04 DETAILED RATE ANALYSIS'!J2081 -> 0.7668 | O95: ='04 DETAILED RATE ANALYSIS'!J2086 -> 31.7493 | P95: ='04 DETAILED RATE ANALYSIS'!J2087+'04 DETAILED RATE ANALYSIS'!J2088 -> 2.539944 | Q95: ='04 DETAILED RATE ANALYSIS'!J2089 -> 3.17493 | R95: ='04 DETAILED RATE ANALYSIS'!J2091 -> 0 | S95: ='04 DETAILED RATE ANALYSIS'!J2092 -> 37 | T95: =S95*100 -> 3700 | U95: =IF(W95>0,"INCOMPLETE – "&W95&" blank/old input(s)","Market-derived + assumptions") -> Market-derived + assumptions | V95: Medium | W95: ='04 DETAILED RATE ANALYSIS'!J2093 -> 0 | X95: See 09 SOURCE REGISTER (SRC-01…08) | Y95: 2026-04-25 to 2026-09-19 | Z95: see 09 | AB95: =IF(COUNTIF($A$5:$A$999,A95)>1,"DUPLICATE","")
A96: ELE-CBL-729 | B96: Electrical | C96: Wiring | D96: Wire 7/.029 in conduit | E96: Providing and drawing single-core PVC copper wire 7/.029 (BS-2004) in conduit, complete in all respects. | F96: 800 Rft/day (assumption) | G96: Rft | H96: =City -> Lahore | I96: 2026-09-27 | J96: ='04 DETAILED RATE ANALYSIS'!J2100 -> 39.66 | K96: ='04 DETAILED RATE ANALYSIS'!J2103 -> 5.4225 | L96: ='04 DETAILED RATE ANALYSIS'!J2104 -> 0 | M96: ='04 DETAILED RATE ANALYSIS'!J2105 -> 0 | N96: ='04 DETAILED RATE ANALYSIS'!J2101 -> 1.1898 | O96: ='04 DETAILED RATE ANALYSIS'!J2106 -> 46.2723 | P96: ='04 DETAILED RATE ANALYSIS'!J2107+'04 DETAILED RATE ANALYSIS'!J2108 -> 3.701784 | Q96: ='04 DETAILED RATE ANALYSIS'!J2109 -> 4.62723 | R96: ='04 DETAILED RATE ANALYSIS'!J2111 -> 0 | S96: ='04 DETAILED RATE ANALYSIS'!J2112 -> 55 | T96: =S96*100 -> 5500 | U96: =IF(W96>0,"INCOMPLETE – "&W96&" blank/old input(s)","Market-derived + assumptions") -> Market-derived + assumptions | V96: Medium | W96: ='04 DETAILED RATE ANALYSIS'!J2113 -> 0 | X96: See 09 SOURCE REGISTER (SRC-01…08) | Y96: 2026-04-25 to 2026-09-19 | Z96: see 09 | AB96: =IF(COUNTIF($A$5:$A$999,A96)>1,"DUPLICATE","")
A97: ELE-CBL-744 | B97: Electrical | C97: Wiring | D97: Wire 7/.044 in conduit | E97: Providing and drawing single-core PVC copper wire 7/.044 (BS-2004) in conduit, complete in all respects. | F97: 800 Rft/day (assumption) | G97: Rft | H97: =City -> Lahore | I97: 2026-09-27 | J97: ='04 DETAILED RATE ANALYSIS'!J2120 -> 63.19 | K97: ='04 DETAILED RATE ANALYSIS'!J2123 -> 5.4225 | L97: ='04 DETAILED RATE ANALYSIS'!J2124 -> 0 | M97: ='04 DETAILED RATE ANALYSIS'!J2125 -> 0 | N97: ='04 DETAILED RATE ANALYSIS'!J2121 -> 1.8957 | O97: ='04 DETAILED RATE ANALYSIS'!J2126 -> 70.5082 | P97: ='04 DETAILED RATE ANALYSIS'!J2127+'04 DETAILED RATE ANALYSIS'!J2128 -> 5.640656 | Q97: ='04 DETAILED RATE ANALYSIS'!J2129 -> 7.05082 | R97: ='04 DETAILED RATE ANALYSIS'!J2131 -> 0 | S97: ='04 DETAILED RATE ANALYSIS'!J2132 -> 83 | T97: =S97*100 -> 8300 | U97: =IF(W97>0,"INCOMPLETE – "&W97&" blank/old input(s)","Market-derived + assumptions") -> Market-derived + assumptions | V97: Medium | W97: ='04 DETAILED RATE ANALYSIS'!J2133 -> 0 | X97: See 09 SOURCE REGISTER (SRC-01…08) | Y97: 2026-04-25 to 2026-09-19 | Z97: see 09 | AB97: =IF(COUNTIF($A$5:$A$999,A97)>1,"DUPLICATE","")
A98: ELE-PNT-001 | B98: Electrical | C98: Points | D98: Light point complete | E98: Wiring a light point with 3/.029 wires (phase, neutral, earth) in 3/4" uPVC conduit, avg 25 Rft run, with switch, boxes, complete in all respects. | F98: Conduit 25 Rft; wire 3×25 = 75 Rft | G98: Nos | H98: =City -> Lahore | I98: 2026-09-27 | J98: ='04 DETAILED RATE ANALYSIS'!J2145 -> 3650 | K98: ='04 DETAILED RATE ANALYSIS'!J2148 -> 1084.5 | L98: ='04 DETAILED RATE ANALYSIS'!J2149 -> 0 | M98: ='04 DETAILED RATE ANALYSIS'!J2150 -> 0 | N98: ='04 DETAILED RATE ANALYSIS'!J2146 -> 112.51 | O98: ='04 DETAILED RATE ANALYSIS'!J2151 -> 4847.01 | P98: ='04 DETAILED RATE ANALYSIS'!J2152+'04 DETAILED RATE ANALYSIS'!J2153 -> 387.7608 | Q98: ='04 DETAILED RATE ANALYSIS'!J2154 -> 484.701 | R98: ='04 DETAILED RATE ANALYSIS'!J2156 -> 0 | S98: ='04 DETAILED RATE ANALYSIS'!J2157 -> 5719 | T98: =S98*100 -> 571900 | U98: =IF(W98>0,"INCOMPLETE – "&W98&" blank/old input(s)","Market-derived + assumptions") -> Market-derived + assumptions | V98: Low | W98: ='04 DETAILED RATE ANALYSIS'!J2158 -> 0 | X98: See 09 SOURCE REGISTER (SRC-01…08) | Y98: 2026-04-25 to 2026-09-19 | Z98: see 09 | AB98: =IF(COUNTIF($A$5:$A$999,A98)>1,"DUPLICATE","")
A99: ELE-PNT-002 | B99: Electrical | C99: Points | D99: 15A power point complete | E99: Wiring a 15A power point with 7/.029 wires in 3/4" uPVC conduit, avg 30 Rft run, with socket and box, complete in all respects. | F99: Conduit 30 Rft; wire 3×30 = 90 Rft | G99: Nos | H99: =City -> Lahore | I99: 2026-09-27 | J99: ='04 DETAILED RATE ANALYSIS'!J2169 -> 6070.4 | K99: ='04 DETAILED RATE ANALYSIS'!J2172 -> 1301.4 | L99: ='04 DETAILED RATE ANALYSIS'!J2173 -> 0 | M99: ='04 DETAILED RATE ANALYSIS'!J2174 -> 0 | N99: ='04 DETAILED RATE ANALYSIS'!J2170 -> 173.082 | O99: ='04 DETAILED RATE ANALYSIS'!J2175 -> 7544.882 | P99: ='04 DETAILED RATE ANALYSIS'!J2176+'04 DETAILED RATE ANALYSIS'!J2177 -> 603.59056 | Q99: ='04 DETAILED RATE ANALYSIS'!J2178 -> 754.4882 | R99: ='04 DETAILED RATE ANALYSIS'!J2180 -> 0 | S99: ='04 DETAILED RATE ANALYSIS'!J2181 -> 8903 | T99: =S99*100 -> 890300 | U99: =IF(W99>0,"INCOMPLETE – "&W99&" blank/old input(s)","Market-derived + assumptions") -> Market-derived + assumptions | V99: Low | W99: ='04 DETAILED RATE ANALYSIS'!J2182 -> 0 | X99: See 09 SOURCE REGISTER (SRC-01…08) | Y99: 2026-04-25 to 2026-09-19 | Z99: see 09 | AB99: =IF(COUNTIF($A$5:$A$999,A99)>1,"DUPLICATE","")
A100: ELE-ERT-001 | B100: Electrical | C100: Earthing | D100: Earth pit | E100: Constructing earth pit with copper electrode, GI pipe, earth-enhancing compound and inspection chamber, tested, complete in all respects. | F100: Materials as set | G100: Nos | H100: =City -> Lahore | I100: 2026-09-27 | J100: ='04 DETAILED RATE ANALYSIS'!J2189 -> 43731.2 | K100: ='04 DETAILED RATE ANALYSIS'!J2192 -> 5876 | L100: ='04 DETAILED RATE ANALYSIS'!J2193 -> 0 | M100: ='04 DETAILED RATE ANALYSIS'!J2194 -> 0 | N100: ='04 DETAILED RATE ANALYSIS'!J2190 -> 0 | O100: ='04 DETAILED RATE ANALYSIS'!J2195 -> 49607.2 | P100: ='04 DETAILED RATE ANALYSIS'!J2196+'04 DETAILED RATE ANALYSIS'!J2197 -> 3968.576 | Q100: ='04 DETAILED RATE ANALYSIS'!J2198 -> 4960.72 | R100: ='04 DETAILED RATE ANALYSIS'!J2200 -> 0 | S100: ='04 DETAILED RATE ANALYSIS'!J2201 -> 58536 | T100: =S100*100 -> 5853600 | U100: =IF(W100>0,"INCOMPLETE – "&W100&" blank/old input(s)","Market-derived + assumptions") -> Market-derived + assumptions | V100: Low | W100: ='04 DETAILED RATE ANALYSIS'!J2202 -> 0 | X100: See 09 SOURCE REGISTER (SRC-01…08) | Y100: 2026-04-25 to 2026-09-19 | Z100: see 09 | AB100: =IF(COUNTIF($A$5:$A$999,A100)>1,"DUPLICATE","")
A101: ELE-DB-001 | B101: Electrical | C101: Distribution | D101: DB supply & install | E101: Supplying and installing populated distribution board, terminated and tested, complete in all respects. | F101: Vendor supply | G101: Nos | H101: =City -> Lahore | I101: 2026-09-27 | J101: ='04 DETAILED RATE ANALYSIS'!J2209 -> 59777.62 | K101: ='04 DETAILED RATE ANALYSIS'!J2212 -> 4338 | L101: ='04 DETAILED RATE ANALYSIS'!J2213 -> 0 | M101: ='04 DETAILED RATE ANALYSIS'!J2214 -> 0 | N101: ='04 DETAILED RATE ANALYSIS'!J2210 -> 0 | O101: ='04 DETAILED RATE ANALYSIS'!J2215 -> 64115.62 | P101: ='04 DETAILED RATE ANALYSIS'!J2216+'04 DETAILED RATE ANALYSIS'!J2217 -> 5129.2496 | Q101: ='04 DETAILED RATE ANALYSIS'!J2218 -> 6411.562 | R101: ='04 DETAILED RATE ANALYSIS'!J2220 -> 0 | S101: ='04 DETAILED RATE ANALYSIS'!J2221 -> 75656 | T101: =S101*100 -> 7565600 | U101: =IF(W101>0,"INCOMPLETE – "&W101&" blank/old input(s)","Market-derived + assumptions") -> INCOMPLETE – 1 blank/old input(s) | V101: Low | W101: ='04 DETAILED RATE ANALYSIS'!J2222 -> 1 | X101: See 09 SOURCE REGISTER (SRC-01…08) | Y101: 2026-04-25 to 2026-09-19 | Z101: see 09 | AB101: =IF(COUNTIF($A$5:$A$999,A101)>1,"DUPLICATE","")
...

Sheet 04 DETAILED RATE ANALYSIS
A1: 04 · DETAILED RATE ANALYSIS
A2: Amount = Adjusted Qty × Base Rate; Adjusted Qty = Consumption × (1 + Wastage). Base rates are live lookups from 05/06/07.
A4: CIV-CON-001 | B4: Providing and laying 5000 PSI concrete (Lab ACI 211.1 – 5000 PSI (W/C 0.34); mix per Image 1 – ACI 211.1 lab sheet) in structural members, including batching, placing, compacting and curing, complete in all respects; excluding reinforcement and formwork measured separately. | J4: Unit: cft
A5: Item Code | B5: Component | C5: Resource Code | D5: Description | E5: Unit | F5: Consumption / unit | G5: Base Rate PKR | H5: Wastage % | I5: Adjusted Qty | J5: Amount PKR | K5: Input flag
A6: CIV-CON-001 | B6: Material | C6: MAT-CEM-OPC | D6: OPC | E6: bag | F6: ='15 MIX DESIGN LIBRARY'!J5 -> 0.31148237 | G6: =N(INDEX('05 MATERIAL RATE LIBRARY'!$E$5:$E$400,MATCH("MAT-CEM-OPC",'05 MATERIAL RATE LIBRARY'!$A$5:$A$400,0))) -> 1575 | H6: =W_Cem -> 0.02 | I6: =F6*(1+H6) -> 0.31771202 | J6: =I6*G6 -> 500.39643 | K6: =IF(INDEX('05 MATERIAL RATE LIBRARY'!$M$5:$M$400,MATCH("MAT-CEM-OPC",'05 MATERIAL RATE LIBRARY'!$A$5:$A$400,0))=1,"",IF(INDEX('05 MATERIAL RATE LIBRARY'!$M$5:$M$400,MATCH("MAT-CEM-OPC",'05 MATERIAL RATE LIBRARY'!$A$5:$A$400,0))=2,"OLD RATE","NO RATE"))
A7: CIV-CON-001 | B7: Material | C7: MAT-CRS-SGD | D7: C/Agg 3/4"–1/2" Sargodha | E7: cft | F7: ='15 MIX DESIGN LIBRARY'!J6 -> 0.27890165 | G7: =N(INDEX('05 MATERIAL RATE LIBRARY'!$E$5:$E$400,MATCH("MAT-CRS-SGD",'05 MATERIAL RATE LIBRARY'!$A$5:$A$400,0))) -> 185 | H7: =W_Agg -> 0.05 | I7: =F7*(1+H7) -> 0.29284673 | J7: =I7*G7 -> 54.176645 | K7: =IF(INDEX('05 MATERIAL RATE LIBRARY'!$M$5:$M$400,MATCH("MAT-CRS-SGD",'05 MATERIAL RATE LIBRARY'!$A$5:$A$400,0))=1,"",IF(INDEX('05 MATERIAL RATE LIBRARY'!$M$5:$M$400,MATCH("MAT-CRS-SGD",'05 MATERIAL RATE LIBRARY'!$A$5:$A$400,0))=2,"OLD RATE","NO RATE"))
A8: CIV-CON-001 | B8: Material | C8: MAT-CRS-SGD | D8: C/Agg 1/2"–3/16" Sargodha | E8: cft | F8: ='15 MIX DESIGN LIBRARY'!J7 -> 0.41835247 | G8: =N(INDEX('05 MATERIAL RATE LIBRARY'!$E$5:$E$400,MATCH("MAT-CRS-SGD",'05 MATERIAL RATE LIBRARY'!$A$5:$A$400,0))) -> 185 | H8: =W_Agg -> 0.05 | I8: =F8*(1+H8) -> 0.4392701 | J8: =I8*G8 -> 81.264968 | K8: =IF(INDEX('05 MATERIAL RATE LIBRARY'!$M$5:$M$400,MATCH("MAT-CRS-SGD",'05 MATERIAL RATE LIBRARY'!$A$5:$A$400,0))=1,"",IF(INDEX('05 MATERIAL RATE LIBRARY'!$M$5:$M$400,MATCH("MAT-CRS-SGD",'05 MATERIAL RATE LIBRARY'!$A$5:$A$400,0))=2,"OLD RATE","NO RATE"))
A9: CIV-CON-001 | B9: Material | C9: MAT-SND-LWP | D9: Sand Lawrencepur | E9: cft | F9: ='15 MIX DESIGN LIBRARY'!J8 -> 0.40756997 | G9: =N(INDEX('05 MATERIAL RATE LIBRARY'!$E$5:$E$400,MATCH("MAT-SND-LWP",'05 MATERIAL RATE LIBRARY'!$A$5:$A$400,0))) -> 240 | H9: =W_Agg -> 0.05 | I9: =F9*(1+H9) -> 0.42794846 | J9: =I9*G9 -> 102.70763 | K9: =IF(INDEX('05 MATERIAL RATE LIBRARY'!$M$5:$M$400,MATCH("MAT-SND-LWP",'05 MATERIAL RATE LIBRARY'!$A$5:$A$400,0))=1,"",IF(INDEX('05 MATERIAL RATE LIBRARY'!$M$5:$M$400,MATCH("MAT-SND-LWP",'05 MATERIAL RATE LIBRARY'!$A$5:$A$400,0))=2,"OLD RATE","NO RATE"))
A10: CIV-CON-001 | B10: Material | C10: MAT-ADM-SP | D10: Sika-520BA / Vertex G-880 @1.2 L/100 kg | E10: kg | F10: ='15 MIX DESIGN LIBRARY'!J9 -> 0.2177545 | G10: =N(INDEX('05 MATERIAL RATE LIBRARY'!$E$5:$E$400,MATCH("MAT-ADM-SP",'05 MATERIAL RATE LIBRARY'!$A$5:$A$400,0))) -> 185 | H10: =W_Adm -> 0.02 | I10: =F10*(1+H10) -> 0.22210959 | J10: =I10*G10 -> 41.090273 | K10: =IF(INDEX('05 MATERIAL RATE LIBRARY'!$M$5:$M$400,MATCH("MAT-ADM-SP",'05 MATERIAL RATE LIBRARY'!$A$5:$A$400,0))=1,"",IF(INDEX('05 MATERIAL RATE LIBRARY'!$M$5:$M$400,MATCH("MAT-ADM-SP",'05 MATERIAL RATE LIBRARY'!$A$5:$A$400,0))=2,"OLD RATE","NO RATE")) -> OLD RATE
A11: CIV-CON-001 | B11: Material | C11: MAT-WTR | D11: Water | E11: litre | F11: ='15 MIX DESIGN LIBRARY'!J10 -> 5.2952003 | G11: =N(INDEX('05 MATERIAL RATE LIBRARY'!$E$5:$E$400,MATCH("MAT-WTR",'05 MATERIAL RATE LIBRARY'!$A$5:$A$400,0))) -> 0.686 | H11: =W_Wtr -> 0 | I11: =F11*(1+H11) -> 5.2952003 | J11: =I11*G11 -> 3.6325074 | K11: =IF(INDEX('05 MATERIAL RATE LIBRARY'!$M$5:$M$400,MATCH("MAT-WTR",'05 MATERIAL RATE LIBRARY'!$A$5:$A$400,0))=1,"",IF(INDEX('05 MATERIAL RATE LIBRARY'!$M$5:$M$400,MATCH("MAT-WTR",'05 MATERIAL RATE LIBRARY'!$A$5:$A$400,0))=2,"OLD RATE","NO RATE"))
A12: CIV-CON-001 | B12: Labour | C12: LAB-MSN | D12: Mason – PR-RCC crew | E12: day | F12: ='13 PRODUCTIVITY LIBRARY'!E5/'13 PRODUCTIVITY LIBRARY'!D5 -> 0.01 | G12: =N(INDEX('06 LABOUR RATE LIBRARY'!$D$5:$D$100,MATCH("LAB-MSN",'06 LABOUR RATE LIBRARY'!$A$5:$A$100,0))) -> 2200 | H12: 0 | I12: =F12*(1+H12) -> 0.01 | J12: =I12*G12 -> 22 | K12: =IF(INDEX('06 LABOUR RATE LIBRARY'!$L$5:$L$100,MATCH("LAB-MSN",'06 LABOUR RATE LIBRARY'!$A$5:$A$100,0))=1,"",IF(INDEX('06 LABOUR RATE LIBRARY'!$L$5:$L$100,MATCH("LAB-MSN",'06 LABOUR RATE LIBRARY'!$A$5:$A$100,0))=2,"OLD RATE","NO RATE"))
A13: CIV-CON-001 | B13: Labour | C13: LAB-HLP | D13: Helpers – PR-RCC crew | E13: day | F13: ='13 PRODUCTIVITY LIBRARY'!F5/'13 PRODUCTIVITY LIBRARY'!D5 -> 0.08 | G13: =N(INDEX('06 LABOUR RATE LIBRARY'!$D$5:$D$100,MATCH("LAB-HLP",'06 LABOUR RATE LIBRARY'!$A$5:$A$100,0))) -> 1538 | H13: 0 | I13: =F13*(1+H13) -> 0.08 | J13: =I13*G13 -> 123.04 | K13: =IF(INDEX('06 LABOUR RATE LIBRARY'!$L$5:$L$100,MATCH("LAB-HLP",'06 LABOUR RATE LIBRARY'!$A$5:$A$100,0))=1,"",IF(INDEX('06 LABOUR RATE LIBRARY'!$L$5:$L$100,MATCH("LAB-HLP",'06 LABOUR RATE LIBRARY'!$A$5:$A$100,0))=2,"OLD RATE","NO RATE"))
A14: CIV-CON-001 | B14: Equipment | C14: EQ-VIB | D14: Needle vibrator (1 per crew-day) | E14: day | F14: =1/'13 PRODUCTIVITY LIBRARY'!D5 -> 0.01 | G14: =N(INDEX('07 EQUIPMENT RATE LIBRARY'!$D$5:$D$100,MATCH("EQ-VIB",'07 EQUIPMENT RATE LIBRARY'!$A$5:$A$100,0))) -> 227 | H14: 0 | I14: =F14*(1+H14) -> 0.01 | J14: =I14*G14 -> 2.27 | K14: =IF(INDEX('07 EQUIPMENT RATE LIBRARY'!$H$5:$H$100,MATCH("EQ-VIB",'07 EQUIPMENT RATE LIBRARY'!$A$5:$A$100,0))=1,"",IF(INDEX('07 EQUIPMENT RATE LIBRARY'!$H$5:$H$100,MATCH("EQ-VIB",'07 EQUIPMENT RATE LIBRARY'!$A$5:$A$100,0))=2,"OLD RATE","NO RATE"))
A15: CIV-CON-001 | B15: Equipment | C15: EQ-MIX | D15: Concrete mixer (site-batched; for plant supply use RMC items CIV-CON-020..023) | E15: day | F15: =1/'13 PRODUCTIVITY LIBRARY'!D5 -> 0.01 | G15: =N(INDEX('07 EQUIPMENT RATE LIBRARY'!$D$5:$D$100,MATCH("EQ-MIX",'07 EQUIPMENT RATE LIBRARY'!$A$5:$A$100,0))) -> 3500 | H15: 0 | I15: =F15*(1+H15) -> 0.01 | J15: =I15*G15 -> 35 | K15: =IF(INDEX('07 EQUIPMENT RATE LIBRARY'!$H$5:$H$100,MATCH("EQ-MIX",'07 EQUIPMENT RATE LIBRARY'!$A$5:$A$100,0))=1,"",IF(INDEX('07 EQUIPMENT RATE LIBRARY'!$H$5:$H$100,MATCH("EQ-MIX",'07 EQUIPMENT RATE LIBRARY'!$A$5:$A$100,0))=2,"OLD RATE","NO RATE"))
A16: CIV-CON-001 | B16: Equipment | C16: EQ-PUMP | D16: Concrete pump – ground-floor base (set 0 if chute/manual) | E16: cft | F16: 1 | G16: =N(INDEX('07 EQUIPMENT RATE LIBRARY'!$D$5:$D$100,MATCH("EQ-PUMP",'07 EQUIPMENT RATE LIBRARY'!$A$5:$A$100,0))) -> 28.32 | H16: 0 | I16: =F16*(1+H16) -> 1 | J16: =I16*G16 -> 28.32 | K16: =IF(INDEX('07 EQUIPMENT RATE LIBRARY'!$H$5:$H$100,MATCH("EQ-PUMP",'07 EQUIPMENT RATE LIBRARY'!$A$5:$A$100,0))=1,"",IF(INDEX('07 EQUIPMENT RATE LIBRARY'!$H$5:$H$100,MATCH("EQ-PUMP",'07 EQUIPMENT RATE LIBRARY'!$A$5:$A$100,0))=2,"OLD RATE","NO RATE"))
D17: Material – net (excl. wastage) | J17: =SUMPRODUCT((B6:B16="Material")*F6:F16*G6:G16) -> 761.31063
D18: Material – wastage | J18: =SUMIF(B6:B16,"Material",J6:J16)-J17 -> 21.957827
D19: Material total | J19: =SUMIF(B6:B16,"Material",J6:J16) -> 783.26846
D20: Labour total | J20: =SUMIF(B6:B16,"Labour",J6:J16) -> 145.04
D21: Equipment total | J21: =SUMIF(B6:B16,"Equipment",J6:J16) -> 65.59
D22: Transport / handling total | J22: =SUMIF(B6:B16,"Transport",J6:J16) -> 0
D23: DIRECT COST | J23: =J19+J20+J21+J22 -> 993.89846
D24: Site overheads @ OH_Site | J24: =J23*OH_Site -> 29.816954
D25: Head-office overheads @ OH_HO | J25: =J23*OH_HO -> 49.694923
D26: Profit @ Profit | J26: =J23*Profit -> 99.389846
D27: Rate excl. tax | J27: =J23+J24+J25+J26 -> 1172.8002
D28: Sales tax (only if Tax_On = Yes) | J28: =IF(Tax_On="Yes",J27*N(Tax_Rate),0) -> 0
D29: FINAL RATE per cft (rounded) | J29: =ROUND(J27+J28,0) -> 1173
D30: Blank / old (red) inputs in this analysis | J30: =COUNTIF(K6:K16,"NO RATE")+COUNTIF(K6:K16,"OLD RATE") -> 1
A32: CIV-CON-002 | B32: Providing and laying 1000 PSI concrete (Lab – 1000 PSI (lean); mix per Image 2 – lab mix sheet) in sub-structure/PCC, including batching, placing, compacting and curing, complete in all respects; excluding reinforcement and formwork measured separately. | J32: Unit: cft
A33: Item Code | B33: Component | C33: Resource Code | D33: Description | E33: Unit | F33: Consumption / unit | G33: Base Rate PKR | H33: Wastage % | I33: Adjusted Qty | J33: Amount PKR | K33: Input flag
A34: CIV-CON-002 | B34: Material | C34: MAT-CEM-OPC | D34: OPC | E34: bag | F34: ='15 MIX DESIGN LIBRARY'!J13 -> 0.11326632 | G34: =N(INDEX('05 MATERIAL RATE LIBRARY'!$E$5:$E$400,MATCH("MAT-CEM-OPC",'05 MATERIAL RATE LIBRARY'!$A$5:$A$400,0))) -> 1575 | H34: =W_Cem -> 0.02 | I34: =F34*(1+H34) -> 0.11553164 | J34: =I34*G34 -> 181.96234 | K34: =IF(INDEX('05 MATERIAL RATE LIBRARY'!$M$5:$M$400,MATCH("MAT-CEM-OPC",'05 MATERIAL RATE LIBRARY'!$A$5:$A$400,0))=1,"",IF(INDEX('05 MATERIAL RATE LIBRARY'!$M$5:$M$400,MATCH("MAT-CEM-OPC",'05 MATERIAL RATE LIBRARY'!$A$5:$A$400,0))=2,"OLD RATE","NO RATE"))
A35: CIV-CON-002 | B35: Material | C35: MAT-CRS-MGL | D35: 3/4" (lab: 20) crushed Margalla | E35: cft | F35: ='15 MIX DESIGN LIBRARY'!J14 -> 0.4330771 | G35: =N(INDEX('05 MATERIAL RATE LIBRARY'!$E$5:$E$400,MATCH("MAT-CRS-MGL",'05 MATERIAL RATE LIBRARY'!$A$5:$A$400,0))) -> 180 | H35: =W_Agg -> 0.05 | I35: =F35*(1+H35) -> 0.45473095 | J35: =I35*G35 -> 81.851571 | K35: =IF(INDEX('05 MATERIAL RATE LIBRARY'!$M$5:$M$400,MATCH("MAT-CRS-MGL",'05 MATERIAL RATE LIBRARY'!$A$5:$A$400,0))=1,"",IF(INDEX('05 MATERIAL RATE LIBRARY'!$M$5:$M$400,MATCH("MAT-CRS-MGL",'05 MATERIAL RATE LIBRARY'!$A$5:$A$400,0))=2,"OLD RATE","NO RATE"))
A36: CIV-CON-002 | B36: Material | C36: MAT-CRS-MGL | D36: 3/8" (lab: 10) crushed Margalla | E36: cft | F36: ='15 MIX DESIGN LIBRARY'!J15 -> 0.27983443 | G36: =N(INDEX('05 MATERIAL RATE LIBRARY'!$E$5:$E$400,MATCH("MAT-CRS-MGL",'05 MATERIAL RATE LIBRARY'!$A$5:$A$400,0))) -> 180 | H36: =W_Agg -> 0.05 | I36: =F36*(1+H36) -> 0.29382615 | J36: =I36*G36 -> 52.888708 | K36: =IF(INDEX('05 MATERIAL RATE LIBRARY'!$M$5:$M$400,MATCH("MAT-CRS-MGL",'05 MATERIAL RATE LIBRARY'!$A$5:$A$400,0))=1,"",IF(INDEX('05 MATERIAL RATE LIBRARY'!$M$5:$M$400,MATCH("MAT-CRS-MGL",'05 MATERIAL RATE LIBRARY'!$A$5:$A$400,0))=2,"OLD RATE","NO RATE"))
A37: CIV-CON-002 | B37: Material | C37: MAT-SND-LWP | D37: Sand Lawrencepur | E37: cft | F37: ='15 MIX DESIGN LIBRARY'!J16 -> 0.53486872 | G37: =N(INDEX('05 MATERIAL RATE LIBRARY'!$E$5:$E$400,MATCH("MAT-SND-LWP",'05 MATERIAL RATE LIBRARY'!$A$5:$A$400,0))) -> 240 | H37: =W_Agg -> 0.05 | I37: =F37*(1+H37) -> 0.56161216 | J37: =I37*G37 -> 134.78692 | K37: =IF(INDEX('05 MATERIAL RATE LIBRARY'!$M$5:$M$400,MATCH("MAT-SND-LWP",'05 MATERIAL RATE LIBRARY'!$A$5:$A$400,0))=1,"",IF(INDEX('05 MATERIAL RATE LIBRARY'!$M$5:$M$400,MATCH("MAT-SND-LWP",'05 MATERIAL RATE LIBRARY'!$A$5:$A$400,0))=2,"OLD RATE","NO RATE"))
A38: CIV-CON-002 | B38: Material | C38: MAT-WTR | D38: Free water | E38: litre | F38: ='15 MIX DESIGN LIBRARY'!J17 -> 5.9464817 | G38: =N(INDEX('05 MATERIAL RATE LIBRARY'!$E$5:$E$400,MATCH("MAT-WTR",'05 MATERIAL RATE LIBRARY'!$A$5:$A$400,0))) -> 0.686 | H38: =W_Wtr -> 0 | I38: =F38*(1+H38) -> 5.9464817 | J38: =I38*G38 -> 4.0792864 | K38: =IF(INDEX('05 MATERIAL RATE LIBRARY'!$M$5:$M$400,MATCH("MAT-WTR",'05 MATERIAL RATE LIBRARY'!$A$5:$A$400,0))=1,"",IF(INDEX('05 MATERIAL RATE LIBRARY'!$M$5:$M$400,MATCH("MAT-WTR",'05 MATERIAL RATE LIBRARY'!$A$5:$A$400,0))=2,"OLD RATE","NO RATE"))
A39: CIV-CON-002 | B39: Labour | C39: LAB-MSN | D39: Mason – PR-PCC crew | E39: day | F39: ='13 PRODUCTIVITY LIBRARY'!E6/'13 PRODUCTIVITY LIBRARY'!D6 -> 0.0125 | G39: =N(INDEX('06 LABOUR RATE LIBRARY'!$D$5:$D$100,MATCH("LAB-MSN",'06 LABOUR RATE LIBRARY'!$A$5:$A$100,0))) -> 2200 | H39: 0 | I39: =F39*(1+H39) -> 0.0125 | J39: =I39*G39 -> 27.5 | K39: =IF(INDEX('06 LABOUR RATE LIBRARY'!$L$5:$L$100,MATCH("LAB-MSN",'06 LABOUR RATE LIBRARY'!$A$5:$A$100,0))=1,"",IF(INDEX('06 LABOUR RATE LIBRARY'!$L$5:$L$100,MATCH("LAB-MSN",'06 LABOUR RATE LIBRARY'!$A$5:$A$100,0))=2,"OLD RATE","NO RATE"))
A40: CIV-CON-002 | B40: Labour | C40: LAB-HLP | D40: Helpers – PR-PCC crew | E40: day | F40: ='13 PRODUCTIVITY LIBRARY'!F6/'13 PRODUCTIVITY LIBRARY'!D6 -> 0.075 | G40: =N(INDEX('06 LABOUR RATE LIBRARY'!$D$5:$D$100,MATCH("LAB-HLP",'06 LABOUR RATE LIBRARY'!$A$5:$A$100,0))) -> 1538 | H40: 0 | I40: =F40*(1+H40) -> 0.075 | J40: =I40*G40 -> 115.35 | K40: =IF(INDEX('06 LABOUR RATE LIBRARY'!$L$5:$L$100,MATCH("LAB-HLP",'06 LABOUR RATE LIBRARY'!$A$5:$A$100,0))=1,"",IF(INDEX('06 LABOUR RATE LIBRARY'!$L$5:$L$100,MATCH("LAB-HLP",'06 LABOUR RATE LIBRARY'!$A$5:$A$100,0))=2,"OLD RATE","NO RATE"))
A41: CIV-CON-002 | B41: Equipment | C41: EQ-VIB | D41: Needle vibrator (1 per crew-day) | E41: day | F41: =1/'13 PRODUCTIVITY LIBRARY'!D6 -> 0.0125 | G41: =N(INDEX('07 EQUIPMENT RATE LIBRARY'!$D$5:$D$100,MATCH("EQ-VIB",'07 EQUIPMENT RATE LIBRARY'!$A$5:$A$100,0))) -> 227 | H41: 0 | I41: =F41*(1+H41) -> 0.0125 | J41: =I41*G41 -> 2.8375 | K41: =IF(INDEX('07 EQUIPMENT RATE LIBRARY'!$H$5:$H$100,MATCH("EQ-VIB",'07 EQUIPMENT RATE LIBRARY'!$A$5:$A$100,0))=1,"",IF(INDEX('07 EQUIPMENT RATE LIBRARY'!$H$5:$H$100,MATCH("EQ-VIB",'07 EQUIPMENT RATE LIBRARY'!$A$5:$A$100,0))=2,"OLD RATE","NO RATE"))
A42: CIV-CON-002 | B42: Equipment | C42: EQ-MIX | D42: Concrete mixer (site-batched; for plant supply use RMC items CIV-CON-020..023) | E42: day | F42: =1/'13 PRODUCTIVITY LIBRARY'!D6 -> 0.0125 | G42: =N(INDEX('07 EQUIPMENT RATE LIBRARY'!$D$5:$D$100,MATCH("EQ-MIX",'07 EQUIPMENT RATE LIBRARY'!$A$5:$A$100,0))) -> 3500 | H42: 0 | I42: =F42*(1+H42) -> 0.0125 | J42: =I42*G42 -> 43.75 | K42: =IF(INDEX('07 EQUIPMENT RATE LIBRARY'!$H$5:$H$100,MATCH("EQ-MIX",'07 EQUIPMENT RATE LIBRARY'!$A$5:$A$100,0))=1,"",IF(INDEX('07 EQUIPMENT RATE LIBRARY'!$H$5:$H$100,MATCH("EQ-MIX",'07 EQUIPMENT RATE LIBRARY'!$A$5:$A$100,0))=2,"OLD RATE","NO RATE"))
A43: CIV-CON-002 | B43: Equipment | C43: EQ-PUMP | D43: Concrete pump – ground-floor base (set 0 if chute/manual) | E43: cft | F43: 1 | G43: =N(INDEX('07 EQUIPMENT RATE LIBRARY'!$D$5:$D$100,MATCH("EQ-PUMP",'07 EQUIPMENT RATE LIBRARY'!$A$5:$A$100,0))) -> 28.32 | H43: 0 | I43: =F43*(1+H43) -> 1 | J43: =I43*G43 -> 28.32 | K43: =IF(INDEX('07 EQUIPMENT RATE LIBRARY'!$H$5:$H$100,MATCH("EQ-PUMP",'07 EQUIPMENT RATE LIBRARY'!$A$5:$A$100,0))=1,"",IF(INDEX('07 EQUIPMENT RATE LIBRARY'!$H$5:$H$100,MATCH("EQ-PUMP",'07 EQUIPMENT RATE LIBRARY'!$A$5:$A$100,0))=2,"OLD RATE","NO RATE"))
D44: Material – net (excl. wastage) | J44: =SUMPRODUCT((B34:B43="Material")*F34:F43*G34:G43) -> 439.1663
D45: Material – wastage | J45: =SUMIF(B34:B43,"Material",J34:J43)-J44 -> 16.402517
D46: Material total | J46: =SUMIF(B34:B43,"Material",J34:J43) -> 455.56882
D47: Labour total | J47: =SUMIF(B34:B43,"Labour",J34:J43) -> 142.85
D48: Equipment total | J48: =SUMIF(B34:B43,"Equipment",J34:J43) -> 74.9075
D49: Transport / handling total | J49: =SUMIF(B34:B43,"Transport",J34:J43) -> 0
D50: DIRECT COST | J50: =J46+J47+J48+J49 -> 673.32632
D51: Site overheads @ OH_Site | J51: =J50*OH_Site -> 20.19979
D52: Head-office overheads @ OH_HO | J52: =J50*OH_HO -> 33.666316
D53: Profit @ Profit | J53: =J50*Profit -> 67.332632
D54: Rate excl. tax | J54: =J50+J51+J52+J53 -> 794.52506
D55: Sales tax (only if Tax_On = Yes) | J55: =IF(Tax_On="Yes",J54*N(Tax_Rate),0) -> 0
D56: FINAL RATE per cft (rounded) | J56: =ROUND(J54+J55,0) -> 795
D57: Blank / old (red) inputs in this analysis | J57: =COUNTIF(K34:K43,"NO RATE")+COUNTIF(K34:K43,"OLD RATE") -> 0
A59: CIV-CON-003 | B59: Providing and laying 6000 PSI concrete (Lab – 6000 PSI (DHA Multan sheet); mix per Image 3 – lab mix sheet) in structural members, including batching, placing, compacting and curing, complete in all respects; excluding reinforcement and formwork measured separately. | J59: Unit: cft
A60: Item Code | B60: Component | C60: Resource Code | D60: Description | E60: Unit | F60: Consumption / unit | G60: Base Rate PKR | H60: Wastage % | I60: Adjusted Qty | J60: Amount PKR | K60: Input flag
A61: CIV-CON-003 | B61: Material | C61: MAT-CEM-OPC | D61: OPC | E61: bag | F61: ='15 MIX DESIGN LIBRARY'!J20 -> 0.31148237 | G61: =N(INDEX('05 MATERIAL RATE LIBRARY'!$E$5:$E$400,MATCH("MAT-CEM-OPC",'05 MATERIAL RATE LIBRARY'!$A$5:$A$400,0))) -> 1575 | H61: =W_Cem -> 0.02 | I61: =F61*(1+H61) -> 0.31771202 | J61: =I61*G61 -> 500.39643 | K61: =IF(INDEX('05 MATERIAL RATE LIBRARY'!$M$5:$M$400,MATCH("MAT-CEM-OPC",'05 MATERIAL RATE LIBRARY'!$A$5:$A$400,0))=1,"",IF(INDEX('05 MATERIAL RATE LIBRARY'!$M$5:$M$400,MATCH("MAT-CEM-OPC",'05 MATERIAL RATE LIBRARY'!$A$5:$A$400,0))=2,"OLD RATE","NO RATE"))
A62: CIV-CON-003 | B62: Material | C62: MAT-CRS-MGL | D62: 3/4" (lab: 20) crushed Margalla | E62: cft | F62: ='15 MIX DESIGN LIBRARY'!J21 -> 0.4184191 | G62: =N(INDEX('05 MATERIAL RATE LIBRARY'!$E$5:$E$400,MATCH("MAT-CRS-MGL",'05 MATERIAL RATE LIBRARY'!$A$5:$A$400,0))) -> 180 | H62: =W_Agg -> 0.05 | I62: =F62*(1+H62) -> 0.43934006 | J62: =I62*G62 -> 79.08121 | K62: =IF(INDEX('05 MATERIAL RATE LIBRARY'!$M$5:$M$400,MATCH("MAT-CRS-MGL",'05 MATERIAL RATE LIBRARY'!$A$5:$A$400,0))=1,"",IF(INDEX('05 MATERIAL RATE LIBRARY'!$M$5:$M$400,MATCH("MAT-CRS-MGL",'05 MATERIAL RATE LIBRARY'!$A$5:$A$400,0))=2,"OLD RATE","NO RATE"))
A63: CIV-CON-003 | B63: Material | C63: MAT-CRS-MGL | D63: 3/8" (lab: 10) crushed Margalla | E63: cft | F63: ='15 MIX DESIGN LIBRARY'!J22 -> 0.27716934 | G63: =N(INDEX('05 MATERIAL RATE LIBRARY'!$E$5:$E$400,MATCH("MAT-CRS-MGL",'05 MATERIAL RATE LIBRARY'!$A$5:$A$400,0))) -> 180 | H63: =W_Agg -> 0.05 | I63: =F63*(1+H63) -> 0.29102781 | J63: =I63*G63 -> 52.385006 | K63: =IF(INDEX('05 MATERIAL RATE LIBRARY'!$M$5:$M$400,MATCH("MAT-CRS-MGL",'05 MATERIAL RATE LIBRARY'!$A$5:$A$400,0))=1,"",IF(INDEX('05 MATERIAL RATE LIBRARY'!$M$5:$M$400,MATCH("MAT-CRS-MGL",'05 MATERIAL RATE LIBRARY'!$A$5:$A$400,0))=2,"OLD RATE","NO RATE"))
A64: CIV-CON-003 | B64: Material | C64: MAT-SND-LWP | D64: Sand Lawrencepur | E64: cft | F64: ='15 MIX DESIGN LIBRARY'!J23 -> 0.37126182 | G64: =N(INDEX('05 MATERIAL RATE LIBRARY'!$E$5:$E$400,MATCH("MAT-SND-LWP",'05 MATERIAL RATE LIBRARY'!$A$5:$A$400,0))) -> 240 | H64: =W_Agg -> 0.05 | I64: =F64*(1+H64) -> 0.38982491 | J64: =I64*G64 -> 93.557978 | K64: =IF(INDEX('05 MATERIAL RATE LIBRARY'!$M$5:$M$400,MATCH("MAT-SND-LWP",'05 MATERIAL RATE LIBRARY'!$A$5:$A$400,0))=1,"",IF(INDEX('05 MATERIAL RATE LIBRARY'!$M$5:$M$400,MATCH("MAT-SND-LWP",'05 MATERIAL RATE LIBRARY'!$A$5:$A$400,0))=2,"OLD RATE","NO RATE"))
A65: CIV-CON-003 | B65: Material | C65: MAT-ADM-SP | D65: Admixture-2 (product not named) | E65: kg | F65: ='15 MIX DESIGN LIBRARY'!J24 -> 0.1415829 | G65: =N(INDEX('05 MATERIAL RATE LIBRARY'!$E$5:$E$400,MATCH("MAT-ADM-SP",'05 MATERIAL RATE LIBRARY'!$A$5:$A$400,0))) -> 185 | H65: =W_Adm -> 0.02 | I65: =F65*(1+H65) -> 0.14441455 | J65: =I65*G65 -> 26.716693 | K65: =IF(INDEX('05 MATERIAL RATE LIBRARY'!$M$5:$M$400,MATCH("MAT-ADM-SP",'05 MATERIAL RATE LIBRARY'!$A$5:$A$400,0))=1,"",IF(INDEX('05 MATERIAL RATE LIBRARY'!$M$5:$M$400,MATCH("MAT-ADM-SP",'05 MATERIAL RATE LIBRARY'!$A$5:$A$400,0))=2,"OLD RATE","NO RATE")) -> OLD RATE
A66: CIV-CON-003 | B66: Material | C66: MAT-WTR | D66: Free water | E66: litre | F66: ='15 MIX DESIGN LIBRARY'!J25 -> 6.0031148 | G66: =N(INDEX('05 MATERIAL RATE LIBRARY'!$E$5:$E$400,MATCH("MAT-WTR",'05 MATERIAL RATE LIBRARY'!$A$5:$A$400,0))) -> 0.686 | H66: =W_Wtr -> 0 | I66: =F66*(1+H66) -> 6.0031148 | J66: =I66*G66 -> 4.1181368 | K66: =IF(INDEX('05 MATERIAL RATE LIBRARY'!$M$5:$M$400,MATCH("MAT-WTR",'05 MATERIAL RATE LIBRARY'!$A$5:$A$400,0))=1,"",IF(INDEX('05 MATERIAL RATE LIBRARY'!$M$5:$M$400,MATCH("MAT-WTR",'05 MATERIAL RATE LIBRARY'!$A$5:$A$400,0))=2,"OLD RATE","NO RATE"))
A67: CIV-CON-003 | B67: Labour | C67: LAB-MSN | D67: Mason – PR-RCC crew | E67: day | F67: ='13 PRODUCTIVITY LIBRARY'!E5/'13 PRODUCTIVITY LIBRARY'!D5 -> 0.01 | G67: =N(INDEX('06 LABOUR RATE LIBRARY'!$D$5:$D$100,MATCH("LAB-MSN",'06 LABOUR RATE LIBRARY'!$A$5:$A$100,0))) -> 2200 | H67: 0 | I67: =F67*(1+H67) -> 0.01 | J67: =I67*G67 -> 22 | K67: =IF(INDEX('06 LABOUR RATE LIBRARY'!$L$5:$L$100,MATCH("LAB-MSN",'06 LABOUR RATE LIBRARY'!$A$5:$A$100,0))=1,"",IF(INDEX('06 LABOUR RATE LIBRARY'!$L$5:$L$100,MATCH("LAB-MSN",'06 LABOUR RATE LIBRARY'!$A$5:$A$100,0))=2,"OLD RATE","NO RATE"))
A68: CIV-CON-003 | B68: Labour | C68: LAB-HLP | D68: Helpers – PR-RCC crew | E68: day | F68: ='13 PRODUCTIVITY LIBRARY'!F5/'13 PRODUCTIVITY LIBRARY'!D5 -> 0.08 | G68: =N(INDEX('06 LABOUR RATE LIBRARY'!$D$5:$D$100,MATCH("LAB-HLP",'06 LABOUR RATE LIBRARY'!$A$5:$A$100,0))) -> 1538 | H68: 0 | I68: =F68*(1+H68) -> 0.08 | J68: =I68*G68 -> 123.04 | K68: =IF(INDEX('06 LABOUR RATE LIBRARY'!$L$5:$L$100,MATCH("LAB-HLP",'06 LABOUR RATE LIBRARY'!$A$5:$A$100,0))=1,"",IF(INDEX('06 LABOUR RATE LIBRARY'!$L$5:$L$100,MATCH("LAB-HLP",'06 LABOUR RATE LIBRARY'!$A$5:$A$100,0))=2,"OLD RATE","NO RATE"))
A69: CIV-CON-003 | B69: Equipment | C69: EQ-VIB | D69: Needle vibrator (1 per crew-day) | E69: day | F69: =1/'13 PRODUCTIVITY LIBRARY'!D5 -> 0.01 | G69: =N(INDEX('07 EQUIPMENT RATE LIBRARY'!$D$5:$D$100,MATCH("EQ-VIB",'07 EQUIPMENT RATE LIBRARY'!$A$5:$A$100,0))) -> 227 | H69: 0 | I69: =F69*(1+H69) -> 0.01 | J69: =I69*G69 -> 2.27 | K69: =IF(INDEX('07 EQUIPMENT RATE LIBRARY'!$H$5:$H$100,MATCH("EQ-VIB",'07 EQUIPMENT RATE LIBRARY'!$A$5:$A$100,0))=1,"",IF(INDEX('07 EQUIPMENT RATE LIBRARY'!$H$5:$H$100,MATCH("EQ-VIB",'07 EQUIPMENT RATE LIBRARY'!$A$5:$A$100,0))=2,"OLD RATE","NO RATE"))
A70: CIV-CON-003 | B70: Equipment | C70: EQ-MIX | D70: Concrete mixer (site-batched; for plant supply use RMC items CIV-CON-020..023) | E70: day | F70: =1/'13 PRODUCTIVITY LIBRARY'!D5 -> 0.01 | G70: =N(INDEX('07 EQUIPMENT RATE LIBRARY'!$D$5:$D$100,MATCH("EQ-MIX",'07 EQUIPMENT RATE LIBRARY'!$A$5:$A$100,0))) -> 3500 | H70: 0 | I70: =F70*(1+H70) -> 0.01 | J70: =I70*G70 -> 35 | K70: =IF(INDEX('07 EQUIPMENT RATE LIBRARY'!$H$5:$H$100,MATCH("EQ-MIX",'07 EQUIPMENT RATE LIBRARY'!$A$5:$A$100,0))=1,"",IF(INDEX('07 EQUIPMENT RATE LIBRARY'!$H$5:$H$100,MATCH("EQ-MIX",'07 EQUIPMENT RATE LIBRARY'!$A$5:$A$100,0))=2,"OLD RATE","NO RATE"))
A71: CIV-CON-003 | B71: Equipment | C71: EQ-PUMP | D71: Concrete pump – ground-floor base (set 0 if chute/manual) | E71: cft | F71: 1 | G71: =N(INDEX('07 EQUIPMENT RATE LIBRARY'!$D$5:$D$100,MATCH("EQ-PUMP",'07 EQUIPMENT RATE LIBRARY'!$A$5:$A$100,0))) -> 28.32 | H71: 0 | I71: =F71*(1+H71) -> 1 | J71: =I71*G71 -> 28.32 | K71: =IF(INDEX('07 EQUIPMENT RATE LIBRARY'!$H$5:$H$100,MATCH("EQ-PUMP",'07 EQUIPMENT RATE LIBRARY'!$A$5:$A$100,0))=1,"",IF(INDEX('07 EQUIPMENT RATE LIBRARY'!$H$5:$H$100,MATCH("EQ-PUMP",'07 EQUIPMENT RATE LIBRARY'!$A$5:$A$100,0))=2,"OLD RATE","NO RATE"))
D72: Material – net (excl. wastage) | J72: =SUMPRODUCT((B61:B71="Material")*F61:F71*G61:G71) -> 735.20447
D73: Material – wastage | J73: =SUMIF(B61:B71,"Material",J61:J71)-J72 -> 21.050989
D74: Material total | J74: =SUMIF(B61:B71,"Material",J61:J71) -> 756.25546
D75: Labour total | J75: =SUMIF(B61:B71,"Labour",J61:J71) -> 145.04
D76: Equipment total | J76: =SUMIF(B61:B71,"Equipment",J61:J71) -> 65.59
D77: Transport / handling total | J77: =SUMIF(B61:B71,"Transport",J61:J71) -> 0
D78: DIRECT COST | J78: =J74+J75+J76+J77 -> 966.88546
D79: Site overheads @ OH_Site | J79: =J78*OH_Site -> 29.006564
D80: Head-office overheads @ OH_HO | J80: =J78*OH_HO -> 48.344273
D81: Profit @ Profit | J81: =J78*Profit -> 96.688546
D82: Rate excl. tax | J82: =J78+J79+J80+J81 -> 1140.9248
D83: Sales tax (only if Tax_On = Yes) | J83: =IF(Tax_On="Yes",J82*N(Tax_Rate),0) -> 0
D84: FINAL RATE per cft (rounded) | J84: =ROUND(J82+J83,0) -> 1141
D85: Blank / old (red) inputs in this analysis | J85: =COUNTIF(K61:K71,"NO RATE")+COUNTIF(K61:K71,"OLD RATE") -> 1
A87: CIV-CON-004 | B87: Providing and laying 1:3:6 concrete (Lab – 1:3:6 ratio (PCC); mix per Image 5 – lab mix sheet) in sub-structure/PCC, including batching, placing, compacting and curing, complete in all respects; excluding reinforcement and formwork measured separately. | J87: Unit: cft
A88: Item Code | B88: Component | C88: Resource Code | D88: Description | E88: Unit | F88: Consumption / unit | G88: Base Rate PKR | H88: Wastage % | I88: Adjusted Qty | J88: Amount PKR | K88: Input flag
A89: CIV-CON-004 | B89: Material | C89: MAT-CEM-OPC | D89: OPC | E89: bag | F89: ='15 MIX DESIGN LIBRARY'!J28 -> 0.1415829 | G89: =N(INDEX('05 MATERIAL RATE LIBRARY'!$E$5:$E$400,MATCH("MAT-CEM-OPC",'05 MATERIAL RATE LIBRARY'!$A$5:$A$400,0))) -> 1575 | H89: =W_Cem -> 0.02 | I89: =F89*(1+H89) -> 0.14441455 | J89: =I89*G89 -> 227.45292 | K89: =IF(INDEX('05 MATERIAL RATE LIBRARY'!$M$5:$M$400,MATCH("MAT-CEM-OPC",'05 MATERIAL RATE LIBRARY'!$A$5:$A$400,0))=1,"",IF(INDEX('05 MATERIAL RATE LIBRARY'!$M$5:$M$400,MATCH("MAT-CEM-OPC",'05 MATERIAL RATE LIBRARY'!$A$5:$A$400,0))=2,"OLD RATE","NO RATE"))
A90: CIV-CON-004 | B90: Material | C90: MAT-CRS-MGL | D90: 3/4" (lab: 20) crushed Margalla | E90: cft | F90: ='15 MIX DESIGN LIBRARY'!J29 -> 0.42774692 | G90: =N(INDEX('05 MATERIAL RATE LIBRARY'!$E$5:$E$400,MATCH("MAT-CRS-MGL",'05 MATERIAL RATE LIBRARY'!$A$5:$A$400,0))) -> 180 | H90: =W_Agg -> 0.05 | I90: =F90*(1+H90) -> 0.44913426 | J90: =I90*G90 -> 80.844167 | K90: =IF(INDEX('05 MATERIAL RATE LIBRARY'!$M$5:$M$400,MATCH("MAT-CRS-MGL",'05 MATERIAL RATE LIBRARY'!$A$5:$A$400,0))=1,"",IF(INDEX('05 MATERIAL RATE LIBRARY'!$M$5:$M$400,MATCH("MAT-CRS-MGL",'05 MATERIAL RATE LIBRARY'!$A$5:$A$400,0))=2,"OLD RATE","NO RATE"))
A91: CIV-CON-004 | B91: Material | C91: MAT-CRS-MGL | D91: 3/8" (lab: 10) crushed Margalla | E91: cft | F91: ='15 MIX DESIGN LIBRARY'!J30 -> 0.27983443 | G91: =N(INDEX('05 MATERIAL RATE LIBRARY'!$E$5:$E$400,MATCH("MAT-CRS-MGL",'05 MATERIAL RATE LIBRARY'!$A$5:$A$400,0))) -> 180 | H91: =W_Agg -> 0.05 | I91: =F91*(1+H91) -> 0.29382615 | J91: =I91*G91 -> 52.888708 | K91: =IF(INDEX('05 MATERIAL RATE LIBRARY'!$M$5:$M$400,MATCH("MAT-CRS-MGL",'05 MATERIAL RATE LIBRARY'!$A$5:$A$400,0))=1,"",IF(INDEX('05 MATERIAL RATE LIBRARY'!$M$5:$M$400,MATCH("MAT-CRS-MGL",'05 MATERIAL RATE LIBRARY'!$A$5:$A$400,0))=2,"OLD RATE","NO RATE"))
A92: CIV-CON-004 | B92: Material | C92: MAT-SND-ZDP | D92: Sand Zinda Pir | E92: cft | F92: ='15 MIX DESIGN LIBRARY'!J31 -> 0.50969843 | G92: =N(INDEX('05 MATERIAL RATE LIBRARY'!$E$5:$E$400,MATCH("MAT-SND-ZDP",'05 MATERIAL RATE LIBRARY'!$A$5:$A$400,0))) -> 70 | H92: =W_Agg -> 0.05 | I92: =F92*(1+H92) -> 0.53518335 | J92: =I92*G92 -> 37.462834 | K92: =IF(INDEX('05 MATERIAL RATE LIBRARY'!$M$5:$M$400,MATCH("MAT-SND-ZDP",'05 MATERIAL RATE LIBRARY'!$A$5:$A$400,0))=1,"",IF(INDEX('05 MATERIAL RATE LIBRARY'!$M$5:$M$400,MATCH("MAT-SND-ZDP",'05 MATERIAL RATE LIBRARY'!$A$5:$A$400,0))=2,"OLD RATE","NO RATE"))
A93: CIV-CON-004 | B93: Material | C93: MAT-WTR | D93: Free water | E93: litre | F93: ='15 MIX DESIGN LIBRARY'!J32 -> 6.0314314 | G93: =N(INDEX('05 MATERIAL RATE LIBRARY'!$E$5:$E$400,MATCH("MAT-WTR",'05 MATERIAL RATE LIBRARY'!$A$5:$A$400,0))) -> 0.686 | H93: =W_Wtr -> 0 | I93: =F93*(1+H93) -> 6.0314314 | J93: =I93*G93 -> 4.1375619 | K93: =IF(INDEX('05 MATERIAL RATE LIBRARY'!$M$5:$M$400,MATCH("MAT-WTR",'05 MATERIAL RATE LIBRARY'!$A$5:$A$400,0))=1,"",IF(INDEX('05 MATERIAL RATE LIBRARY'!$M$5:$M$400,MATCH("MAT-WTR",'05 MATERIAL RATE LIBRARY'!$A$5:$A$400,0))=2,"OLD RATE","NO RATE"))
A94: CIV-CON-004 | B94: Labour | C94: LAB-MSN | D94: Mason – PR-PCC crew | E94: day | F94: ='13 PRODUCTIVITY LIBRARY'!E6/'13 PRODUCTIVITY LIBRARY'!D6 -> 0.0125 | G94: =N(INDEX('06 LABOUR RATE LIBRARY'!$D$5:$D$100,MATCH("LAB-MSN",'06 LABOUR RATE LIBRARY'!$A$5:$A$100,0))) -> 2200 | H94: 0 | I94: =F94*(1+H94) -> 0.0125 | J94: =I94*G94 -> 27.5 | K94: =IF(INDEX('06 LABOUR RATE LIBRARY'!$L$5:$L$100,MATCH("LAB-MSN",'06 LABOUR RATE LIBRARY'!$A$5:$A$100,0))=1,"",IF(INDEX('06 LABOUR RATE LIBRARY'!$L$5:$L$100,MATCH("LAB-MSN",'06 LABOUR RATE LIBRARY'!$A$5:$A$100,0))=2,"OLD RATE","NO RATE"))
A95: CIV-CON-004 | B95: Labour | C95: LAB-HLP | D95: Helpers – PR-PCC crew | E95: day | F95: ='13 PRODUCTIVITY LIBRARY'!F6/'13 PRODUCTIVITY LIBRARY'!D6 -> 0.075 | G95: =N(INDEX('06 LABOUR RATE LIBRARY'!$D$5:$D$100,MATCH("LAB-HLP",'06 LABOUR RATE LIBRARY'!$A$5:$A$100,0))) -> 1538 | H95: 0 | I95: =F95*(1+H95) -> 0.075 | J95: =I95*G95 -> 115.35 | K95: =IF(INDEX('06 LABOUR RATE LIBRARY'!$L$5:$L$100,MATCH("LAB-HLP",'06 LABOUR RATE LIBRARY'!$A$5:$A$100,0))=1,"",IF(INDEX('06 LABOUR RATE LIBRARY'!$L$5:$L$100,MATCH("LAB-HLP",'06 LABOUR RATE LIBRARY'!$A$5:$A$100,0))=2,"OLD RATE","NO RATE"))
A96: CIV-CON-004 | B96: Equipment | C96: EQ-VIB | D96: Needle vibrator (1 per crew-day) | E96: day | F96: =1/'13 PRODUCTIVITY LIBRARY'!D6 -> 0.0125 | G96: =N(INDEX('07 EQUIPMENT RATE LIBRARY'!$D$5:$D$100,MATCH("EQ-VIB",'07 EQUIPMENT RATE LIBRARY'!$A$5:$A$100,0))) -> 227 | H96: 0 | I96: =F96*(1+H96) -> 0.0125 | J96: =I96*G96 -> 2.8375 | K96: =IF(INDEX('07 EQUIPMENT RATE LIBRARY'!$H$5:$H$100,MATCH("EQ-VIB",'07 EQUIPMENT RATE LIBRARY'!$A$5:$A$100,0))=1,"",IF(INDEX('07 EQUIPMENT RATE LIBRARY'!$H$5:$H$100,MATCH("EQ-VIB",'07 EQUIPMENT RATE LIBRARY'!$A$5:$A$100,0))=2,"OLD RATE","NO RATE"))
A97: CIV-CON-004 | B97: Equipment | C97: EQ-MIX | D97: Concrete mixer (site-batched; for plant supply use RMC items CIV-CON-020..023) | E97: day | F97: =1/'13 PRODUCTIVITY LIBRARY'!D6 -> 0.0125 | G97: =N(INDEX('07 EQUIPMENT RATE LIBRARY'!$D$5:$D$100,MATCH("EQ-MIX",'07 EQUIPMENT RATE LIBRARY'!$A$5:$A$100,0))) -> 3500 | H97: 0 | I97: =F97*(1+H97) -> 0.0125 | J97: =I97*G97 -> 43.75 | K97: =IF(INDEX('07 EQUIPMENT RATE LIBRARY'!$H$5:$H$100,MATCH("EQ-MIX",'07 EQUIPMENT RATE LIBRARY'!$A$5:$A$100,0))=1,"",IF(INDEX('07 EQUIPMENT RATE LIBRARY'!$H$5:$H$100,MATCH("EQ-MIX",'07 EQUIPMENT RATE LIBRARY'!$A$5:$A$100,0))=2,"OLD RATE","NO RATE"))
A98: CIV-CON-004 | B98: Equipment | C98: EQ-PUMP | D98: Concrete pump – ground-floor base (set 0 if chute/manual) | E98: cft | F98: 1 | G98: =N(INDEX('07 EQUIPMENT RATE LIBRARY'!$D$5:$D$100,MATCH("EQ-PUMP",'07 EQUIPMENT RATE LIBRARY'!$A$5:$A$100,0))) -> 28.32 | H98: 0 | I98: =F98*(1+H98) -> 1 | J98: =I98*G98 -> 28.32 | K98: =IF(INDEX('07 EQUIPMENT RATE LIBRARY'!$H$5:$H$100,MATCH("EQ-PUMP",'07 EQUIPMENT RATE LIBRARY'!$A$5:$A$100,0))=1,"",IF(INDEX('07 EQUIPMENT RATE LIBRARY'!$H$5:$H$100,MATCH("EQ-PUMP",'07 EQUIPMENT RATE LIBRARY'!$A$5:$A$100,0))=2,"OLD RATE","NO RATE"))
D99: Material – net (excl. wastage) | J99: =SUMPRODUCT((B89:B98="Material")*F89:F98*G89:G98) -> 390.17416
D100: Material – wastage | J100: =SUMIF(B89:B98,"Material",J89:J98)-J99 -> 12.612038
D101: Material total | J101: =SUMIF(B89:B98,"Material",J89:J98) -> 402.78619
D102: Labour total | J102: =SUMIF(B89:B98,"Labour",J89:J98) -> 142.85
D103: Equipment total | J103: =SUMIF(B89:B98,"Equipment",J89:J98) -> 74.9075
D104: Transport / handling total | J104: =SUMIF(B89:B98,"Transport",J89:J98) -> 0
...

Sheet 05 MATERIAL RATE LIBRARY
A1: 05 · MATERIAL RATE LIBRARY (city-driven)
A2: Base Rate (E) = rate for the City selected in 10 ASSUMPTIONS, pulled from 08. Lahore Rate (N) is the Lahore input (red items link to 16 RFQ).
A4: Material Code | B4: Description | C4: Specification | D4: Unit | E4: Base Rate PKR (selected city) | F4: Low (Lahore) | G4: High (Lahore) | H4: Location | I4: Rate Date | J4: Rate Status | K4: Source ID | L4: Basis / Note | M4: Has Rate (1 ok / 0 blank / 2 old) | N4: Lahore Rate PKR (input) | O4: Scope
A5: MAT-CEM-OPC | B5: Cement OPC | C5: OPC Grade 53, 50 kg bag, any approved brand (DG/Lucky/Maple Leaf/Fauji/Bestway) | D5: bag | E5: =IF(INDEX('08 LOCATION RATE LIBRARY'!$D$5:$N$5,MATCH(City,'08 LOCATION RATE LIBRARY'!$D$4:$N$4,0))="","",INDEX('08 LOCATION RATE LIBRARY'!$D$5:$N$5,MATCH(City,'08 LOCATION RATE LIBRARY'!$D$4:$N$4,0))) -> 1575 | F5: 1350 | G5: 1650 | H5: =City -> Lahore | I5: 2026-09-05 | J5: Market indication | K5: SRC-39 | L5: Rev07: 1,415 (Phoenix GRN RCP-266, 06-May-2026, >4 months) -> 1,575 Lahore market 05-Sep-2026 (band 1,520–1,605; web 04-Sep-2026 1,500–1,610). Same as dashboard CEM. | M5: =IF(NOT(ISNUMBER(E5)),0,IF(OR(J5="OLD SOURCE",J5="UNDATED SOURCE"),2,1)) -> 1 | N5: 1575 | O5: National list
A6: MAT-SND-LWP | B6: Sand – Lawrencepur | C6: Coarse sand, FM ~2.4–2.6, delivered Lahore | D6: cft | E6: =IF(INDEX('08 LOCATION RATE LIBRARY'!$D$6:$N$6,MATCH(City,'08 LOCATION RATE LIBRARY'!$D$4:$N$4,0))="","",INDEX('08 LOCATION RATE LIBRARY'!$D$6:$N$6,MATCH(City,'08 LOCATION RATE LIBRARY'!$D$4:$N$4,0))) -> 240 | F6: 180 | G6: 305 | H6: =City -> Lahore | I6: 2026-09-04 | J6: Market indication | K6: SRC-40 | L6: Rev07: 190 (SRC-03 national north band, Jul-2026) -> 240 Lahore market rate supplied by Sajjad 04-Sep-2026. Same as dashboard SAND-LP. | M6: =IF(NOT(ISNUMBER(E6)),0,IF(OR(J6="OLD SOURCE",J6="UNDATED SOURCE"),2,1)) -> 1 | N6: 240 | O6: City-specific
A7: MAT-SND-CHN | B7: Sand – Chenab | C7: A-grade, delivered Lahore | D7: cft | E7: =IF(INDEX('08 LOCATION RATE LIBRARY'!$D$7:$N$7,MATCH(City,'08 LOCATION RATE LIBRARY'!$D$4:$N$4,0))="","",INDEX('08 LOCATION RATE LIBRARY'!$D$7:$N$7,MATCH(City,'08 LOCATION RATE LIBRARY'!$D$4:$N$4,0))) -> 80 | F7: 60 | G7: 100 | H7: =City -> Lahore | I7: 2026-09-07 | J7: GRN verified | K7: SRC-30 | L7: Phoenix GRN RCP-316, 07-Sep-2026 – Mushtaq & Sons. | M7: =IF(NOT(ISNUMBER(E7)),0,IF(OR(J7="OLD SOURCE",J7="UNDATED SOURCE"),2,1)) -> 1 | N7: 80 | O7: City-specific
A8: MAT-SND-ZDP | B8: Sand – Zinda Pir | C8: As per mix design Image 5 (1:3:6) | D8: cft | E8: =IF(INDEX('08 LOCATION RATE LIBRARY'!$D$8:$N$8,MATCH(City,'08 LOCATION RATE LIBRARY'!$D$4:$N$4,0))="","",INDEX('08 LOCATION RATE LIBRARY'!$D$8:$N$8,MATCH(City,'08 LOCATION RATE LIBRARY'!$D$4:$N$4,0))) -> 70 | H8: =City -> Lahore | I8: 2026-09-27 | J8: =IF(ISNUMBER('16 VENDOR ENQUIRY (RFQ)'!H18),"Vendor quote","ASSUMED") -> ASSUMED | K8: SRC-49 | L8: ASSUMPTION — no dated source (2026-09-27, assumed on request): between Ravi 52 (Phoenix GRN RCP-310, 27-Aug-2026) and Chenab 80 (RCP-316, 07-Sep-2026). Replace with a quotation in 16 RFQ col H. | M8: =IF(NOT(ISNUMBER(E8)),0,IF(OR(J8="OLD SOURCE",J8="UNDATED SOURCE"),2,1)) -> 1 | N8: =IF(ISNUMBER('16 VENDOR ENQUIRY (RFQ)'!H18),'16 VENDOR ENQUIRY (RFQ)'!H18,70) -> 70 | O8: City-specific
A9: MAT-CRS-MGL | B9: Crush – Margalla (all fractions) | C9: Crushed stone, fraction as per mix (3/4", 1/2", 3/8", 1/4") | D9: cft | E9: =IF(INDEX('08 LOCATION RATE LIBRARY'!$D$9:$N$9,MATCH(City,'08 LOCATION RATE LIBRARY'!$D$4:$N$4,0))="","",INDEX('08 LOCATION RATE LIBRARY'!$D$9:$N$9,MATCH(City,'08 LOCATION RATE LIBRARY'!$D$4:$N$4,0))) -> 180 | F9: 130 | G9: 170 | H9: =City -> Lahore | I9: 2026-07-01 | J9: Market indication | K9: SRC-41 | L9: Rev07: 145 -> 180. Rev06 midpoint was below the 04-Sep-2026 Sargodha quote (185) although Margalla hauls further; 180 = dashboard CRSH-MG (web, Jul-2026). Get a delivered quote. | M9: =IF(NOT(ISNUMBER(E9)),0,IF(OR(J9="OLD SOURCE",J9="UNDATED SOURCE"),2,1)) -> 1 | N9: 180 | O9: City-specific
A10: MAT-CRS-SGD | B10: Crush – Sargodha (all fractions) | C10: Crushed stone 3/4"–1/2" & 1/2"–3/16" | D10: cft | E10: =IF(INDEX('08 LOCATION RATE LIBRARY'!$D$10:$N$10,MATCH(City,'08 LOCATION RATE LIBRARY'!$D$4:$N$4,0))="","",INDEX('08 LOCATION RATE LIBRARY'!$D$10:$N$10,MATCH(City,'08 LOCATION RATE LIBRARY'!$D$4:$N$4,0))) -> 185 | F10: 120 | G10: 135 | H10: =City -> Lahore | I10: 2026-09-04 | J10: Market indication | K10: SRC-40 | L10: Rev07: 190 (Quadrangle GRN RCP-2607, Jul-2025, >12 months) -> 185 Lahore market 04-Sep-2026. Same as dashboard CRSH-SG. | M10: =IF(NOT(ISNUMBER(E10)),0,IF(OR(J10="OLD SOURCE",J10="UNDATED SOURCE"),2,1)) -> 1 | N10: 185 | O10: City-specific
A11: MAT-ADM-SP | B11: Admixture – superplasticizer | C11: Sikament 512 PK / Sika 520 BA / Imperial 540M or equivalent (ASTM C494 Type G/F) | D11: kg | E11: =IF(INDEX('08 LOCATION RATE LIBRARY'!$D$11:$N$11,MATCH(City,'08 LOCATION RATE LIBRARY'!$D$4:$N$4,0))="","",INDEX('08 LOCATION RATE LIBRARY'!$D$11:$N$11,MATCH(City,'08 LOCATION RATE LIBRARY'!$D$4:$N$4,0))) -> 185 | H11: =City -> Lahore | I11: 2024-07-24 | J11: =IF(ISNUMBER('16 VENDOR ENQUIRY (RFQ)'!H12),"Vendor quote","OLD SOURCE") -> OLD SOURCE | K11: SRC-30 | L11: Quadrangle GRN RCP-1847, 24-Jul-2024 – FosPak SP 568 @ Rs185/kg. >24 months old – escalate / re-quote. | M11: =IF(NOT(ISNUMBER(E11)),0,IF(OR(J11="OLD SOURCE",J11="UNDATED SOURCE"),2,1)) -> 2 | N11: =IF(ISNUMBER('16 VENDOR ENQUIRY (RFQ)'!H12),'16 VENDOR ENQUIRY (RFQ)'!H12,185) -> 185 | O11: City-specific
A12: MAT-WTR | B12: Water for mixing & curing | C12: Clean potable water | D12: litre | E12: =IF(INDEX('08 LOCATION RATE LIBRARY'!$D$12:$N$12,MATCH(City,'08 LOCATION RATE LIBRARY'!$D$4:$N$4,0))="","",INDEX('08 LOCATION RATE LIBRARY'!$D$12:$N$12,MATCH(City,'08 LOCATION RATE LIBRARY'!$D$4:$N$4,0))) -> 0.686 | H12: =City -> Lahore | I12: 2026-07-01 | J12: =IF(ISNUMBER('16 VENDOR ENQUIRY (RFQ)'!H19),"Vendor quote","ASSUMED") -> ASSUMED | K12: SRC-38 | L12: PROXY: Karachi KWSC commercial tanker Rs3,120 per 1,000 gal (4,546 L). No Lahore tariff found; nil if site bore water. | M12: =IF(NOT(ISNUMBER(E12)),0,IF(OR(J12="OLD SOURCE",J12="UNDATED SOURCE"),2,1)) -> 1 | N12: =IF(ISNUMBER('16 VENDOR ENQUIRY (RFQ)'!H19),'16 VENDOR ENQUIRY (RFQ)'!H19,0.686) -> 0.686 | O12: City-specific
A13: MAT-STL-G60 | B13: Steel reinforcement Grade 60 | C13: Deformed bars ASTM A615 Gr.60, any approved mill | D13: kg | E13: =IF(INDEX('08 LOCATION RATE LIBRARY'!$D$13:$N$13,MATCH(City,'08 LOCATION RATE LIBRARY'!$D$4:$N$4,0))="","",INDEX('08 LOCATION RATE LIBRARY'!$D$13:$N$13,MATCH(City,'08 LOCATION RATE LIBRARY'!$D$4:$N$4,0))) -> 242 | F13: 254 | G13: 285 | H13: =City -> Lahore | I13: 2026-08-30 | J13: GRN verified | K13: SRC-30 | L13: Phoenix GRN RCP-312, 30-Aug-2026 – M/S Hamza Steel, G-60 #3–#8 @ Rs242,000/ton. | M13: =IF(NOT(ISNUMBER(E13)),0,IF(OR(J13="OLD SOURCE",J13="UNDATED SOURCE"),2,1)) -> 1 | N13: 242 | O13: National list
A14: MAT-BWIRE | B14: Binding wire | C14: GI / black annealed binding wire | D14: kg | E14: =IF(INDEX('08 LOCATION RATE LIBRARY'!$D$14:$N$14,MATCH(City,'08 LOCATION RATE LIBRARY'!$D$4:$N$4,0))="","",INDEX('08 LOCATION RATE LIBRARY'!$D$14:$N$14,MATCH(City,'08 LOCATION RATE LIBRARY'!$D$4:$N$4,0))) -> 345 | H14: =City -> Lahore | I14: 2026-08-19 | J14: GRN verified | K14: SRC-30 | L14: Phoenix GRN RCP-308, 19-Aug-2026 – Ibrahim Nizami Steel Wire, 20 SWG. | M14: =IF(NOT(ISNUMBER(E14)),0,IF(OR(J14="OLD SOURCE",J14="UNDATED SOURCE"),2,1)) -> 1 | N14: 345 | O14: City-specific
A15: MAT-BRK-A | B15: Brick – A class (Awwal) | C15: Burnt clay 9"×4.5"×3" | D15: Nos | E15: =IF(INDEX('08 LOCATION RATE LIBRARY'!$D$15:$N$15,MATCH(City,'08 LOCATION RATE LIBRARY'!$D$4:$N$4,0))="","",INDEX('08 LOCATION RATE LIBRARY'!$D$15:$N$15,MATCH(City,'08 LOCATION RATE LIBRARY'!$D$4:$N$4,0))) -> 17.5 | F15: 14 | G15: 21.5 | H15: =City -> Lahore | I15: 2026-09-26 | J15: Market indication | K15: SRC-42 | L15: Rev07: 18 -> 17.5 (Rs 16,000–19,000 per 1,000, Sep-2026). Same as dashboard BRK-1. | M15: =IF(NOT(ISNUMBER(E15)),0,IF(OR(J15="OLD SOURCE",J15="UNDATED SOURCE"),2,1)) -> 1 | N15: 17.5 | O15: City-specific
A16: MAT-BLK-8H | B16: Concrete block 8" hollow | C16: 16"x8"x8" hollow, 1200 PSI class | D16: Nos | E16: =IF(INDEX('08 LOCATION RATE LIBRARY'!$D$16:$N$16,MATCH(City,'08 LOCATION RATE LIBRARY'!$D$4:$N$4,0))="","",INDEX('08 LOCATION RATE LIBRARY'!$D$16:$N$16,MATCH(City,'08 LOCATION RATE LIBRARY'!$D$4:$N$4,0))) -> 210 | F16: 120 | G16: 175 | H16: =City -> Lahore | I16: 2026-09-07 | J16: GRN verified | K16: SRC-30 | L16: Phoenix GRN RCP-317, 07-Sep-2026 – Azmat Sons, 8"x8"x16" hollow. | M16: =IF(NOT(ISNUMBER(E16)),0,IF(OR(J16="OLD SOURCE",J16="UNDATED SOURCE"),2,1)) -> 1 | N16: 210 | O16: Hubs (LHR/KHI/ISB/RWP)
A17: MAT-BLK-6H | B17: Concrete block 6" hollow | C17: 16"x6"x8" | D17: Nos | E17: =IF(INDEX('08 LOCATION RATE LIBRARY'!$D$17:$N$17,MATCH(City,'08 LOCATION RATE LIBRARY'!$D$4:$N$4,0))="","",INDEX('08 LOCATION RATE LIBRARY'!$D$17:$N$17,MATCH(City,'08 LOCATION RATE LIBRARY'!$D$4:$N$4,0))) -> 165 | F17: 95 | G17: 125 | H17: =City -> Lahore | I17: 2026-09-05 | J17: Vendor quote | K17: SRC-43 | L17: Rev07: 110 (national ex-factory midpoint, Jun-2026) -> 165 Zarea Lahore quotation 05-Sep-2026. Same as dashboard BLK-H6. | M17: =IF(NOT(ISNUMBER(E17)),0,IF(OR(J17="OLD SOURCE",J17="UNDATED SOURCE"),2,1)) -> 1 | N17: 165 | O17: Hubs (LHR/KHI/ISB/RWP)
A18: MAT-BLK-4S | B18: Concrete block 4" solid | C18: 12"x4"x8" partition block | D18: Nos | E18: =IF(INDEX('08 LOCATION RATE LIBRARY'!$D$18:$N$18,MATCH(City,'08 LOCATION RATE LIBRARY'!$D$4:$N$4,0))="","",INDEX('08 LOCATION RATE LIBRARY'!$D$18:$N$18,MATCH(City,'08 LOCATION RATE LIBRARY'!$D$4:$N$4,0))) -> 140 | F18: 55 | G18: 65 | H18: =City -> Lahore | I18: 2026-09-05 | J18: Vendor quote | K18: SRC-43 | L18: Rev07: 103 (Phoenix GRN RCP-213, Oct-2025, >11 months) -> 140 Zarea Lahore quotation 05-Sep-2026. Same as dashboard BLK-S4. | M18: =IF(NOT(ISNUMBER(E18)),0,IF(OR(J18="OLD SOURCE",J18="UNDATED SOURCE"),2,1)) -> 1 | N18: 140 | O18: Hubs (LHR/KHI/ISB/RWP)
A19: MAT-PLY-18 | B19: Shuttering plywood 3/4" 8'x4' | C19: 3/4" plywood sheet 32 Sft | D19: sheet | E19: =IF(INDEX('08 LOCATION RATE LIBRARY'!$D$19:$N$19,MATCH(City,'08 LOCATION RATE LIBRARY'!$D$4:$N$4,0))="","",INDEX('08 LOCATION RATE LIBRARY'!$D$19:$N$19,MATCH(City,'08 LOCATION RATE LIBRARY'!$D$4:$N$4,0))) -> 5500 | F19: 4500 | G19: 6500 | H19: =City -> Lahore | I19: 2026-09-27 | J19: Market indication | K19: SRC-10 | L19: Midpoint of general plywood band; film-faced shuttering ply may differ – confirm. | M19: =IF(NOT(ISNUMBER(E19)),0,IF(OR(J19="OLD SOURCE",J19="UNDATED SOURCE"),2,1)) -> 1 | N19: 5500 | O19: National list
A20: MAT-TIM-CHR | B20: Timber – Chir (battens, bearers, yokes) | C20: Sawn chir wood | D20: cft | E20: =IF(INDEX('08 LOCATION RATE LIBRARY'!$D$20:$N$20,MATCH(City,'08 LOCATION RATE LIBRARY'!$D$4:$N$4,0))="","",INDEX('08 LOCATION RATE LIBRARY'!$D$20:$N$20,MATCH(City,'08 LOCATION RATE LIBRARY'!$D$4:$N$4,0))) -> 3680 | H20: =City -> Lahore | I20: 2026-06-10 | J20: GRN verified | K20: SRC-30 | L20: Phoenix GRN RCP-277, 10-Jun-2026 – Taha International, wooden planks 1.5"x9"x10' @ Rs3,450 each ÷ 0.9375 cft = Rs3,680/cft (species not stated). | M20: =IF(NOT(ISNUMBER(E20)),0,IF(OR(J20="OLD SOURCE",J20="UNDATED SOURCE"),2,1)) -> 1 | N20: 3680 | O20: City-specific
A21: MAT-NAIL | B21: Nails / tie wire for formwork | C21: Assorted | D21: kg | E21: =IF(INDEX('08 LOCATION RATE LIBRARY'!$D$21:$N$21,MATCH(City,'08 LOCATION RATE LIBRARY'!$D$4:$N$4,0))="","",INDEX('08 LOCATION RATE LIBRARY'!$D$21:$N$21,MATCH(City,'08 LOCATION RATE LIBRARY'!$D$4:$N$4,0))) -> 715 | H21: =City -> Lahore | I21: 2026-05-21 | J21: GRN verified | K21: SRC-30 | L21: Phoenix GRN RCP-273, 21-May-2026 – Taha International, MS nails 2". | M21: =IF(NOT(ISNUMBER(E21)),0,IF(OR(J21="OLD SOURCE",J21="UNDATED SOURCE"),2,1)) -> 1 | N21: 715 | O21: City-specific
A22: MAT-SHOIL | B22: Shuttering / release oil | C22: Mould release agent | D22: litre | E22: =IF(INDEX('08 LOCATION RATE LIBRARY'!$D$22:$N$22,MATCH(City,'08 LOCATION RATE LIBRARY'!$D$4:$N$4,0))="","",INDEX('08 LOCATION RATE LIBRARY'!$D$22:$N$22,MATCH(City,'08 LOCATION RATE LIBRARY'!$D$4:$N$4,0))) -> 400 | H22: =City -> Lahore | I22: 2026-09-27 | J22: =IF(ISNUMBER('16 VENDOR ENQUIRY (RFQ)'!H16),"Vendor quote","ASSUMED") -> ASSUMED | K22: SRC-49 | L22: ASSUMPTION — no dated source (2026-09-27, assumed on request): same as the dashboard's MOULD assumption – set near diesel 392/Ltr (Phoenix GRN RCP-311, 28-Aug-2026). Replace with a quotation in 16 RFQ col H. | M22: =IF(NOT(ISNUMBER(E22)),0,IF(OR(J22="OLD SOURCE",J22="UNDATED SOURCE"),2,1)) -> 1 | N22: =IF(ISNUMBER('16 VENDOR ENQUIRY (RFQ)'!H16),'16 VENDOR ENQUIRY (RFQ)'!H16,400) -> 400 | O22: City-specific
A23: MAT-MEM-APP | B23: APP modified bitumen membrane 4-thick (torch-on) | C23: Polyester reinforced, roll | D23: Sft | E23: =IF(INDEX('08 LOCATION RATE LIBRARY'!$D$23:$N$23,MATCH(City,'08 LOCATION RATE LIBRARY'!$D$4:$N$4,0))="","",INDEX('08 LOCATION RATE LIBRARY'!$D$23:$N$23,MATCH(City,'08 LOCATION RATE LIBRARY'!$D$4:$N$4,0))) -> 98 | H23: =City -> Lahore | I23: 2025-08-19 | J23: GRN verified | K23: SRC-30 | L23: Quadrangle GRN RCP-2689, 19-Aug-2025 – Grace Chemicals, 4-thick membrane WITH primer coat, per Sft. | M23: =IF(NOT(ISNUMBER(E23)),0,IF(OR(J23="OLD SOURCE",J23="UNDATED SOURCE"),2,1)) -> 1 | N23: 98 | O23: City-specific
A24: MAT-BIT-PRM | B24: Bitumen primer | C24: Solvent/oil-based bituminous primer | D24: litre | E24: =IF(INDEX('08 LOCATION RATE LIBRARY'!$D$24:$N$24,MATCH(City,'08 LOCATION RATE LIBRARY'!$D$4:$N$4,0))="","",INDEX('08 LOCATION RATE LIBRARY'!$D$24:$N$24,MATCH(City,'08 LOCATION RATE LIBRARY'!$D$4:$N$4,0))) -> 87.5 | H24: =City -> Lahore | I24: 2021-12-23 | J24: =IF(ISNUMBER('16 VENDOR ENQUIRY (RFQ)'!H13),"Vendor quote","OLD SOURCE") -> OLD SOURCE | K24: SRC-30 | L24: Quadrangle GRN RCP-192 – Roof Line. Not used: membrane GRN rate includes primer coat (FIN-WPF-001 primer set to nil). | M24: =IF(NOT(ISNUMBER(E24)),0,IF(OR(J24="OLD SOURCE",J24="UNDATED SOURCE"),2,1)) -> 2 | N24: =IF(ISNUMBER('16 VENDOR ENQUIRY (RFQ)'!H13),'16 VENDOR ENQUIRY (RFQ)'!H13,87.5) -> 87.5 | O24: City-specific
A25: MAT-BIT-HOT | B25: Bitumen 80/100 (hot applied) | C25: Penetration grade bitumen | D25: kg | E25: =IF(INDEX('08 LOCATION RATE LIBRARY'!$D$25:$N$25,MATCH(City,'08 LOCATION RATE LIBRARY'!$D$4:$N$4,0))="","",INDEX('08 LOCATION RATE LIBRARY'!$D$25:$N$25,MATCH(City,'08 LOCATION RATE LIBRARY'!$D$4:$N$4,0))) -> 197.5 | H25: =City -> Lahore | I25: 2026-09-26 | J25: Market indication | K25: SRC-33 | L25: Dashboard civil review: 60/70 bitumen Rs185,000–210,000/ton (web 26-Sep-2026). | M25: =IF(NOT(ISNUMBER(E25)),0,IF(OR(J25="OLD SOURCE",J25="UNDATED SOURCE"),2,1)) -> 1 | N25: 197.5 | O25: City-specific
A26: MAT-LPG | B26: LPG for torching | C26: Gas cylinder, per kg | D26: kg | E26: =IF(INDEX('08 LOCATION RATE LIBRARY'!$D$26:$N$26,MATCH(City,'08 LOCATION RATE LIBRARY'!$D$4:$N$4,0))="","",INDEX('08 LOCATION RATE LIBRARY'!$D$26:$N$26,MATCH(City,'08 LOCATION RATE LIBRARY'!$D$4:$N$4,0))) -> 258.65 | H26: =City -> Lahore | I26: 2026-09-01 | J26: Govt notified | K26: SRC-34 | L26: OGRA LPG price September 2026. | M26: =IF(NOT(ISNUMBER(E26)),0,IF(OR(J26="OLD SOURCE",J26="UNDATED SOURCE"),2,1)) -> 1 | N26: 258.65 | O26: City-specific
A27: MAT-CWP | B27: Cementitious waterproofing (2-component) | C27: e.g. Sika/Ultra/Fosroc brushable slurry | D27: Sft | E27: =IF(INDEX('08 LOCATION RATE LIBRARY'!$D$27:$N$27,MATCH(City,'08 LOCATION RATE LIBRARY'!$D$4:$N$4,0))="","",INDEX('08 LOCATION RATE LIBRARY'!$D$27:$N$27,MATCH(City,'08 LOCATION RATE LIBRARY'!$D$4:$N$4,0))) -> 47 | H27: =City -> Lahore | I27: 2024-03-13 | J27: =IF(ISNUMBER('16 VENDOR ENQUIRY (RFQ)'!H14),"Vendor quote","OLD SOURCE") -> OLD SOURCE | K27: SRC-30 | L27: Quadrangle GRN RCP-1567 – Fawchem, Sika Seal 105 cementitious coating per Sft. >24 months – re-quote. | M27: =IF(NOT(ISNUMBER(E27)),0,IF(OR(J27="OLD SOURCE",J27="UNDATED SOURCE"),2,1)) -> 2 | N27: =IF(ISNUMBER('16 VENDOR ENQUIRY (RFQ)'!H14),'16 VENDOR ENQUIRY (RFQ)'!H14,47) -> 47 | O27: City-specific
A28: MAT-TIL-POR | B28: Porcelain tile 24"x24" local A-grade | C28: Local brand (Master/Stile/Time) – PC rate, depends on selected series | D28: Sft | E28: =IF(INDEX('08 LOCATION RATE LIBRARY'!$D$28:$N$28,MATCH(City,'08 LOCATION RATE LIBRARY'!$D$4:$N$4,0))="","",INDEX('08 LOCATION RATE LIBRARY'!$D$28:$N$28,MATCH(City,'08 LOCATION RATE LIBRARY'!$D$4:$N$4,0))) -> 209 | F28: 90 | G28: 350 | H28: =City -> Lahore | I28: 2026-09-27 | J28: Market indication | K28: SRC-14; SRC-13 | L28: Converted from SRC-14; replace with selected product rate (PC). | M28: =IF(NOT(ISNUMBER(E28)),0,IF(OR(J28="OLD SOURCE",J28="UNDATED SOURCE"),2,1)) -> 1 | N28: 209 | O28: National list
A29: MAT-TIL-CER | B29: Ceramic tile local (floor/wall) | C29: Local brand – PC rate | D29: Sft | E29: =IF(INDEX('08 LOCATION RATE LIBRARY'!$D$29:$N$29,MATCH(City,'08 LOCATION RATE LIBRARY'!$D$4:$N$4,0))="","",INDEX('08 LOCATION RATE LIBRARY'!$D$29:$N$29,MATCH(City,'08 LOCATION RATE LIBRARY'!$D$4:$N$4,0))) -> 125 | F29: 90 | G29: 350 | H29: =City -> Lahore | I29: 2026-09-27 | J29: Market indication | K29: SRC-14; SRC-13 | L29: Converted from SRC-14; replace with selected product rate (PC). | M29: =IF(NOT(ISNUMBER(E29)),0,IF(OR(J29="OLD SOURCE",J29="UNDATED SOURCE"),2,1)) -> 1 | N29: 125 | O29: National list
A30: MAT-TADH | B30: Tile adhesive 20 kg bag | C30: Cementitious C1 (Bestway / Stile Bond) | D30: bag | E30: =IF(INDEX('08 LOCATION RATE LIBRARY'!$D$30:$N$30,MATCH(City,'08 LOCATION RATE LIBRARY'!$D$4:$N$4,0))="","",INDEX('08 LOCATION RATE LIBRARY'!$D$30:$N$30,MATCH(City,'08 LOCATION RATE LIBRARY'!$D$4:$N$4,0))) -> 650 | F30: 600 | G30: 780 | H30: =City -> Lahore | I30: 2026-09-27 | J30: Market indication | K30: SRC-15 | L30: Upper end of Bestway band; Stile Bond also Rs650. | M30: =IF(NOT(ISNUMBER(E30)),0,IF(OR(J30="OLD SOURCE",J30="UNDATED SOURCE"),2,1)) -> 1 | N30: 650 | O30: National list
A31: MAT-GRT | B31: Tile grout (cementitious) | C31: Sanded/unsanded, colour to match | D31: kg | E31: =IF(INDEX('08 LOCATION RATE LIBRARY'!$D$31:$N$31,MATCH(City,'08 LOCATION RATE LIBRARY'!$D$4:$N$4,0))="","",INDEX('08 LOCATION RATE LIBRARY'!$D$31:$N$31,MATCH(City,'08 LOCATION RATE LIBRARY'!$D$4:$N$4,0))) -> 300 | H31: =City -> Lahore | I31: 2025-05-14 | J31: GRN verified | K31: SRC-30 | L31: Quadrangle GRN RCP-2505, 14-May-2025 – Hassan Enterprises, Rs300 per pack; pack taken as 1 kg (ASSUMPTION – confirm pack size). | M31: =IF(NOT(ISNUMBER(E31)),0,IF(OR(J31="OLD SOURCE",J31="UNDATED SOURCE"),2,1)) -> 1 | N31: 300 | O31: City-specific
A32: MAT-MBL-ZW | B32: Marble Ziarat White 3/4" floor | C32: Local, polished-in-situ | D32: Sft | E32: =IF(INDEX('08 LOCATION RATE LIBRARY'!$D$32:$N$32,MATCH(City,'08 LOCATION RATE LIBRARY'!$D$4:$N$4,0))="","",INDEX('08 LOCATION RATE LIBRARY'!$D$32:$N$32,MATCH(City,'08 LOCATION RATE LIBRARY'!$D$4:$N$4,0))) -> 337.5 | F32: 320 | G32: 360 | H32: =City -> Lahore | I32: 2026-09-10 | J32: Market indication | K32: SRC-37 | L32: ICONS 10-Sep-2026: Ziarat White floor marble Rs330–345/Sft (midpoint). | M32: =IF(NOT(ISNUMBER(E32)),0,IF(OR(J32="OLD SOURCE",J32="UNDATED SOURCE"),2,1)) -> 1 | N32: 337.5 | O32: City-specific
A33: MAT-MBL-TV | B33: Marble Tavera 3/4" floor | C33: Local | D33: Sft | E33: =IF(INDEX('08 LOCATION RATE LIBRARY'!$D$33:$N$33,MATCH(City,'08 LOCATION RATE LIBRARY'!$D$4:$N$4,0))="","",INDEX('08 LOCATION RATE LIBRARY'!$D$33:$N$33,MATCH(City,'08 LOCATION RATE LIBRARY'!$D$4:$N$4,0))) -> 92.5 | F33: 90 | G33: 110 | H33: =City -> Lahore | I33: 2026-09-10 | J33: Market indication | K33: SRC-37 | L33: ICONS 10-Sep-2026: Tavera floor marble Rs85–100/Sft (midpoint). | M33: =IF(NOT(ISNUMBER(E33)),0,IF(OR(J33="OLD SOURCE",J33="UNDATED SOURCE"),2,1)) -> 1 | N33: 92.5 | O33: City-specific
A34: MAT-GYP-12 | B34: Gypsum board 1/2" standard 4'x8' | C34: Tapered edge, 32 Sft/sheet | D34: sheet | E34: =IF(INDEX('08 LOCATION RATE LIBRARY'!$D$34:$N$34,MATCH(City,'08 LOCATION RATE LIBRARY'!$D$4:$N$4,0))="","",INDEX('08 LOCATION RATE LIBRARY'!$D$34:$N$34,MATCH(City,'08 LOCATION RATE LIBRARY'!$D$4:$N$4,0))) -> 3550 | H34: =City -> Lahore | I34: 2026-09-27 | J34: =IF(ISNUMBER('16 VENDOR ENQUIRY (RFQ)'!H8),"Vendor quote","ASSUMED") -> ASSUMED | K34: SRC-49 | L34: ASSUMPTION — no dated source (2026-09-27, assumed on request): web B2B listing 27-Sep-2026 (tradekey.com, undated): Pakistan gypsum board 3,550–3,600 per sheet; low end. Replace with a quotation in 16 RFQ col H. | M34: =IF(NOT(ISNUMBER(E34)),0,IF(OR(J34="OLD SOURCE",J34="UNDATED SOURCE"),2,1)) -> 1 | N34: =IF(ISNUMBER('16 VENDOR ENQUIRY (RFQ)'!H8),'16 VENDOR ENQUIRY (RFQ)'!H8,3550) -> 3550 | O34: City-specific
A35: MAT-GYP-MR | B35: Gypsum board 1/2" moisture-resistant 4'x8' | C35: MR (green) board | D35: sheet | E35: =IF(INDEX('08 LOCATION RATE LIBRARY'!$D$35:$N$35,MATCH(City,'08 LOCATION RATE LIBRARY'!$D$4:$N$4,0))="","",INDEX('08 LOCATION RATE LIBRARY'!$D$35:$N$35,MATCH(City,'08 LOCATION RATE LIBRARY'!$D$4:$N$4,0))) -> 4600 | H35: =City -> Lahore | I35: 2026-09-27 | J35: =IF(ISNUMBER('16 VENDOR ENQUIRY (RFQ)'!H9),"Vendor quote","ASSUMED") -> ASSUMED | K35: SRC-49 | L35: ASSUMPTION — no dated source (2026-09-27, assumed on request): standard board 3,550 + ≈30% moisture-resistant premium (Claude estimate for Lahore, Sep-2026). Replace with a quotation in 16 RFQ col H. | M35: =IF(NOT(ISNUMBER(E35)),0,IF(OR(J35="OLD SOURCE",J35="UNDATED SOURCE"),2,1)) -> 1 | N35: =IF(ISNUMBER('16 VENDOR ENQUIRY (RFQ)'!H9),'16 VENDOR ENQUIRY (RFQ)'!H9,4600) -> 4600 | O35: City-specific
A36: MAT-GI-MC | B36: GI main channel | C36: Primary carrying channel | D36: Rft | E36: =IF(INDEX('08 LOCATION RATE LIBRARY'!$D$36:$N$36,MATCH(City,'08 LOCATION RATE LIBRARY'!$D$4:$N$4,0))="","",INDEX('08 LOCATION RATE LIBRARY'!$D$36:$N$36,MATCH(City,'08 LOCATION RATE LIBRARY'!$D$4:$N$4,0))) -> 60 | H36: =City -> Lahore | I36: 2026-09-27 | J36: =IF(ISNUMBER('16 VENDOR ENQUIRY (RFQ)'!H6),"Vendor quote","ASSUMED") -> ASSUMED | K36: SRC-49 | L36: ASSUMPTION — no dated source (2026-09-27, assumed on request): calibrated so board + frame + accessories ≈ the Punjab MRS 2026 Ch.9 item 49(ii) gypsum-ceiling system material (176.10/Sft). Replace with a quotation in 16 RFQ col H. | M36: =IF(NOT(ISNUMBER(E36)),0,IF(OR(J36="OLD SOURCE",J36="UNDATED SOURCE"),2,1)) -> 1 | N36: =IF(ISNUMBER('16 VENDOR ENQUIRY (RFQ)'!H6),'16 VENDOR ENQUIRY (RFQ)'!H6,60) -> 60 | O36: City-specific
A37: MAT-GI-FC | B37: GI furring channel | C37: Secondary furring | D37: Rft | E37: =IF(INDEX('08 LOCATION RATE LIBRARY'!$D$37:$N$37,MATCH(City,'08 LOCATION RATE LIBRARY'!$D$4:$N$4,0))="","",INDEX('08 LOCATION RATE LIBRARY'!$D$37:$N$37,MATCH(City,'08 LOCATION RATE LIBRARY'!$D$4:$N$4,0))) -> 45 | H37: =City -> Lahore | I37: 2026-09-27 | J37: =IF(ISNUMBER('16 VENDOR ENQUIRY (RFQ)'!H5),"Vendor quote","ASSUMED") -> ASSUMED | K37: SRC-49 | L37: ASSUMPTION — no dated source (2026-09-27, assumed on request): calibrated so board + frame + accessories ≈ the Punjab MRS 2026 Ch.9 item 49(ii) gypsum-ceiling system material (176.10/Sft). Replace with a quotation in 16 RFQ col H. | M37: =IF(NOT(ISNUMBER(E37)),0,IF(OR(J37="OLD SOURCE",J37="UNDATED SOURCE"),2,1)) -> 1 | N37: =IF(ISNUMBER('16 VENDOR ENQUIRY (RFQ)'!H5),'16 VENDOR ENQUIRY (RFQ)'!H5,45) -> 45 | O37: City-specific
A38: MAT-GI-WA | B38: GI wall angle | C38: Perimeter angle | D38: Rft | E38: =IF(INDEX('08 LOCATION RATE LIBRARY'!$D$38:$N$38,MATCH(City,'08 LOCATION RATE LIBRARY'!$D$4:$N$4,0))="","",INDEX('08 LOCATION RATE LIBRARY'!$D$38:$N$38,MATCH(City,'08 LOCATION RATE LIBRARY'!$D$4:$N$4,0))) -> 35 | H38: =City -> Lahore | I38: 2026-09-27 | J38: =IF(ISNUMBER('16 VENDOR ENQUIRY (RFQ)'!H7),"Vendor quote","ASSUMED") -> ASSUMED | K38: SRC-49 | L38: ASSUMPTION — no dated source (2026-09-27, assumed on request): calibrated so board + frame + accessories ≈ the Punjab MRS 2026 Ch.9 item 49(ii) gypsum-ceiling system material (176.10/Sft). Replace with a quotation in 16 RFQ col H. | M38: =IF(NOT(ISNUMBER(E38)),0,IF(OR(J38="OLD SOURCE",J38="UNDATED SOURCE"),2,1)) -> 1 | N38: =IF(ISNUMBER('16 VENDOR ENQUIRY (RFQ)'!H7),'16 VENDOR ENQUIRY (RFQ)'!H7,35) -> 35 | O38: City-specific
A39: MAT-HGR | B39: Hanger set (rod/wire, anchor, clip) | C39: Soffit fixing | D39: Nos | E39: =IF(INDEX('08 LOCATION RATE LIBRARY'!$D$39:$N$39,MATCH(City,'08 LOCATION RATE LIBRARY'!$D$4:$N$4,0))="","",INDEX('08 LOCATION RATE LIBRARY'!$D$39:$N$39,MATCH(City,'08 LOCATION RATE LIBRARY'!$D$4:$N$4,0))) -> 217.76 | H39: =City -> Lahore | I39: 2025-08-06 | J39: GRN verified | K39: SRC-30 | L39: As MAT-DHNG (rod + anchor); clip excluded. | M39: =IF(NOT(ISNUMBER(E39)),0,IF(OR(J39="OLD SOURCE",J39="UNDATED SOURCE"),2,1)) -> 1 | N39: 217.76 | O39: City-specific
A40: MAT-SCRW | B40: Drywall screws | C40: Self-tapping | D40: Nos | E40: =IF(INDEX('08 LOCATION RATE LIBRARY'!$D$40:$N$40,MATCH(City,'08 LOCATION RATE LIBRARY'!$D$4:$N$4,0))="","",INDEX('08 LOCATION RATE LIBRARY'!$D$40:$N$40,MATCH(City,'08 LOCATION RATE LIBRARY'!$D$4:$N$4,0))) -> 2.5 | H40: =City -> Lahore | I40: 2026-05-15 | J40: GRN verified | K40: SRC-30 | L40: Phoenix GRN RCP-271 – Rehman Ali, self-tapping screw 1-1/2". | M40: =IF(NOT(ISNUMBER(E40)),0,IF(OR(J40="OLD SOURCE",J40="UNDATED SOURCE"),2,1)) -> 1 | N40: 2.5 | O40: City-specific
A41: MAT-JTAPE | B41: Joint tape | C41: Paper/mesh tape | D41: Rft | E41: =IF(INDEX('08 LOCATION RATE LIBRARY'!$D$41:$N$41,MATCH(City,'08 LOCATION RATE LIBRARY'!$D$4:$N$4,0))="","",INDEX('08 LOCATION RATE LIBRARY'!$D$41:$N$41,MATCH(City,'08 LOCATION RATE LIBRARY'!$D$4:$N$4,0))) -> 3 | H41: =City -> Lahore | I41: 2026-09-27 | J41: =IF(ISNUMBER('16 VENDOR ENQUIRY (RFQ)'!H11),"Vendor quote","ASSUMED") -> ASSUMED | K41: SRC-49 | L41: ASSUMPTION — no dated source (2026-09-27, assumed on request): calibrated so board + frame + accessories ≈ the Punjab MRS 2026 Ch.9 item 49(ii) gypsum-ceiling system material (176.10/Sft). Replace with a quotation in 16 RFQ col H. | M41: =IF(NOT(ISNUMBER(E41)),0,IF(OR(J41="OLD SOURCE",J41="UNDATED SOURCE"),2,1)) -> 1 | N41: =IF(ISNUMBER('16 VENDOR ENQUIRY (RFQ)'!H11),'16 VENDOR ENQUIRY (RFQ)'!H11,3) -> 3 | O41: City-specific
A42: MAT-JCMP | B42: Jointing compound | C42: Ready-mix / powder | D42: kg | E42: =IF(INDEX('08 LOCATION RATE LIBRARY'!$D$42:$N$42,MATCH(City,'08 LOCATION RATE LIBRARY'!$D$4:$N$4,0))="","",INDEX('08 LOCATION RATE LIBRARY'!$D$42:$N$42,MATCH(City,'08 LOCATION RATE LIBRARY'!$D$4:$N$4,0))) -> 120 | H42: =City -> Lahore | I42: 2026-09-27 | J42: =IF(ISNUMBER('16 VENDOR ENQUIRY (RFQ)'!H15),"Vendor quote","ASSUMED") -> ASSUMED | K42: SRC-49 | L42: ASSUMPTION — no dated source (2026-09-27, assumed on request): calibrated so board + frame + accessories ≈ the Punjab MRS 2026 Ch.9 item 49(ii) gypsum-ceiling system material (176.10/Sft). Replace with a quotation in 16 RFQ col H. | M42: =IF(NOT(ISNUMBER(E42)),0,IF(OR(J42="OLD SOURCE",J42="UNDATED SOURCE"),2,1)) -> 1 | N42: =IF(ISNUMBER('16 VENDOR ENQUIRY (RFQ)'!H15),'16 VENDOR ENQUIRY (RFQ)'!H15,120) -> 120 | O42: City-specific
A43: MAT-PNT-PE | B43: Plastic emulsion (interior) | C43: Master/Diamond/Brighto plastic emulsion, 1 gallon | D43: gallon | E43: =IF(INDEX('08 LOCATION RATE LIBRARY'!$D$43:$N$43,MATCH(City,'08 LOCATION RATE LIBRARY'!$D$4:$N$4,0))="","",INDEX('08 LOCATION RATE LIBRARY'!$D$43:$N$43,MATCH(City,'08 LOCATION RATE LIBRARY'!$D$4:$N$4,0))) -> 2850 | F43: 2200 | G43: 3500 | H43: =City -> Lahore | I43: 2026-09-27 | J43: Market indication | K43: SRC-21 | L43: Midpoint of Master Paints band. | M43: =IF(NOT(ISNUMBER(E43)),0,IF(OR(J43="OLD SOURCE",J43="UNDATED SOURCE"),2,1)) -> 1 | N43: 2850 | O43: National list
A44: MAT-PNT-WS | B44: Weather shield (exterior acrylic) | C44: Premium exterior, 1 gallon | D44: gallon | E44: =IF(INDEX('08 LOCATION RATE LIBRARY'!$D$44:$N$44,MATCH(City,'08 LOCATION RATE LIBRARY'!$D$4:$N$4,0))="","",INDEX('08 LOCATION RATE LIBRARY'!$D$44:$N$44,MATCH(City,'08 LOCATION RATE LIBRARY'!$D$4:$N$4,0))) -> 5987.8 | H44: =City -> Lahore | I44: 2026-09-27 | J44: Market indication | K44: SRC-36 | L44: Berger VIP Weathercoat Rs1,645 per 1 L (official Berger shop, Punjab region) × 3.64 L. Bulk 16 L packs are usually cheaper per litre. | M44: =IF(NOT(ISNUMBER(E44)),0,IF(OR(J44="OLD SOURCE",J44="UNDATED SOURCE"),2,1)) -> 1 | N44: 5987.8 | O44: City-specific
A45: MAT-PNT-PRM | B45: Wall sealer / primer | C45: Alkali-resistant primer, 1 gallon | D45: gallon | E45: =IF(INDEX('08 LOCATION RATE LIBRARY'!$D$45:$N$45,MATCH(City,'08 LOCATION RATE LIBRARY'!$D$4:$N$4,0))="","",INDEX('08 LOCATION RATE LIBRARY'!$D$45:$N$45,MATCH(City,'08 LOCATION RATE LIBRARY'!$D$4:$N$4,0))) -> 1011.11 | H45: =City -> Lahore | I45: 2025-07-23 | J45: GRN verified | K45: SRC-30 | L45: Quadrangle GRN RCP-2630 – Berger, water-based primer 18 L bucket Rs5,000 → Rs277.78/L × 3.64 L gallon. | M45: =IF(NOT(ISNUMBER(E45)),0,IF(OR(J45="OLD SOURCE",J45="UNDATED SOURCE"),2,1)) -> 1 | N45: 1011.11 | O45: City-specific
